Workbook

Sheet Players
A1: Player | B1: Team 26/27 | C1: Pos | D1: Pos 25/26 | E1: Price 26/27 | F1: Draftable | G1: Played 25/26 | H1: Age | I1: Status | J1: News | K1: Chance next GW % | L1: Opta ID | M1: FPL ID | N1: Pens order | O1: Corners/IFK order | P1: Direct FK order | Q1: Mins | R1: Apps | S1: Starts | T1: 90s | U1: Mins per app | V1: FPL points | W1: FPL pts/90 | X1: Goals | Y1: Assists (FPL) | Z1: Assists (Opta) | AA1: Clean sheets | AB1: Goals conceded | AC1: Bonus | AD1: Bonus (new rules) | AE1: Bonus change | AF1: BPS | AG1: BPS (new rules) | AH1: BPS change | AI1: Points (new rules) | AJ1: Bonus per point | AK1: Bonus per non-bonus point | AL1: DefCon actions | AM1: DefCon actions/90 | AN1: DefCon matches | AO1: DefCon points | AP1: DefCon hit rate | AQ1: DefCon rate at 10 | AR1: DefCon rate at 12 | AS1: Start rate | AT1: 60+ min rate | AU1: Blanks | AV1: Hauls | AW1: Points SD | AX1: Best GW | AY1: xG (Opta) | AZ1: xG (Understat) | BA1: xG (blend) | BB1: npxG (Understat) | BC1: xG/90 (Opta) | BD1: xG/90 (Understat) | BE1: xG/90 (blend) | BF1: xGOT | BG1: xGOT/90 | BH1: Placement ratio | BI1: Placement sample xG | BJ1: Adjusted xGOT | BK1: Adjusted xGOT/90 | BL1: Goals - xG | BM1: xGOT - xG | BN1: Goals - xGOT | BO1: xG model gap | BP1: Shots | BQ1: Shots on target | BR1: Big chances missed | BS1: Touches in box | BT1: Touches in box/90 | BU1: Pen goals | BV1: Headed goals | BW1: xA (Opta) | BX1: xA (Understat) | BY1: xA (blend) | BZ1: xA/90 (blend) | CA1: xGI (blend) | CB1: xGI/90 (blend) | CC1: Key passes | CD1: Big chances created | CE1: Chances created | CF1: Crosses (acc) | CG1: Through balls (acc) | CH1: Corners taken | CI1: xGChain | CJ1: xGBuildup | CK1: CBI | CL1: Recoveries | CM1: Tackles | CN1: Tackles won | CO1: Interceptions | CP1: Clearances | CQ1: Blocks | CR1: Duels won | CS1: Aerials won | CT1: Poss won att 3rd/90 | CU1: Errors -> goal | CV1: Errors -> shot | CW1: xGC (Opta) | CX1: xGC/90 | CY1: Saves | CZ1: Save % | DA1: Goals prevented | DB1: Pens saved | DC1: High claims | DD1: Punches | DE1: FotMob rating | DF1: Yellows | DG1: Reds | DH1: Fouls | DI1: Fouled | DJ1: Pens won | DK1: Pens conceded | DL1: Dribbles won | DM1: Dispossessed | DN1: Offsides | DO1: Selected by % | DP1: Solio season pts | DQ1: Solio H1 pts (GW1-19) | DR1: Solio naive x2 | DS1: Solio correction | DT1: Solio xMins (season) | DU1: Solio xMins (settled) | DV1: Solio xMins pattern | DW1: ADP | DX1: ADP (8-team only) | DY1: ADP (last 7 days) | DZ1: ADP move | EA1: Times drafted (recent) | EB1: ADP spread | EC1: ADP earliest | ED1: ADP latest | EE1: Times drafted | EF1: ADP reliable | EG1: Drafted % | EH1: Auto-pick % | EI1: FPL draft rank | EJ1: Mins per shot | EK1: Mins per touch in box | EL1: Mins per chance created | EM1: Mins per xG (blend) | EN1: Mins per xA (blend) | EO1: Mins per xGI (blend) | EP1: Mins per point
A2: Erling Haaland | B2: MCI | C2: FWD | D2: FWD | E2: 15.5 | F2: TRUE | G2: TRUE | H2: 26.1 | I2: a | L2: p223094 | M2: 411 | N2: 1 | Q2: 2953 | R2: 35 | S2: 34 | T2: 32.811 | U2: 84.4 | V2: 239 | W2: 7.284 | X2: 27 | Y2: 8 | Z2: 8 | AA2: 13 | AB2: 32 | AC2: 43 | AD2: 43 | AE2: 0 | AF2: 952 | AG2: 943 | AH2: -9 | AI2: 239 | AJ2: 0.18 | AK2: 0.219 | AL2: 104 | AM2: 3.17 | AN2: 0 | AO2: 0 | AP2: 0 | AQ2: 0 | AR2: 0 | AS2: 0.895 | AT2: 0.943 | AU2: 13 | AV2: 10 | AW2: 4.99 | AX2: 16 | AY2: 25.5 | AZ2: 28.795 | BA2: 27.148 | BB2: 25.751 | BC2: 0.777 | BD2: 0.878 | BE2: 0.827 | BF2: 23.3 | BG2: 0.71 | BH2: 0.958 | BI2: 105.51 | BJ2: 24.419 | BK2: 0.744 | BL2: -0.148 | BM2: -2.2 | BN2: 3.7 | BO2: -3.295 | BP2: 126 | BQ2: 59 | BR2: 30 | BS2: 213 | BT2: 6.492 | BU2: 3 | BV2: 3 | BW2: 2.67 | BX2: 5.508 | BY2: 4.089 | BZ2: 0.125 | CA2: 31.237 | CB2: 0.952 | CC2: 25 | CD2: 9 | CE2: 25 | CF2: 1 | CG2: 6 | CI2: 32.735 | CJ2: 5.164 | CK2: 48 | CL2: 41 | CM2: 15 | CN2: 9 | CO2: 5 | CP2: 42 | CQ2: 1 | CR2: 130 | CS2: 73 | CT2: 0.4 | CW2: 38.6 | CX2: 1.176 | CY2: 0 | DB2: 0 | DE2: 7.68 | DF2: 2 | DG2: 0 | DH2: 24 | DI2: 25 | DL2: 17 | DM2: 23 | DN2: 5 | DO2: 73.4 | DP2: 249.31 | DQ2: 124.38 | DR2: 248.76 | DS2: 0.55 | DT2: 3204 | DU2: 84.31 | DV2: flat | DW2: 1.23 | DX2: 1.1 | DY2: 1.06 | DZ2: -0.17 | EA2: 1473 | EB2: 3.32 | EC2: 0.5 | ED2: 113.33 | EE2: 3095 | EF2: TRUE | EG2: 99.7 | EH2: 36.3 | EI2: 1 | EJ2: 23.4 | EK2: 13.9 | EL2: 118.1 | EM2: 108.8 | EN2: 722.2 | EO2: 94.5 | EP2: 12.4
A3: Bruno Fernandes | B3: MUN | C3: MID | D3: MID | E3: 12 | F3: TRUE | G3: TRUE | H3: 32 | I3: a | L3: p141746 | M3: 426 | N3: 1 | O3: 1 | P3: 1 | Q3: 3065 | R3: 35 | S3: 35 | T3: 34.056 | U3: 87.6 | V3: 235 | W3: 6.9 | X3: 9 | Y3: 24 | Z3: 21 | AA3: 7 | AB3: 46 | AC3: 41 | AD3: 43 | AE3: 2 | AF3: 1008 | AG3: 994 | AH3: -14 | AI3: 237 | AJ3: 0.174 | AK3: 0.211 | AL3: 287 | AM3: 8.427 | AN3: 5 | AO3: 10 | AP3: 0.143 | AQ3: 0.314 | AR3: 0.143 | AS3: 0.921 | AT3: 0.971 | AU3: 8 | AV3: 12 | AW3: 4.67 | AX3: 18 | AY3: 10.79 | AZ3: 11.932 | BA3: 11.361 | BB3: 7.365 | BC3: 0.317 | BD3: 0.35 | BE3: 0.334 | BF3: 9.1 | BG3: 0.267 | BH3: 0.954 | BI3: 39.78 | BJ3: 10.298 | BK3: 0.302 | BL3: -2.361 | BM3: -1.69 | BN3: -0.1 | BO3: -1.142 | BP3: 85 | BQ3: 24 | BR3: 8 | BS3: 91 | BT3: 2.672 | BU3: 4 | BW3: 12.28 | BX3: 17.757 | BY3: 15.019 | BZ3: 0.441 | CA3: 26.379 | CB3: 0.775 | CC3: 137 | CD3: 33 | CE3: 136 | CF3: 55 | CG3: 15 | CH3: 90 | CI3: 25.944 | CJ3: 11.664 | CK3: 67 | CL3: 167 | CM3: 53 | CN3: 32 | CO3: 20 | CP3: 42 | CQ3: 5 | CR3: 124 | CS3: 21 | CT3: 0.5 | CV3: 3 | CW3: 44.42 | CX3: 1.304 | CY3: 0 | DB3: 0 | DE3: 8.03 | DF3: 5 | DG3: 0 | DH3: 25 | DI3: 35 | DK3: 1 | DL3: 15 | DM3: 30 | DN3: 4 | DO3: 48 | DP3: 226.84 | DQ3: 113.42 | DR3: 226.84 | DS3: 0 | DT3: 3342 | DU3: 87.96 | DV3: flat | DW3: 2.46 | DX3: 2.27 | DY3: 2.32 | DZ3: -0.14 | EA3: 1455 | EB3: 3.12 | EC3: 0.5 | ED3: 102.67 | EE3: 3114 | EF3: TRUE | EG3: 99.9 | EH3: 36 | EI3: 2 | EJ3: 36.1 | EK3: 33.7 | EL3: 22.5 | EM3: 269.8 | EN3: 204.1 | EO3: 116.2 | EP3: 13
A4: Gabriel Magalhães | B4: ARS | C4: DEF | D4: DEF | E4: 8 | F4: TRUE | G4: TRUE | H4: 28.7 | I4: a | L4: p226597 | M4: 4 | Q4: 2750 | R4: 32 | S4: 30 | T4: 30.556 | U4: 85.9 | V4: 209 | W4: 6.84 | X4: 3 | Y4: 5 | Z4: 4 | AA4: 18 | AB4: 20 | AC4: 30 | AD4: 24 | AE4: -6 | AF4: 724 | AG4: 683 | AH4: -41 | AI4: 203 | AJ4: 0.144 | AK4: 0.168 | AL4: 277 | AM4: 9.065 | AN4: 11 | AO4: 22 | AP4: 0.367 | AQ4: 0.367 | AR4: 0.233 | AS4: 0.789 | AT4: 0.938 | AU4: 8 | AV4: 6 | AW4: 4.43 | AX4: 15 | AY4: 2.94 | AZ4: 4.649 | BA4: 3.795 | BB4: 4.649 | BC4: 0.096 | BD4: 0.152 | BE4: 0.124 | BF4: 2.4 | BG4: 0.079 | BH4: 0.816 | BI4: 15.16 | BJ4: 2.399 | BK4: 0.079 | BL4: -0.795 | BM4: -0.54 | BN4: 0.6 | BO4: -1.709 | BP4: 27 | BQ4: 7 | BR4: 4 | BS4: 46 | BT4: 1.505 | BV4: 1 | BW4: 1.75 | BX4: 2.725 | BY4: 2.238 | BZ4: 0.073 | CA4: 6.032 | CB4: 0.197 | CC4: 7 | CD4: 5 | CE4: 7 | CF4: 1 | CG4: 2 | CI4: 8.894 | CJ4: 8.31 | CK4: 239 | CL4: 64 | CM4: 38 | CN4: 20 | CO4: 23 | CP4: 182 | CQ4: 34 | CR4: 171 | CS4: 99 | CT4: 0.1 | CU4: 1 | CV4: 2 | CW4: 22.01 | CX4: 0.72 | CY4: 0 | DB4: 0 | DE4: 7.32 | DF4: 4 | DG4: 0 | DH4: 21 | DI4: 34 | DL4: 1 | DM4: 4 | DN4: 0 | DO4: 27.2 | DP4: 185.19 | DQ4: 92.85 | DR4: 185.7 | DS4: -0.51 | DT4: 3283 | DU4: 86.4 | DV4: flat | DW4: 7.56 | DX4: 6.97 | DY4: 8.04 | DZ4: 0.48 | EA4: 1475 | EB4: 5.06 | EC4: 1 | ED4: 117.33 | EE4: 3242 | EF4: TRUE | EG4: 99.8 | EH4: 33.4 | EI4: 7 | EJ4: 101.9 | EK4: 59.8 | EL4: 392.9 | EM4: 724.7 | EN4: 1229 | EO4: 455.9 | EP4: 13.2
A5: Antoine Semenyo | B5: MCI | C5: MID | D5: MID | E5: 8.5 | F5: TRUE | G5: TRUE | H5: 26.6 | I5: a | L5: p437730 | M5: 397 | N5: 3 | Q5: 3200 | R5: 37 | S5: 37 | T5: 35.556 | U5: 86.5 | V5: 202 | W5: 5.681 | X5: 17 | Y5: 6 | Z5: 4 | AA5: 12 | AB5: 52 | AC5: 18 | AD5: 19 | AE5: 1 | AF5: 678 | AG5: 672 | AH5: -6 | AI5: 203 | AJ5: 0.089 | AK5: 0.098 | AL5: 236 | AM5: 6.637 | AN5: 3 | AO5: 6 | AP5: 0.081 | AQ5: 0.108 | AR5: 0.081 | AS5: 0.974 | AT5: 0.946 | AU5: 12 | AV5: 5 | AW5: 4.32 | AX5: 18 | AY5: 11.1 | AZ5: 12.837 | BA5: 11.968 | BB5: 11.314 | BC5: 0.312 | BD5: 0.361 | BE5: 0.337 | BF5: 13 | BG5: 0.366 | BH5: 1.141 | BI5: 25.66 | BJ5: 12.663 | BK5: 0.356 | BL5: 5.032 | BM5: 1.9 | BN5: 4 | BO5: -1.737 | BP5: 83 | BQ5: 41 | BR5: 7 | BS5: 176 | BT5: 4.95 | BU5: 1 | BW5: 3.12 | BX5: 4.13 | BY5: 3.625 | BZ5: 0.102 | CA5: 15.593 | CB5: 0.439 | CC5: 38 | CD5: 8 | CE5: 39 | CF5: 8 | CG5: 2 | CI5: 20.871 | CJ5: 7.894 | CK5: 49 | CL5: 142 | CM5: 45 | CN5: 32 | CO5: 13 | CP5: 29 | CQ5: 7 | CR5: 184 | CS5: 59 | CT5: 0.7 | CV5: 2 | CW5: 47.67 | CX5: 1.341 | CY5: 0 | DB5: 0 | DE5: 7.34 | DF5: 7 | DG5: 0 | DH5: 56 | DI5: 21 | DK5: 1 | DL5: 59 | DM5: 63 | DN5: 19 | DO5: 27.5 | DP5: 182.2 | DQ5: 91.1 | DR5: 182.2 | DS5: 0 | DT5: 3106 | DU5: 81.75 | DV5: flat | DW5: 7.24 | DX5: 6.55 | DY5: 6.75 | DZ5: -0.49 | EA5: 1512 | EB5: 5.9 | EC5: 0.8 | ED5: 101.33 | EE5: 3116 | EF5: TRUE | EG5: 99.9 | EH5: 36 | EI5: 6 | EJ5: 38.6 | EK5: 18.2 | EL5: 82.1 | EM5: 267.4 | EN5: 882.7 | EO5: 205.2 | EP5: 15.8
A6: Morgan Gibbs-White | B6: NFO | C6: MID | D6: MID | E6: 8 | F6: TRUE | G6: TRUE | H6: 26.6 | I6: a | L6: p222531 | M6: 480 | N6: 2 | P6: 1 | Q6: 3101 | R6: 37 | S6: 35 | T6: 34.456 | U6: 83.8 | V6: 188 | W6: 5.456 | X6: 15 | Y6: 4 | Z6: 4 | AA6: 10 | AB6: 45 | AC6: 18 | AD6: 18 | AE6: 0 | AF6: 712 | AG6: 702 | AH6: -10 | AI6: 188 | AJ6: 0.096 | AK6: 0.106 | AL6: 178 | AM6: 5.166 | AN6: 1 | AO6: 2 | AP6: 0.029 | AQ6: 0.029 | AR6: 0.029 | AS6: 0.921 | AT6: 0.946 | AU6: 15 | AV6: 3 | AW6: 4.06 | AX6: 20 | AY6: 10.81 | AZ6: 11.672 | BA6: 11.241 | BB6: 10.911 | BC6: 0.314 | BD6: 0.339 | BE6: 0.326 | BF6: 12.9 | BG6: 0.374 | BH6: 0.989 | BI6: 30.54 | BJ6: 10.687 | BK6: 0.31 | BL6: 3.759 | BM6: 2.09 | BN6: 2.1 | BO6: -0.862 | BP6: 83 | BQ6: 32 | BR6: 10 | BS6: 126 | BT6: 3.657 | BU6: 1 | BV6: 3 | BW6: 2.91 | BX6: 4.504 | BY6: 3.707 | BZ6: 0.108 | CA6: 14.948 | CB6: 0.434 | CC6: 48 | CD6: 5 | CE6: 49 | CF6: 9 | CG6: 1 | CH6: 1 | CI6: 17.265 | CJ6: 5.414 | CK6: 48 | CL6: 110 | CM6: 20 | CN6: 15 | CO6: 13 | CP6: 32 | CQ6: 3 | CR6: 130 | CS6: 41 | CT6: 0.6 | CU6: 1 | CV6: 4 | CW6: 49.7 | CX6: 1.442 | CY6: 0 | DB6: 0 | DE6: 7.15 | DF6: 1 | DG6: 0 | DH6: 26 | DI6: 41 | DJ6: 1 | DL6: 30 | DM6: 37 | DN6: 5 | DO6: 11.6 | DP6: 182.08 | DQ6: 91.04 | DR6: 182.08 | DS6: 0 | DT6: 3301 | DU6: 86.86 | DV6: flat | DW6: 17.37 | DX6: 14.7 | DY6: 17.33 | DZ6: -0.03 | EA6: 1268 | EB6: 11.79 | EC6: 1.33 | ED6: 118.67 | EE6: 2152 | EF6: TRUE | EG6: 99.9 | EH6: 55.8 | EI6: 8 | EJ6: 37.4 | EK6: 24.6 | EL6: 63.3 | EM6: 275.9 | EN6: 836.5 | EO6: 207.5 | EP6: 16.5
A7: Declan Rice | B7: ARS | C7: MID | D7: MID | E7: 7.5 | F7: TRUE | G7: TRUE | H7: 27.6 | I7: a | L7: p204480 | M7: 13 | O7: 1 | P7: 1 | Q7: 3093 | R7: 36 | S7: 35 | T7: 34.367 | U7: 85.9 | V7: 184 | W7: 5.354 | X7: 4 | Y7: 9 | Z7: 5 | AA7: 18 | AB7: 25 | AC7: 23 | AD7: 24 | AE7: 1 | AF7: 790 | AG7: 769 | AH7: -21 | AI7: 185 | AJ7: 0.125 | AK7: 0.143 | AL7: 376 | AM7: 10.941 | AN7: 14 | AO7: 28 | AP7: 0.4 | AQ7: 0.6 | AR7: 0.4 | AS7: 0.921 | AT7: 0.972 | AU7: 6 | AV7: 4 | AW7: 3.59 | AX7: 17 | AY7: 3.15 | AZ7: 3.721 | BA7: 3.435 | BB7: 3.721 | BC7: 0.092 | BD7: 0.108 | BE7: 0.1 | BF7: 4.5 | BG7: 0.131 | BH7: 1.132 | BI7: 12.59 | BJ7: 3.565 | BK7: 0.104 | BL7: 0.565 | BM7: 1.35 | BN7: -0.5 | BO7: -0.571 | BP7: 40 | BQ7: 13 | BR7: 3 | BS7: 56 | BT7: 1.629 | BV7: 1 | BW7: 7.32 | BX7: 8.159 | BY7: 7.74 | BZ7: 0.225 | CA7: 11.175 | CB7: 0.325 | CC7: 63 | CD7: 17 | CE7: 63 | CF7: 47 | CG7: 5 | CH7: 95 | CI7: 18.491 | CJ7: 12.957 | CK7: 127 | CL7: 180 | CM7: 69 | CN7: 35 | CO7: 37 | CP7: 78 | CQ7: 12 | CR7: 145 | CS7: 50 | CT7: 0.3 | CU7: 1 | CW7: 23.87 | CX7: 0.695 | CY7: 0 | DB7: 0 | DE7: 7.56 | DF7: 3 | DG7: 0 | DH7: 26 | DI7: 11 | DL7: 14 | DM7: 18 | DN7: 1 | DO7: 21.6 | DP7: 152.45 | DQ7: 75.39 | DR7: 150.78 | DS7: 1.67 | DT7: 3106 | DU7: 81.75 | DV7: flat | DW7: 15.01 | DX7: 14.33 | DY7: 15.11 | DZ7: 0.1 | EA7: 1509 | EB7: 8.43 | EC7: 1.14 | ED7: 110.67 | EE7: 3060 | EF7: TRUE | EG7: 99.9 | EH7: 37.1 | EI7: 13 | EJ7: 77.3 | EK7: 55.2 | EL7: 49.1 | EM7: 900.3 | EN7: 399.6 | EO7: 276.8 | EP7: 16.8
A8: Igor Thiago | B8: BRE | C8: FWD | D8: FWD | E8: 8 | F8: TRUE | G8: TRUE | H8: 25.2 | I8: a | L8: p502500 | M8: 106 | N8: 1 | Q8: 3282 | R8: 38 | S8: 37 | T8: 36.467 | U8: 86.4 | V8: 181 | W8: 4.963 | X8: 22 | Y8: 1 | Z8: 1 | AA8: 10 | AB8: 50 | AC8: 22 | AD8: 22 | AE8: 0 | AF8: 710 | AG8: 694 | AH8: -16 | AI8: 181 | AJ8: 0.122 | AK8: 0.138 | AL8: 214 | AM8: 5.868 | AN8: 1 | AO8: 2 | AP8: 0.027 | AQ8: 0.054 | AR8: 0.027 | AS8: 0.974 | AT8: 0.974 | AU8: 21 | AV8: 6 | AW8: 4.26 | AX8: 17 | AY8: 20.6 | AZ8: 24.69 | BA8: 22.645 | BB8: 17.839 | BC8: 0.565 | BD8: 0.677 | BE8: 0.621 | BF8: 20.1 | BG8: 0.551 | BH8: 0.978 | BI8: 20.73 | BJ8: 20.148 | BK8: 0.553 | BL8: -0.645 | BM8: -0.5 | BN8: 1.9 | BO8: -4.09 | BP8: 84 | BQ8: 43 | BR8: 20 | BS8: 169 | BT8: 4.634 | BU8: 8 | BV8: 2 | BW8: 1.83 | BX8: 3.45 | BY8: 2.64 | BZ8: 0.072 | CA8: 25.285 | CB8: 0.693 | CC8: 24 | CD8: 6 | CE8: 24 | CF8: 7 | CG8: 2 | CI8: 22.693 | CJ8: 4.928 | CK8: 84 | CL8: 93 | CM8: 37 | CN8: 22 | CO8: 12 | CP8: 64 | CQ8: 8 | CR8: 203 | CS8: 112 | CT8: 0.4 | CV8: 2 | CW8: 53.17 | CX8: 1.458 | CY8: 0 | DB8: 0 | DE8: 7.14 | DF8: 7 | DG8: 0 | DH8: 73 | DI8: 26 | DL8: 29 | DM8: 42 | DN8: 23 | DO8: 16.1 | DP8: 167.6 | DQ8: 83.8 | DR8: 167.6 | DS8: 0 | DT8: 3209 | DU8: 84.45 | DV8: flat | DW8: 12.17 | DX8: 10.77 | DY8: 11.56 | DZ8: -0.61 | EA8: 1522 | EB8: 8.58 | EC8: 0.5 | ED8: 114.67 | EE8: 2989 | EF8: TRUE | EG8: 99.9 | EH8: 38.6 | EI8: 9 | EJ8: 39.1 | EK8: 19.4 | EL8: 136.8 | EM8: 144.9 | EN8: 1243.2 | EO8: 129.8 | EP8: 18.1
A9: Elliot Anderson | B9: MCI | C9: MID | D9: MID | E9: 6.5 | F9: TRUE | G9: TRUE | H9: 23.8 | I9: a | L9: p215379 | M9: 481 | O9: 3 | Q9: 3332 | R9: 38 | S9: 37 | T9: 37.022 | U9: 87.7 | V9: 180 | W9: 4.862 | X9: 4 | Y9: 5 | Z9: 4 | AA9: 10 | AB9: 50 | AC9: 16 | AD9: 18 | AE9: 2 | AF9: 795 | AG9: 775 | AH9: -20 | AI9: 182 | AJ9: 0.089 | AK9: 0.098 | AL9: 515 | AM9: 13.911 | AN9: 26 | AO9: 52 | AP9: 0.703 | AQ9: 0.892 | AR9: 0.703 | AS9: 0.974 | AT9: 0.974 | AU9: 10 | AV9: 3 | AW9: 3.01 | AX9: 12 | AY9: 2.94 | AZ9: 3.444 | BA9: 3.192 | BB9: 2.683 | BC9: 0.079 | BD9: 0.093 | BE9: 0.086 | BF9: 2.4 | BG9: 0.065 | BH9: 0.902 | BI9: 7.75 | BJ9: 2.651 | BK9: 0.072 | BL9: 0.808 | BM9: -0.54 | BN9: 1.6 | BO9: -0.504 | BP9: 44 | BQ9: 10 | BR9: 1 | BS9: 62 | BT9: 1.675 | BU9: 1 | BW9: 4.79 | BX9: 4.843 | BY9: 4.816 | BZ9: 0.13 | CA9: 8.008 | CB9: 0.216 | CC9: 55 | CD9: 9 | CE9: 54 | CF9: 51 | CG9: 2 | CH9: 87 | CI9: 16.283 | CJ9: 11.958 | CK9: 106 | CL9: 306 | CM9: 103 | CN9: 63 | CO9: 41 | CP9: 49 | CQ9: 16 | CR9: 297 | CS9: 66 | CT9: 0.7 | CV9: 4 | CW9: 53.65 | CX9: 1.449 | CY9: 0 | DB9: 0 | DE9: 7.51 | DF9: 8 | DG9: 0 | DH9: 57 | DI9: 80 | DK9: 1 | DL9: 50 | DM9: 62 | DN9: 2 | DO9: 11.1 | DP9: 116.9 | DQ9: 63.21 | DR9: 126.42 | DS9: -9.52 | DT9: 2096 | DU9: 55.17 | DV9: flat | DW9: 33.68 | DX9: 31.37 | DY9: 34.6 | DZ9: 0.92 | EA9: 1544 | EB9: 16.01 | EC9: 1.6 | ED9: 113.14 | EE9: 3363 | EF9: TRUE | EG9: 98.9 | EH9: 30.2 | EI9: 31 | EJ9: 75.7 | EK9: 53.7 | EL9: 61.7 | EM9: 1043.8 | EN9: 691.8 | EO9: 416.1 | EP9: 18.5
A10: Marc Guéhi | B10: MCI | C10: DEF | D10: DEF | E10: 6 | F10: TRUE | G10: TRUE | H10: 26.1 | I10: a | L10: p209036 | M10: 388 | Q10: 3150 | R10: 35 | S10: 35 | T10: 35 | U10: 90 | V10: 179 | W10: 5.114 | X10: 3 | Y10: 5 | Z10: 3 | AA10: 14 | AB10: 35 | AC10: 14 | AD10: 12 | AE10: -2 | AF10: 688 | AG10: 647 | AH10: -41 | AI10: 177 | AJ10: 0.078 | AK10: 0.085 | AL10: 278 | AM10: 7.943 | AN10: 11 | AO10: 22 | AP10: 0.314 | AQ10: 0.314 | AR10: 0.114 | AS10: 0.921 | AT10: 1 | AU10: 12 | AV10: 4 | AW10: 4 | AX10: 15 | AY10: 4.05 | AZ10: 4.697 | BA10: 4.374 | BB10: 4.697 | BC10: 0.116 | BD10: 0.134 | BE10: 0.125 | BF10: 4 | BG10: 0.114 | BH10: 1.084 | BI10: 7.96 | BJ10: 4.39 | BK10: 0.125 | BL10: -1.374 | BM10: -0.05 | BN10: -1 | BO10: -0.647 | BP10: 32 | BQ10: 9 | BR10: 6 | BS10: 62 | BT10: 1.771 | BV10: 1 | BW10: 2.37 | BX10: 2.727 | BY10: 2.548 | BZ10: 0.073 | CA10: 6.922 | CB10: 0.198 | CC10: 18 | CD10: 5 | CE10: 18 | CF10: 3 | CG10: 3 | CH10: 2 | CI10: 17.673 | CJ10: 15.488 | CK10: 232 | CL10: 139 | CM10: 46 | CN10: 31 | CO10: 50 | CP10: 164 | CQ10: 23 | CR10: 194 | CS10: 103 | CT10: 0.1 | CU10: 2 | CV10: 0 | CW10: 44.58 | CX10: 1.274 | CY10: 0 | DB10: 0 | DE10: 7.37 | DF10: 6 | DG10: 0 | DH10: 25 | DI10: 38 | DJ10: 1 | DL10: 7 | DM10: 18 | DO10: 22.6 | DP10: 116.75 | DQ10: 58.17 | DR10: 116.34 | DS10: 0.41 | DT10: 2611 | DU10: 68.7 | DV10: flat | DW10: 32.73 | DX10: 34.4 | DY10: 29.35 | DZ10: -3.38 | EA10: 1622 | EB10: 11.58 | EC10: 1 | ED10: 100 | EE10: 3874 | EF10: TRUE | EG10: 99.9 | EH10: 20.5 | EI10: 56 | EJ10: 98.4 | EK10: 50.8 | EL10: 175 | EM10: 720.2 | EN10: 1236.1 | EO10: 455.1 | EP10: 17.6
A11: João Pedro | B11: CHE | C11: FWD | D11: FWD | E11: 7.5 | F11: TRUE | G11: TRUE | H11: 24.9 | I11: a | L11: p475168 | M11: 165 | Q11: 2658 | R11: 35 | S11: 31 | T11: 29.533 | U11: 75.9 | V11: 177 | W11: 5.993 | X11: 15 | Y11: 9 | Z11: 5 | AA11: 10 | AB11: 36 | AC11: 30 | AD11: 30 | AE11: 0 | AF11: 715 | AG11: 710 | AH11: -5 | AI11: 177 | AJ11: 0.169 | AK11: 0.204 | AL11: 138 | AM11: 4.673 | AN11: 0 | AO11: 0 | AP11: 0 | AQ11: 0.032 | AR11: 0 | AS11: 0.816 | AT11: 0.857 | AU11: 20 | AV11: 5 | AW11: 4.56 | AX11: 19 | AY11: 14.91 | AZ11: 15.724 | BA11: 15.317 | BB11: 15.724 | BC11: 0.505 | BD11: 0.532 | BE11: 0.519 | BF11: 15.2 | BG11: 0.515 | BH11: 1.003 | BI11: 35.88 | BJ11: 14.951 | BK11: 0.506 | BL11: -0.317 | BM11: 0.29 | BN11: -0.2 | BO11: -0.814 | BP11: 73 | BQ11: 28 | BR11: 12 | BS11: 145 | BT11: 4.91 | BV11: 3 | BW11: 1.96 | BX11: 3.984 | BY11: 2.972 | BZ11: 0.101 | CA11: 18.289 | CB11: 0.619 | CC11: 29 | CD11: 6 | CE11: 29 | CF11: 1 | CG11: 5 | CI11: 19.28 | CJ11: 4.796 | CK11: 39 | CL11: 72 | CM11: 27 | CN11: 18 | CO11: 7 | CP11: 27 | CQ11: 5 | CR11: 196 | CS11: 74 | CT11: 0.5 | CU11: 0 | CW11: 37.25 | CX11: 1.261 | CY11: 0 | DB11: 0 | DE11: 7.18 | DF11: 5 | DG11: 0 | DH11: 38 | DI11: 56 | DJ11: 3 | DL11: 40 | DM11: 55 | DN11: 16 | DO11: 55.9 | DP11: 176.3 | DQ11: 88.23 | DR11: 176.46 | DS11: -0.16 | DT11: 2890 | DU11: 76.05 | DV11: flat | DW11: 8.78 | DX11: 8.83 | DY11: 7.46 | DZ11: -1.33 | EA11: 1635 | EB11: 6.04 | EC11: 0.8 | ED11: 120 | EE11: 4154 | EF11: TRUE | EG11: 100 | EH11: 14.8 | EI11: 14 | EJ11: 36.4 | EK11: 18.3 | EL11: 91.7 | EM11: 173.5 | EN11: 894.4 | EO11: 145.3 | EP11: 15
A12: Virgil van Dijk | B12: LIV | C12: DEF | D12: DEF | E12: 6.5 | F12: TRUE | G12: TRUE | H12: 35.1 | I12: a | L12: p97032 | M12: 356 | Q12: 3420 | R12: 38 | S12: 38 | T12: 38 | U12: 90 | V12: 175 | W12: 4.605 | X12: 6 | Y12: 1 | AA12: 10 | AB12: 53 | AC12: 10 | AD12: 9 | AE12: -1 | AF12: 593 | AG12: 534 | AH12: -59 | AI12: 174 | AJ12: 0.057 | AK12: 0.061 | AL12: 352 | AM12: 9.263 | AN12: 16 | AO12: 32 | AP12: 0.421 | AQ12: 0.421 | AR12: 0.289 | AS12: 1 | AT12: 1 | AU12: 14 | AV12: 3 | AW12: 3.77 | AX12: 17 | AY12: 3.77 | AZ12: 4.891 | BA12: 4.331 | BB12: 4.891 | BC12: 0.099 | BD12: 0.129 | BE12: 0.114 | BF12: 4.9 | BG12: 0.129 | BH12: 0.991 | BI12: 11.37 | BJ12: 3.737 | BK12: 0.098 | BL12: 1.669 | BM12: 1.13 | BN12: 1.1 | BO12: -1.121 | BP12: 30 | BQ12: 14 | BR12: 8 | BS12: 71 | BT12: 1.868 | BV12: 5 | BW12: 1.44 | BX12: 0.329 | BY12: 0.884 | BZ12: 0.023 | CA12: 5.215 | CB12: 0.137 | CC12: 11 | CE12: 12 | CG12: 1 | CI12: 12.486 | CJ12: 11.383 | CK12: 329 | CL12: 87 | CM12: 23 | CN12: 13 | CO12: 28 | CP12: 275 | CQ12: 26 | CR12: 216 | CS12: 174 | CT12: 0.1 | CU12: 2 | CV12: 2 | CW12: 47.63 | CX12: 1.253 | CY12: 0 | DB12: 0 | DE12: 7.26 | DF12: 4 | DG12: 0 | DH12: 19 | DI12: 18 | DK12: 1 | DL12: 2 | DM12: 1 | DN12: 1 | DO12: 16.9 | DP12: 158.96 | DQ12: 79.48 | DR12: 158.96 | DS12: 0 | DT12: 3340 | DU12: 87.9 | DV12: flat | DW12: 24.92 | DX12: 25.44 | DY12: 23.63 | DZ12: -1.29 | EA12: 1617 | EB12: 9.39 | EC12: 0.8 | ED12: 88 | EE12: 3851 | EF12: TRUE | EG12: 99.9 | EH12: 20.9 | EI12: 32 | EJ12: 114 | EK12: 48.2 | EL12: 285 | EM12: 789.7 | EN12: 3867.6 | EO12: 655.8 | EP12: 19.5
A13: Marcos Senesi | B13: TOT | C13: DEF | D13: DEF | E13: 6 | F13: TRUE | G13: TRUE | H13: 29.3 | I13: a | L13: p221466 | M13: 498 | Q13: 3288 | R13: 37 | S13: 37 | T13: 36.533 | U13: 88.9 | V13: 175 | W13: 4.79 | X13: 0 | Y13: 6 | Z13: 5 | AA13: 11 | AB13: 53 | AC13: 14 | AD13: 12 | AE13: -2 | AF13: 571 | AG13: 508 | AH13: -63 | AI13: 173 | AJ13: 0.08 | AK13: 0.087 | AL13: 419 | AM13: 11.469 | AN13: 26 | AO13: 52 | AP13: 0.703 | AQ13: 0.703 | AR13: 0.432 | AS13: 0.974 | AT13: 1 | AU13: 13 | AV13: 4 | AW13: 3.58 | AX13: 14 | AY13: 1.53 | AZ13: 1.851 | BA13: 1.69 | BB13: 1.851 | BC13: 0.042 | BD13: 0.051 | BE13: 0.046 | BF13: 0.5 | BG13: 0.014 | BH13: 0.799 | BI13: 6.01 | BJ13: 1.223 | BK13: 0.033 | BL13: -1.69 | BM13: -1.03 | BN13: -0.5 | BO13: -0.321 | BP13: 17 | BQ13: 5 | BR13: 2 | BS13: 53 | BT13: 1.451 | BW13: 4.72 | BX13: 4.027 | BY13: 4.373 | BZ13: 0.12 | CA13: 6.064 | CB13: 0.166 | CC13: 24 | CD13: 7 | CE13: 24 | CF13: 8 | CG13: 10 | CI13: 14.265 | CJ13: 10.906 | CK13: 357 | CL13: 155 | CM13: 62 | CN13: 35 | CO13: 56 | CP13: 253 | CQ13: 47 | CR13: 196 | CS13: 92 | CT13: 0.1 | CV13: 2 | CW13: 54.77 | CX13: 1.499 | CY13: 0 | DB13: 0 | DE13: 7.19 | DF13: 8 | DG13: 0 | DH13: 34 | DI13: 37 | DJ13: 1 | DL13: 6 | DM13: 14 | DN13: 1 | DO13: 10.2 | DP13: 71.48 | DQ13: 35.74 | DR13: 71.48 | DS13: 0 | DT13: 1573 | DU13: 41.4 | DV13: flat | DW13: 49.73 | DX13: 48.99 | DY13: 49.65 | DZ13: -0.08 | EA13: 1488 | EB13: 16.74 | EC13: 9 | ED13: 119 | EE13: 2815 | EF13: TRUE | EG13: 98.9 | EH13: 41.6 | EI13: 57 | EJ13: 193.4 | EK13: 62 | EL13: 137 | EM13: 1945.2 | EN13: 751.8 | EO13: 542.2 | EP13: 18.8
A14: James Tarkowski | B14: EVE | C14: DEF | D14: DEF | E14: 6 | F14: TRUE | G14: TRUE | H14: 33.8 | I14: a | L14: p17761 | M14: 229 | Q14: 3330 | R14: 37 | S14: 37 | T14: 37 | U14: 90 | V14: 170 | W14: 4.595 | X14: 2 | Y14: 3 | Z14: 3 | AA14: 11 | AB14: 48 | AC14: 12 | AD14: 12 | AE14: 0 | AF14: 592 | AG14: 538 | AH14: -54 | AI14: 170 | AJ14: 0.071 | AK14: 0.076 | AL14: 376 | AM14: 10.162 | AN14: 22 | AO14: 44 | AP14: 0.595 | AQ14: 0.595 | AR14: 0.351 | AS14: 0.974 | AT14: 1 | AU14: 11 | AV14: 3 | AW14: 3.74 | AX14: 15 | AY14: 2.53 | AZ14: 2.869 | BA14: 2.7 | BB14: 2.869 | BC14: 0.068 | BD14: 0.078 | BE14: 0.073 | BF14: 3.2 | BG14: 0.086 | BH14: 0.812 | BI14: 9.37 | BJ14: 2.054 | BK14: 0.056 | BL14: -0.7 | BM14: 0.67 | BN14: -1.2 | BO14: -0.339 | BP14: 21 | BQ14: 10 | BR14: 4 | BS14: 84 | BT14: 2.27 | BV14: 1 | BW14: 2.1 | BX14: 2.057 | BY14: 2.078 | BZ14: 0.056 | CA14: 4.778 | CB14: 0.129 | CC14: 18 | CD14: 2 | CE14: 18 | CF14: 2 | CG14: 3 | CI14: 6.824 | CJ14: 5.569 | CK14: 325 | CL14: 90 | CM14: 51 | CN14: 29 | CO14: 32 | CP14: 242 | CQ14: 52 | CR14: 234 | CS14: 147 | CT14: 0.1 | CU14: 1 | CV14: 7 | CW14: 53.54 | CX14: 1.447 | CY14: 0 | DB14: 0 | DE14: 7.13 | DF14: 8 | DG14: 0 | DH14: 32 | DI14: 35 | DK14: 1 | DL14: 4 | DM14: 1 | DN14: 2 | DO14: 9.7 | DP14: 150.34 | DQ14: 75.17 | DR14: 150.34 | DS14: 0 | DT14: 3266 | DU14: 85.95 | DV14: flat | DW14: 48.45 | DX14: 48.13 | DY14: 47.51 | DZ14: -0.93 | EA14: 1519 | EB14: 15.58 | EC14: 5.33 | ED14: 118.67 | EE14: 3130 | EF14: TRUE | EG14: 99.6 | EH14: 35.5 | EI14: 58 | EJ14: 158.6 | EK14: 39.6 | EL14: 185 | EM14: 1233.5 | EN14: 1602.2 | EO14: 697 | EP14: 19.6
A15: Morgan Rogers | B15: CHE | C15: MID | D15: MID | E15: 7.5 | F15: TRUE | G15: TRUE | H15: 24.1 | I15: a | L15: p244850 | M15: 40 | Q15: 3280 | R15: 37 | S15: 37 | T15: 36.444 | U15: 88.6 | V15: 169 | W15: 4.637 | X15: 10 | Y15: 8 | Z15: 6 | AA15: 9 | AB15: 48 | AC15: 17 | AD15: 17 | AE15: 0 | AF15: 605 | AG15: 591 | AH15: -14 | AI15: 169 | AJ15: 0.101 | AK15: 0.112 | AL15: 230 | AM15: 6.311 | AN15: 1 | AO15: 2 | AP15: 0.027 | AQ15: 0.135 | AR15: 0.027 | AS15: 0.974 | AT15: 1 | AU15: 18 | AV15: 5 | AW15: 4.14 | AX15: 15 | AY15: 6.84 | AZ15: 7.146 | BA15: 6.993 | BB15: 7.146 | BC15: 0.188 | BD15: 0.196 | BE15: 0.192 | BF15: 8.1 | BG15: 0.222 | BH15: 1.116 | BI15: 14.68 | BJ15: 7.63 | BK15: 0.209 | BL15: 3.007 | BM15: 1.26 | BN15: 1.9 | BO15: -0.306 | BP15: 84 | BQ15: 32 | BR15: 4 | BS15: 181 | BT15: 4.966 | BW15: 4.32 | BX15: 7.475 | BY15: 5.898 | BZ15: 0.162 | CA15: 12.89 | CB15: 0.354 | CC15: 48 | CD15: 13 | CE15: 47 | CF15: 3 | CG15: 5 | CH15: 1 | CI15: 18.205 | CJ15: 7.18 | CK15: 49 | CL15: 139 | CM15: 42 | CN15: 23 | CO15: 13 | CP15: 32 | CQ15: 3 | CR15: 158 | CS15: 26 | CT15: 0.7 | CV15: 2 | CW15: 51.55 | CX15: 1.414 | CY15: 0 | DB15: 0 | DE15: 7 | DF15: 7 | DG15: 0 | DH15: 46 | DI15: 49 | DK15: 1 | DL15: 42 | DM15: 80 | DN15: 3 | DO15: 26.1 | DP15: 159.75 | DQ15: 79.57 | DR15: 159.14 | DS15: 0.61 | DT15: 2890 | DU15: 76.05 | DV15: flat | DW15: 16.73 | DX15: 15.52 | DY15: 16.45 | DZ15: -0.28 | EA15: 1499 | EB15: 9.31 | EC15: 1.14 | ED15: 114.67 | EE15: 3098 | EF15: TRUE | EG15: 99.9 | EH15: 36.4 | EI15: 15 | EJ15: 39 | EK15: 18.1 | EL15: 69.8 | EM15: 469 | EN15: 556.2 | EO15: 254.5 | EP15: 19.4
A16: Harry Wilson | B16: LEE | C16: MID | D16: MID | E16: 6.5 | F16: TRUE | G16: TRUE | H16: 29.4 | I16: a | L16: p153682 | M16: 260 | O16: 2 | Q16: 2674 | R16: 36 | S16: 32 | T16: 29.711 | U16: 74.3 | V16: 168 | W16: 5.654 | X16: 10 | Y16: 9 | Z16: 7 | AA16: 9 | AB16: 38 | AC16: 21 | AD16: 21 | AE16: 0 | AF16: 637 | AG16: 624 | AH16: -13 | AI16: 168 | AJ16: 0.125 | AK16: 0.143 | AL16: 177 | AM16: 5.957 | AN16: 1 | AO16: 2 | AP16: 0.031 | AQ16: 0.062 | AR16: 0.031 | AS16: 0.842 | AT16: 0.833 | AU16: 18 | AV16: 5 | AW16: 3.94 | AX16: 16 | AY16: 5.88 | AZ16: 5.76 | BA16: 5.82 | BB16: 5.76 | BC16: 0.198 | BD16: 0.194 | BE16: 0.196 | BF16: 8.9 | BG16: 0.3 | BH16: 1.236 | BI16: 15.55 | BJ16: 7.266 | BK16: 0.245 | BL16: 4.18 | BM16: 3.02 | BN16: 1.1 | BO16: 0.12 | BP16: 78 | BQ16: 25 | BR16: 1 | BS16: 105 | BT16: 3.534 | BW16: 4.77 | BX16: 5.504 | BY16: 5.137 | BZ16: 0.173 | CA16: 10.957 | CB16: 0.369 | CC16: 37 | CD16: 8 | CE16: 39 | CF16: 32 | CG16: 6 | CH16: 70 | CI16: 11.092 | CJ16: 4.133 | CK16: 66 | CL16: 82 | CM16: 29 | CN16: 19 | CO16: 15 | CP16: 48 | CQ16: 3 | CR16: 89 | CS16: 5 | CT16: 0.3 | CV16: 2 | CW16: 40.14 | CX16: 1.351 | CY16: 0 | DB16: 0 | DE16: 7.14 | DF16: 7 | DG16: 0 | DH16: 13 | DI16: 37 | DL16: 18 | DM16: 23 | DN16: 13 | DO16: 7.9 | DP16: 146.08 | DQ16: 73.04 | DR16: 146.08 | DS16: 0 | DT16: 2810 | DU16: 73.95 | DV16: flat | DW16: 46.77 | DX16: 43.66 | DY16: 47.42 | DZ16: 0.65 | EA16: 1411 | EB16: 20.28 | EC16: 0.8 | ED16: 120 | EE16: 2610 | EF16: TRUE | EG16: 96.7 | EH16: 44.6 | EI16: 33 | EJ16: 34.3 | EK16: 25.5 | EL16: 68.6 | EM16: 459.5 | EN16: 520.6 | EO16: 244.1 | EP16: 15.9
A17: Ollie Watkins | B17: AVL | C17: FWD | D17: FWD | E17: 8 | F17: TRUE | G17: TRUE | H17: 30.6 | I17: a | L17: p178301 | M17: 55 | N17: 2 | Q17: 2833 | R17: 37 | S17: 33 | T17: 31.478 | U17: 76.6 | V17: 167 | W17: 5.305 | X17: 16 | Y17: 4 | Z17: 3 | AA17: 9 | AB17: 38 | AC17: 26 | AD17: 26 | AE17: 0 | AF17: 623 | AG17: 618 | AH17: -5 | AI17: 167 | AJ17: 0.156 | AK17: 0.184 | AL17: 94 | AM17: 2.986 | AN17: 0 | AO17: 0 | AP17: 0 | AQ17: 0 | AR17: 0 | AS17: 0.868 | AT17: 0.865 | AU17: 24 | AV17: 5 | AW17: 4.42 | AX17: 16 | AY17: 15.4 | AZ17: 18.828 | BA17: 17.114 | BB17: 18.828 | BC17: 0.489 | BD17: 0.598 | BE17: 0.544 | BF17: 15.8 | BG17: 0.502 | BH17: 1.025 | BI17: 63.41 | BJ17: 15.786 | BK17: 0.501 | BL17: -1.114 | BM17: 0.4 | BN17: 0.2 | BO17: -3.428 | BP17: 83 | BQ17: 38 | BR17: 19 | BS17: 177 | BT17: 5.623 | BV17: 4 | BW17: 1.18 | BX17: 2.816 | BY17: 1.998 | BZ17: 0.063 | CA17: 19.112 | CB17: 0.607 | CC17: 23 | CD17: 4 | CE17: 23 | CF17: 2 | CH17: 0 | CI17: 21.746 | CJ17: 4.341 | CK17: 23 | CL17: 49 | CM17: 22 | CN17: 14 | CO17: 6 | CP17: 15 | CQ17: 2 | CR17: 116 | CS17: 36 | CT17: 0.5 | CW17: 43.39 | CX17: 1.378 | CY17: 0 | DB17: 0 | DE17: 6.97 | DF17: 4 | DG17: 0 | DH17: 35 | DI17: 32 | DJ17: 0 | DL17: 26 | DM17: 43 | DN17: 24 | DO17: 12.6 | DP17: 167.14 | DQ17: 83.7 | DR17: 167.4 | DS17: -0.26 | DT17: 2679 | DU17: 70.5 | DV17: flat | DW17: 13.66 | DX17: 11.89 | DY17: 12.81 | DZ17: -0.85 | EA17: 1497 | EB17: 9.36 | EC17: 1 | ED17: 112 | EE17: 2853 | EF17: TRUE | EG17: 99.9 | EH17: 41.4 | EI17: 10 | EJ17: 34.1 | EK17: 16 | EL17: 123.2 | EM17: 165.5 | EN17: 1417.9 | EO17: 148.2 | EP17: 17
A18: Adrien Truffert | B18: BOU | C18: DEF | D18: DEF | E18: 5.5 | F18: TRUE | G18: TRUE | H18: 24.8 | I18: a | L18: p494521 | M18: 61 | Q18: 3378 | R18: 38 | S18: 38 | T18: 37.533 | U18: 88.9 | V18: 165 | W18: 4.396 | X18: 1 | Y18: 6 | Z18: 5 | AA18: 11 | AB18: 51 | AC18: 19 | AD18: 19 | AE18: 0 | AF18: 607 | AG18: 567 | AH18: -40 | AI18: 165 | AJ18: 0.115 | AK18: 0.13 | AL18: 301 | AM18: 8.02 | AN18: 12 | AO18: 24 | AP18: 0.316 | AQ18: 0.316 | AR18: 0.132 | AS18: 1 | AT18: 1 | AU18: 12 | AV18: 3 | AW18: 3.1 | AX18: 11 | AY18: 1.35 | AZ18: 1.989 | BA18: 1.669 | BB18: 1.989 | BC18: 0.036 | BD18: 0.053 | BE18: 0.044 | BF18: 1.6 | BG18: 0.043 | BH18: 1.027 | BI18: 1.35 | BJ18: 1.386 | BK18: 0.037 | BL18: -0.669 | BM18: 0.25 | BN18: -0.6 | BO18: -0.639 | BP18: 16 | BQ18: 6 | BR18: 1 | BS18: 53 | BT18: 1.412 | BW18: 3.07 | BX18: 4.408 | BY18: 3.739 | BZ18: 0.1 | CA18: 5.408 | CB18: 0.144 | CC18: 33 | CD18: 4 | CE18: 32 | CF18: 34 | CH18: 1 | CI18: 15.239 | CJ18: 9.959 | CK18: 199 | CL18: 188 | CM18: 102 | CN18: 52 | CO18: 48 | CP18: 143 | CQ18: 10 | CR18: 212 | CS18: 44 | CT18: 0.2 | CU18: 1 | CV18: 2 | CW18: 54.42 | CX18: 1.45 | CY18: 0 | DB18: 0 | DE18: 7.18 | DF18: 5 | DG18: 0 | DH18: 39 | DI18: 32 | DL18: 33 | DM18: 24 | DO18: 4.9 | DP18: 140.24 | DQ18: 70.12 | DR18: 140.24 | DS18: 0 | DT18: 3266 | DU18: 85.95 | DV18: flat | DW18: 65.5 | DX18: 65.42 | DY18: 65.06 | DZ18: -0.44 | EA18: 1441 | EB18: 17.67 | EC18: 8 | ED18: 120 | EE18: 2497 | EF18: TRUE | EG18: 97.9 | EH18: 47.7 | EI18: 111 | EJ18: 211.1 | EK18: 63.7 | EL18: 105.6 | EM18: 2023.5 | EN18: 903.4 | EO18: 624.6 | EP18: 20.5
A19: David Raya | B19: ARS | C19: GKP | D19: GKP | E19: 6 | F19: TRUE | G19: TRUE | H19: 30.9 | I19: a | L19: p154561 | M19: 1 | Q19: 3330 | R19: 37 | S19: 37 | T19: 37 | U19: 90 | V19: 162 | W19: 4.378 | X19: 0 | Y19: 0 | AA19: 19 | AB19: 26 | AC19: 11 | AD19: 11 | AE19: 0 | AF19: 633 | AG19: 624 | AH19: -9 | AI19: 162 | AJ19: 0.068 | AK19: 0.073 | AL19: 0 | AM19: 0 | AN19: 0 | AO19: 0 | AP19: 0 | AQ19: 0 | AR19: 0 | AS19: 0.974 | AT19: 1 | AU19: 15 | AV19: 2 | AW19: 2.79 | AX19: 10 | AY19: 0 | AZ19: 0 | BA19: 0 | BB19: 0 | BC19: 0 | BD19: 0 | BE19: 0 | BH19: 0.986 | BI19: 0.11 | BJ19: 0 | BK19: 0 | BL19: 0 | BO19: 0 | BW19: 0.07 | BX19: 0.149 | BY19: 0.11 | BZ19: 0.003 | CA19: 0.11 | CB19: 0.003 | CC19: 3 | CE19: 3 | CI19: 6.412 | CJ19: 6.322 | CK19: 37 | CL19: 304 | CM19: 1 | CN19: 1 | CO19: 1 | CP19: 37 | CR19: 25 | CS19: 10 | CU19: 1 | CV19: 3 | CW19: 27.56 | CX19: 0.745 | CY19: 60 | CZ19: 69.8 | DA19: -1.1 | DB19: 0 | DC19: 39 | DD19: 10 | DE19: 7.21 | DF19: 1 | DG19: 0 | DI19: 14 | DL19: 1 | DO19: 31.2 | DP19: 149.74 | DQ19: 74.87 | DR19: 149.74 | DS19: 0 | DT19: 3385 | DU19: 89.09 | DV19: flat | DW19: 27.19 | DX19: 28.81 | DY19: 24.86 | DZ19: -2.32 | EA19: 1614 | EB19: 13.8 | EC19: 0.67 | ED19: 118.86 | EE19: 4019 | EF19: TRUE | EG19: 99.9 | EH19: 17.5 | EI19: 59 | EL19: 1110 | EN19: 30356.3 | EO19: 30356.3 | EP19: 20.6
A20: Dominik Szoboszlai | B20: LIV | C20: MID | D20: MID | E20: 7 | F20: TRUE | G20: TRUE | H20: 25.8 | I20: a | L20: p424876 | M20: 368 | N20: 2 | O20: 1 | P20: 1 | Q20: 3232 | R20: 36 | S20: 36 | T20: 35.911 | U20: 89.8 | V20: 160 | W20: 4.455 | X20: 6 | Y20: 7 | Z20: 7 | AA20: 9 | AB20: 52 | AC20: 21 | AD20: 21 | AE20: 0 | AF20: 780 | AG20: 762 | AH20: -18 | AI20: 160 | AJ20: 0.131 | AK20: 0.151 | AL20: 338 | AM20: 9.412 | AN20: 10 | AO20: 20 | AP20: 0.278 | AQ20: 0.389 | AR20: 0.278 | AS20: 0.947 | AT20: 1 | AU20: 14 | AV20: 5 | AW20: 3.75 | AX20: 13 | AY20: 4.76 | AZ20: 4.724 | BA20: 4.742 | BB20: 3.963 | BC20: 0.133 | BD20: 0.132 | BE20: 0.132 | BF20: 4.2 | BG20: 0.117 | BH20: 0.797 | BI20: 15.34 | BJ20: 3.793 | BK20: 0.106 | BL20: 1.258 | BM20: -0.56 | BN20: 1.8 | BO20: 0.036 | BP20: 71 | BQ20: 23 | BR20: 4 | BS20: 69 | BT20: 1.921 | BW20: 6.83 | BX20: 8.835 | BY20: 7.833 | BZ20: 0.218 | CA20: 12.575 | CB20: 0.35 | CC20: 78 | CD20: 14 | CE20: 78 | CF20: 68 | CG20: 2 | CH20: 104 | CI20: 21.543 | CJ20: 15.062 | CK20: 96 | CL20: 186 | CM20: 56 | CN20: 32 | CO20: 30 | CP20: 58 | CQ20: 8 | CR20: 131 | CS20: 19 | CT20: 0.6 | CU20: 2 | CV20: 5 | CW20: 45.63 | CX20: 1.271 | CY20: 0 | DB20: 0 | DE20: 7.5 | DF20: 8 | DG20: 1 | DH20: 41 | DI20: 30 | DL20: 26 | DM20: 27 | DN20: 2 | DO20: 42.7 | DP20: 184.21 | DQ20: 92.1 | DR20: 184.2 | DS20: 0.01 | DT20: 3344 | DU20: 88 | DV20: flat | DW20: 19.4 | DX20: 18.89 | DY20: 19.18 | DZ20: -0.22 | EA20: 1607 | EB20: 9.15 | EC20: 1 | ED20: 80 | EE20: 3829 | EF20: TRUE | EG20: 99.9 | EH20: 21.4 | EI20: 23 | EJ20: 45.5 | EK20: 46.8 | EL20: 41.4 | EM20: 681.6 | EN20: 412.6 | EO20: 257 | EP20: 20.2
A21: Nico O'Reilly | B21: MCI | C21: DEF | D21: DEF | E21: 6.5 | F21: TRUE | G21: TRUE | H21: 21.4 | I21: a | L21: p472769 | M21: 387 | Q21: 2643 | R21: 34 | S21: 29 | T21: 29.367 | U21: 77.7 | V21: 160 | W21: 5.448 | X21: 5 | Y21: 4 | Z21: 3 | AA21: 14 | AB21: 25 | AC21: 10 | AD21: 11 | AE21: 1 | AF21: 567 | AG21: 549 | AH21: -18 | AI21: 161 | AJ21: 0.062 | AK21: 0.067 | AL21: 172 | AM21: 5.857 | AN21: 1 | AO21: 2 | AP21: 0.034 | AQ21: 0.034 | AR21: 0 | AS21: 0.763 | AT21: 0.824 | AU21: 16 | AV21: 5 | AW21: 4.41 | AX21: 17 | AY21: 6.12 | AZ21: 6.727 | BA21: 6.424 | BB21: 6.727 | BC21: 0.208 | BD21: 0.229 | BE21: 0.219 | BF21: 6.2 | BG21: 0.211 | BH21: 1.039 | BI21: 7.4 | BJ21: 6.358 | BK21: 0.217 | BL21: -1.424 | BM21: 0.08 | BN21: -1.2 | BO21: -0.607 | BP21: 41 | BQ21: 15 | BR21: 7 | BS21: 103 | BT21: 3.507 | BV21: 2 | BW21: 2.67 | BX21: 3.847 | BY21: 3.259 | BZ21: 0.111 | CA21: 9.682 | CB21: 0.33 | CC21: 23 | CD21: 6 | CE21: 23 | CF21: 9 | CG21: 1 | CI21: 21.241 | CJ21: 14.798 | CK21: 105 | CL21: 108 | CM21: 67 | CN21: 36 | CO21: 20 | CP21: 72 | CQ21: 12 | CR21: 161 | CS21: 51 | CT21: 0.4 | CV21: 1 | CW21: 34.97 | CX21: 1.191 | CY21: 0 | DB21: 0 | DE21: 7.17 | DF21: 5 | DG21: 0 | DH21: 45 | DI21: 18 | DL21: 24 | DM21: 34 | DN21: 1 | DO21: 22.2 | DP21: 142.55 | DQ21: 71.97 | DR21: 143.94 | DS21: -1.39 | DT21: 2753 | DU21: 72.45 | DV21: flat | DW21: 26.77 | DX21: 27.34 | DY21: 25.31 | DZ21: -1.47 | EA21: 1632 | EB21: 9.09 | EC21: 2 | ED21: 78.67 | EE21: 3836 | EF21: TRUE | EG21: 99.9 | EH21: 21.2 | EI21: 34 | EJ21: 64.5 | EK21: 25.7 | EL21: 114.9 | EM21: 411.5 | EN21: 811.1 | EO21: 273 | EP21: 16.5
A22: James Garner | B22: EVE | C22: MID | D22: MID | E22: 6 | F22: TRUE | G22: TRUE | H22: 25.4 | I22: i | J22: Groin injury - Expected back 22 Aug | K22: 0 | L22: p232928 | M22: 239 | N22: 3 | O22: 1 | P22: 1 | Q22: 3413 | R22: 38 | S22: 38 | T22: 37.922 | U22: 89.8 | V22: 159 | W22: 4.193 | X22: 2 | Y22: 7 | Z22: 7 | AA22: 11 | AB22: 50 | AC22: 13 | AD22: 12 | AE22: -1 | AF22: 818 | AG22: 788 | AH22: -30 | AI22: 158 | AJ22: 0.082 | AK22: 0.089 | AL22: 458 | AM22: 12.077 | AN22: 20 | AO22: 40 | AP22: 0.526 | AQ22: 0.632 | AR22: 0.526 | AS22: 1 | AT22: 1 | AU22: 10 | AV22: 3 | AW22: 2.89 | AX22: 16 | AY22: 2.1 | AZ22: 2.076 | BA22: 2.088 | BB22: 2.076 | BC22: 0.055 | BD22: 0.055 | BE22: 0.055 | BF22: 1.3 | BG22: 0.034 | BH22: 0.916 | BI22: 6.09 | BJ22: 1.923 | BK22: 0.051 | BL22: -0.088 | BM22: -0.8 | BN22: 0.7 | BO22: 0.024 | BP22: 45 | BQ22: 14 | BS22: 27 | BT22: 0.712 | BW22: 6.18 | BX22: 6.067 | BY22: 6.123 | BZ22: 0.161 | CA22: 8.211 | CB22: 0.217 | CC22: 56 | CD22: 12 | CE22: 56 | CF22: 53 | CG22: 3 | CH22: 110 | CI22: 11.283 | CJ22: 8.333 | CK22: 154 | CL22: 185 | CM22: 119 | CN22: 71 | CO22: 59 | CP22: 85 | CQ22: 10 | CR22: 209 | CS22: 30 | CT22: 0.4 | CV22: 1 | CW22: 56.18 | CX22: 1.481 | CY22: 0 | DB22: 0 | DE22: 7.4 | DF22: 12 | DG22: 0 | DH22: 39 | DI22: 42 | DL22: 18 | DM22: 15 | DO22: 0.4 | DP22: 137.8 | DQ22: 65.66 | DR22: 131.32 | DS22: 6.48 | DT22: 3310 | DU22: 87.1 | DV22: flat | DW22: 77.58 | DX22: 79.36 | DY22: 78.01 | DZ22: 0.43 | EA22: 431 | EB22: 21.43 | EC22: 9.78 | ED22: 120 | EE22: 827 | EF22: TRUE | EG22: 20.4 | EH22: 16.7 | EI22: 60 | EJ22: 75.8 | EK22: 126.4 | EL22: 60.9 | EM22: 1634.7 | EN22: 557.4 | EO22: 415.7 | EP22: 21.5
A23: Enzo Fernández | B23: CHE | C23: MID | D23: MID | E23: 7 | F23: TRUE | G23: TRUE | H23: 25.6 | I23: a | L23: p448047 | M23: 155 | N23: 2 | O23: 2 | P23: 2 | Q23: 3114 | R23: 36 | S23: 35 | T23: 34.6 | U23: 86.5 | V23: 157 | W23: 4.538 | X23: 10 | Y23: 5 | Z23: 4 | AA23: 8 | AB23: 46 | AC23: 19 | AD23: 19 | AE23: 0 | AF23: 700 | AG23: 697 | AH23: -3 | AI23: 157 | AJ23: 0.121 | AK23: 0.138 | AL23: 244 | AM23: 7.052 | AN23: 2 | AO23: 4 | AP23: 0.057 | AQ23: 0.171 | AR23: 0.057 | AS23: 0.921 | AT23: 0.972 | AU23: 19 | AV23: 5 | AW23: 3.76 | AX23: 13 | AY23: 11.26 | AZ23: 11.917 | BA23: 11.589 | BB23: 10.395 | BC23: 0.325 | BD23: 0.344 | BE23: 0.335 | BF23: 12.4 | BG23: 0.358 | BH23: 1.06 | BI23: 23.99 | BJ23: 11.932 | BK23: 0.345 | BL23: -1.589 | BM23: 1.14 | BN23: -2.4 | BO23: -0.657 | BP23: 72 | BQ23: 31 | BR23: 9 | BS23: 102 | BT23: 2.948 | BU23: 2 | BV23: 1 | BW23: 7.26 | BX23: 8.866 | BY23: 8.063 | BZ23: 0.233 | CA23: 19.652 | CB23: 0.568 | CC23: 68 | CD23: 11 | CE23: 68 | CF23: 16 | CG23: 11 | CH23: 55 | CI23: 27.902 | CJ23: 16.16 | CK23: 51 | CL23: 140 | CM23: 53 | CN23: 22 | CO23: 21 | CP23: 28 | CQ23: 2 | CR23: 137 | CS23: 26 | CT23: 0.4 | CW23: 44.89 | CX23: 1.297 | CY23: 0 | DB23: 0 | DE23: 7.3 | DF23: 10 | DG23: 0 | DH23: 36 | DI23: 45 | DL23: 13 | DM23: 41 | DN23: 1 | DO23: 5.6 | DP23: 150.5 | DQ23: 74.85 | DR23: 149.7 | DS23: 0.8 | DT23: 3146 | DU23: 82.8 | DV23: flat | DW23: 36.86 | DX23: 33.88 | DY23: 37.22 | DZ23: 0.36 | EA23: 1415 | EB23: 20.1 | EC23: 1.5 | ED23: 120 | EE23: 2487 | EF23: TRUE | EG23: 98.5 | EH23: 48.2 | EI23: 24 | EJ23: 43.2 | EK23: 30.5 | EL23: 45.8 | EM23: 268.7 | EN23: 386.2 | EO23: 158.5 | EP23: 19.8
A24: Bukayo Saka | B24: ARS | C24: MID | D24: MID | E24: 9.5 | F24: TRUE | G24: TRUE | H24: 25 | I24: a | L24: p223340 | M24: 12 | N24: 1 | O24: 2 | P24: 2 | Q24: 2218 | R24: 31 | S24: 25 | T24: 24.644 | U24: 71.5 | V24: 157 | W24: 6.371 | X24: 7 | Y24: 10 | Z24: 5 | AA24: 12 | AB24: 16 | AC24: 18 | AD24: 16 | AE24: -2 | AF24: 570 | AG24: 565 | AH24: -5 | AI24: 155 | AJ24: 0.115 | AK24: 0.129 | AL24: 184 | AM24: 7.466 | AN24: 5 | AO24: 10 | AP24: 0.2 | AQ24: 0.2 | AR24: 0.2 | AS24: 0.658 | AT24: 0.742 | AU24: 8 | AV24: 5 | AW24: 3.69 | AX24: 12 | AY24: 7.57 | AZ24: 8.701 | BA24: 8.136 | BB24: 7.94 | BC24: 0.307 | BD24: 0.353 | BE24: 0.33 | BF24: 6.1 | BG24: 0.248 | BH24: 0.963 | BI24: 41.33 | BJ24: 7.289 | BK24: 0.296 | BL24: -1.136 | BM24: -1.47 | BN24: 0.9 | BO24: -1.131 | BP24: 71 | BQ24: 27 | BR24: 8 | BS24: 185 | BT24: 7.507 | BU24: 1 | BV24: 1 | BW24: 7.16 | BX24: 8.553 | BY24: 7.856 | BZ24: 0.319 | CA24: 15.992 | CB24: 0.649 | CC24: 62 | CD24: 12 | CE24: 61 | CF24: 40 | CG24: 2 | CH24: 65 | CI24: 19.113 | CJ24: 8.038 | CK24: 28 | CL24: 116 | CM24: 40 | CN24: 21 | CO24: 16 | CP24: 11 | CQ24: 1 | CR24: 167 | CS24: 22 | CT24: 1.1 | CV24: 1 | CW24: 15.57 | CX24: 0.632 | CY24: 0 | DB24: 0 | DE24: 7.52 | DF24: 2 | DG24: 0 | DH24: 33 | DI24: 54 | DJ24: 0 | DL24: 50 | DM24: 32 | DN24: 14 | DO24: 10.6 | DP24: 191.85 | DQ24: 94.81 | DR24: 189.62 | DS24: 2.23 | DT24: 2827 | DU24: 74.4 | DV24: flat | DW24: 6.19 | DX24: 5.05 | DY24: 5.87 | DZ24: -0.33 | EA24: 1334 | EB24: 6.79 | EC24: 0.5 | ED24: 120 | EE24: 2394 | EF24: TRUE | EG24: 99.9 | EH24: 50.8 | EI24: 3 | EJ24: 31.2 | EK24: 12 | EL24: 36.4 | EM24: 272.6 | EN24: 282.3 | EO24: 138.7 | EP24: 14.1
A25: Maxence Lacroix | B25: CHE | C25: DEF | D25: DEF | E25: 6 | F25: TRUE | G25: TRUE | H25: 26.4 | I25: a | L25: p437499 | M25: 200 | Q25: 3085 | R25: 35 | S25: 35 | T25: 34.278 | U25: 88.1 | V25: 154 | W25: 4.493 | X25: 1 | Y25: 2 | Z25: 2 | AA25: 11 | AB25: 47 | AC25: 11 | AD25: 12 | AE25: 1 | AF25: 529 | AG25: 474 | AH25: -55 | AI25: 155 | AJ25: 0.071 | AK25: 0.077 | AL25: 370 | AM25: 10.794 | AN25: 20 | AO25: 40 | AP25: 0.571 | AQ25: 0.571 | AR25: 0.371 | AS25: 0.921 | AT25: 0.971 | AU25: 12 | AV25: 4 | AW25: 3.4 | AX25: 11 | AY25: 2.45 | AZ25: 3.007 | BA25: 2.728 | BB25: 3.007 | BC25: 0.071 | BD25: 0.088 | BE25: 0.08 | BF25: 1.5 | BG25: 0.044 | BH25: 0.803 | BI25: 5.95 | BJ25: 1.967 | BK25: 0.057 | BL25: -1.728 | BM25: -0.95 | BN25: -0.5 | BO25: -0.557 | BP25: 24 | BQ25: 7 | BR25: 2 | BS25: 74 | BT25: 2.159 | BV25: 1 | BW25: 0.83 | BX25: 1.287 | BY25: 1.058 | BZ25: 0.031 | CA25: 3.787 | CB25: 0.11 | CC25: 7 | CD25: 3 | CE25: 7 | CF25: 2 | CI25: 10.744 | CJ25: 9.981 | CK25: 310 | CL25: 96 | CM25: 60 | CN25: 38 | CO25: 45 | CP25: 252 | CQ25: 18 | CR25: 204 | CS25: 119 | CT25: 0 | CU25: 1 | CV25: 2 | CW25: 44.04 | CX25: 1.285 | CY25: 0 | DB25: 0 | DE25: 7.04 | DF25: 4 | DG25: 1 | DH25: 34 | DI25: 19 | DK25: 2 | DL25: 7 | DM25: 6 | DO25: 11.2 | DP25: 104.52 | DQ25: 52.6 | DR25: 105.2 | DS25: -0.68 | DT25: 2189 | DU25: 57.6 | DV25: flat | DW25: 47.76 | DX25: 48.16 | DY25: 45.65 | DZ25: -2.11 | EA25: 1563 | EB25: 14.6 | EC25: 5.09 | ED25: 115.43 | EE25: 3223 | EF25: TRUE | EG25: 99.9 | EH25: 33.8 | EI25: 61 | EJ25: 128.5 | EK25: 41.7 | EL25: 440.7 | EM25: 1130.7 | EN25: 2914.7 | EO25: 814.7 | EP25: 20
A26: Bruno Guimarães | B26: ARS | C26: MID | D26: MID | E26: 7 | F26: TRUE | G26: TRUE | H26: 28.8 | I26: a | L26: p208706 | M26: 452 | Q26: 2456 | R26: 29 | S26: 27 | T26: 27.289 | U26: 84.7 | V26: 154 | W26: 5.643 | X26: 9 | Y26: 7 | Z26: 5 | AA26: 6 | AB26: 37 | AC26: 22 | AD26: 22 | AE26: 0 | AF26: 681 | AG26: 673 | AH26: -8 | AI26: 154 | AJ26: 0.143 | AK26: 0.167 | AL26: 251 | AM26: 9.198 | AN26: 5 | AO26: 10 | AP26: 0.185 | AQ26: 0.481 | AR26: 0.185 | AS26: 0.711 | AT26: 0.931 | AU26: 9 | AV26: 8 | AW26: 4.02 | AX26: 14 | AY26: 5.59 | AZ26: 6.597 | BA26: 6.094 | BB26: 5.075 | BC26: 0.205 | BD26: 0.242 | BE26: 0.223 | BF26: 8.6 | BG26: 0.315 | BH26: 1.107 | BI26: 17.66 | BJ26: 6.187 | BK26: 0.227 | BL26: 2.906 | BM26: 3.01 | BN26: 0.4 | BO26: -1.007 | BP26: 42 | BQ26: 23 | BR26: 4 | BS26: 55 | BT26: 2.015 | BU26: 2 | BV26: 2 | BW26: 4.96 | BX26: 3.869 | BY26: 4.415 | BZ26: 0.162 | CA26: 10.508 | CB26: 0.385 | CC26: 44 | CD26: 7 | CE26: 45 | CF26: 21 | CG26: 8 | CH26: 44 | CI26: 14.098 | CJ26: 9.366 | CK26: 55 | CL26: 134 | CM26: 62 | CN26: 43 | CO26: 15 | CP26: 36 | CQ26: 3 | CR26: 168 | CS26: 13 | CT26: 0.7 | CW26: 31.99 | CX26: 1.172 | CY26: 0 | DB26: 0 | DE26: 7.52 | DF26: 6 | DG26: 0 | DH26: 45 | DI26: 75 | DJ26: 2 | DL26: 18 | DM26: 46 | DN26: 2 | DO26: 10.3 | DP26: 144.73 | DQ26: 72.49 | DR26: 144.98 | DS26: -0.25 | DT26: 2816 | DU26: 74.1 | DV26: flat | DW26: 29.88 | DX26: 27.86 | DY26: 29.67 | DZ26: -0.2 | EA26: 1510 | EB26: 16.13 | EC26: 1.6 | ED26: 117.33 | EE26: 2978 | EF26: TRUE | EG26: 99.1 | EH26: 38.3 | EI26: 25 | EJ26: 58.5 | EK26: 44.7 | EL26: 54.6 | EM26: 403 | EN26: 556.3 | EO26: 233.7 | EP26: 15.9
A27: Matheus Nunes | B27: MCI | C27: DEF | D27: DEF | E27: 6 | F27: TRUE | G27: TRUE | H27: 28 | I27: a | L27: p465351 | M27: 389 | N27: 5 | Q27: 2861 | R27: 34 | S27: 32 | T27: 31.789 | U27: 84.1 | V27: 154 | W27: 4.844 | X27: 1 | Y27: 8 | Z27: 5 | AA27: 12 | AB27: 28 | AC27: 16 | AD27: 16 | AE27: 0 | AF27: 676 | AG27: 653 | AH27: -23 | AI27: 154 | AJ27: 0.104 | AK27: 0.116 | AL27: 195 | AM27: 6.134 | AN27: 4 | AO27: 8 | AP27: 0.125 | AQ27: 0.125 | AR27: 0 | AS27: 0.842 | AT27: 0.882 | AU27: 16 | AV27: 5 | AW27: 3.74 | AX27: 13 | AY27: 0.34 | AZ27: 0.675 | BA27: 0.508 | BB27: 0.675 | BC27: 0.011 | BD27: 0.021 | BE27: 0.016 | BF27: 1 | BG27: 0.031 | BH27: 0.98 | BI27: 4.75 | BJ27: 0.333 | BK27: 0.01 | BL27: 0.492 | BM27: 0.66 | BN27: 0 | BO27: -0.335 | BP27: 7 | BQ27: 2 | BS27: 40 | BT27: 1.258 | BW27: 2.23 | BX27: 3.099 | BY27: 2.665 | BZ27: 0.084 | CA27: 3.172 | CB27: 0.1 | CC27: 28 | CD27: 6 | CE27: 28 | CF27: 16 | CG27: 2 | CH27: 1 | CI27: 22.104 | CJ27: 20.289 | CK27: 138 | CL27: 166 | CM27: 57 | CN27: 40 | CO27: 30 | CP27: 100 | CQ27: 8 | CR27: 157 | CS27: 42 | CT27: 0.3 | CU27: 1 | CV27: 2 | CW27: 34.89 | CX27: 1.098 | CY27: 0 | DB27: 0 | DE27: 7.45 | DF27: 5 | DG27: 0 | DH27: 17 | DI27: 30 | DJ27: 1 | DK27: 1 | DL27: 28 | DM27: 18 | DN27: 4 | DO27: 4.6 | DP27: 138.68 | DQ27: 69.34 | DR27: 138.68 | DS27: 0 | DT27: 2896 | DU27: 76.2 | DV27: flat | DW27: 51.35 | DX27: 51.95 | DY27: 50.23 | DZ27: -1.12 | EA27: 1542 | EB27: 16.42 | EC27: 8 | ED27: 120 | EE27: 2920 | EF27: TRUE | EG27: 99.5 | EH27: 39.8 | EI27: 62 | EJ27: 408.7 | EK27: 71.5 | EL27: 102.2 | EM27: 5634.8 | EN27: 1073.7 | EO27: 901.9 | EP27: 18.6
A28: Nordi Mukiele | B28: SUN | C28: DEF | D28: DEF | E28: 5.5 | F28: TRUE | G28: TRUE | H28: 28.8 | I28: d | J28: Knock - 75% chance of playing | K28: 75 | L28: p200834 | M28: 533 | Q28: 2784 | R28: 32 | S28: 32 | T28: 30.933 | U28: 87 | V28: 151 | W28: 4.881 | X28: 3 | Y28: 5 | Z28: 4 | AA28: 9 | AB28: 40 | AC28: 11 | AD28: 11 | AE28: 0 | AF28: 489 | AG28: 452 | AH28: -37 | AI28: 151 | AJ28: 0.073 | AK28: 0.079 | AL28: 273 | AM28: 8.825 | AN28: 13 | AO28: 26 | AP28: 0.406 | AQ28: 0.406 | AR28: 0.281 | AS28: 0.842 | AT28: 0.969 | AU28: 11 | AV28: 5 | AW28: 4.29 | AX28: 17 | AY28: 1.62 | AZ28: 2.779 | BA28: 2.199 | BB28: 2.779 | BC28: 0.052 | BD28: 0.09 | BE28: 0.071 | BF28: 1.3 | BG28: 0.042 | BH28: 0.967 | BI28: 1.62 | BJ28: 1.566 | BK28: 0.051 | BL28: 0.801 | BM28: -0.32 | BN28: 1.7 | BO28: -1.159 | BP28: 26 | BQ28: 4 | BR28: 3 | BS28: 58 | BT28: 1.875 | BV28: 1 | BW28: 2.65 | BX28: 2.753 | BY28: 2.701 | BZ28: 0.087 | CA28: 4.901 | CB28: 0.158 | CC28: 23 | CD28: 7 | CE28: 24 | CF28: 14 | CG28: 2 | CI28: 9.077 | CJ28: 6.989 | CK28: 204 | CL28: 131 | CM28: 69 | CN28: 46 | CO28: 40 | CP28: 156 | CQ28: 10 | CR28: 183 | CS28: 79 | CT28: 0.1 | CU28: 1 | CV28: 2 | CW28: 44.71 | CX28: 1.445 | CY28: 0 | DB28: 0 | DE28: 7.13 | DF28: 5 | DG28: 0 | DH28: 35 | DI28: 26 | DL28: 13 | DM28: 15 | DN28: 3 | DO28: 4.4 | DP28: 137.29 | DQ28: 68.65 | DR28: 137.3 | DS28: -0.01 | DT28: 3312 | DU28: 87.15 | DV28: flat | DW28: 73.43 | DX28: 70.7 | DY28: 79.32 | DZ28: 5.89 | EA28: 978 | EB28: 19.25 | EC28: 10.67 | ED28: 120 | EE28: 2071 | EF28: TRUE | EG28: 92.4 | EH28: 54 | EI28: 112 | EJ28: 107.1 | EK28: 48 | EL28: 116 | EM28: 1265.8 | EN28: 1030.6 | EO28: 568.1 | EP28: 18.4
A29: Kiernan Dewsbury-Hall | B29: EVE | C29: MID | D29: MID | E29: 6.5 | F29: TRUE | G29: TRUE | H29: 28 | I29: a | L29: p215413 | M29: 236 | O29: 2 | Q29: 2629 | R29: 31 | S29: 30 | T29: 29.211 | U29: 84.8 | V29: 151 | W29: 5.169 | X29: 8 | Y29: 7 | Z29: 4 | AA29: 8 | AB29: 39 | AC29: 18 | AD29: 18 | AE29: 0 | AF29: 598 | AG29: 589 | AH29: -9 | AI29: 151 | AJ29: 0.119 | AK29: 0.135 | AL29: 230 | AM29: 7.874 | AN29: 5 | AO29: 10 | AP29: 0.167 | AQ29: 0.367 | AR29: 0.167 | AS29: 0.789 | AT29: 0.935 | AU29: 16 | AV29: 4 | AW29: 4.28 | AX29: 16 | AY29: 4.35 | AZ29: 4.33 | BA29: 4.34 | BB29: 4.33 | BC29: 0.149 | BD29: 0.148 | BE29: 0.149 | BF29: 4.8 | BG29: 0.164 | BH29: 1.024 | BI29: 6.74 | BJ29: 4.456 | BK29: 0.153 | BL29: 3.66 | BM29: 0.45 | BN29: 3.2 | BO29: 0.02 | BP29: 39 | BQ29: 15 | BR29: 3 | BS29: 84 | BT29: 2.876 | BW29: 5.34 | BX29: 6.575 | BY29: 5.957 | BZ29: 0.204 | CA29: 10.297 | CB29: 0.353 | CC29: 36 | CD29: 10 | CE29: 37 | CF29: 21 | CG29: 1 | CH29: 43 | CI29: 14.278 | CJ29: 8.121 | CK29: 44 | CL29: 134 | CM29: 52 | CN29: 25 | CO29: 12 | CP29: 28 | CQ29: 4 | CR29: 147 | CS29: 21 | CT29: 0.7 | CV29: 1 | CW29: 40.38 | CX29: 1.382 | CY29: 0 | DB29: 0 | DE29: 7.17 | DF29: 6 | DG29: 0 | DH29: 32 | DI29: 48 | DK29: 1 | DL29: 27 | DM29: 49 | DN29: 2 | DO29: 3.7 | DP29: 146.14 | DQ29: 73.2 | DR29: 146.4 | DS29: -0.26 | DT29: 3152 | DU29: 82.95 | DV29: flat | DW29: 51.14 | DX29: 48.49 | DY29: 51.24 | DZ29: 0.11 | EA29: 1311 | EB29: 21.38 | EC29: 3.5 | ED29: 120 | EE29: 2396 | EF29: TRUE | EG29: 93.5 | EH29: 47.4 | EI29: 35 | EJ29: 67.4 | EK29: 31.3 | EL29: 71.1 | EM29: 605.8 | EN29: 441.3 | EO29: 255.3 | EP29: 17.4
A30: Jurriën Timber | B30: ARS | C30: DEF | D30: DEF | E30: 6.5 | F30: TRUE | G30: TRUE | H30: 25.2 | I30: i | J30: Groin injury - Unknown return date | K30: 0 | L30: p445122 | M30: 5 | Q30: 2452 | R30: 30 | S30: 28 | T30: 27.244 | U30: 81.7 | V30: 149 | W30: 5.469 | X30: 3 | Y30: 6 | Z30: 5 | AA30: 13 | AB30: 20 | AC30: 9 | AD30: 10 | AE30: 1 | AF30: 532 | AG30: 514 | AH30: -18 | AI30: 150 | AJ30: 0.06 | AK30: 0.064 | AL30: 148 | AM30: 5.432 | AN30: 3 | AO30: 6 | AP30: 0.107 | AQ30: 0.107 | AR30: 0.036 | AS30: 0.737 | AT30: 0.867 | AU30: 12 | AV30: 3 | AW30: 4.75 | AX30: 24 | AY30: 4.71 | AZ30: 4.031 | BA30: 4.37 | BB30: 4.031 | BC30: 0.173 | BD30: 0.148 | BE30: 0.16 | BF30: 4.2 | BG30: 0.154 | BH30: 0.933 | BI30: 5.94 | BJ30: 4.392 | BK30: 0.161 | BL30: -1.37 | BM30: -0.51 | BN30: -1.2 | BO30: 0.679 | BP30: 25 | BQ30: 7 | BR30: 7 | BS30: 91 | BT30: 3.34 | BV30: 2 | BW30: 1.53 | BX30: 2.589 | BY30: 2.06 | BZ30: 0.076 | CA30: 6.43 | CB30: 0.236 | CC30: 28 | CD30: 4 | CE30: 27 | CF30: 6 | CG30: 3 | CH30: 1 | CI30: 11.439 | CJ30: 8.659 | CK30: 82 | CL30: 97 | CM30: 66 | CN30: 37 | CO30: 24 | CP30: 53 | CQ30: 6 | CR30: 147 | CS30: 40 | CT30: 0.3 | CV30: 1 | CW30: 17.45 | CX30: 0.64 | CY30: 0 | DB30: 0 | DE30: 7.26 | DF30: 5 | DG30: 0 | DH30: 38 | DI30: 29 | DJ30: 1 | DL30: 13 | DM30: 25 | DN30: 0 | DO30: 0.3 | DP30: 154.51 | DQ30: 74.34 | DR30: 148.68 | DS30: 5.83 | DT30: 2878 | DU30: 75.75 | DV30: flat | DW30: 54.07 | DX30: 48.52 | DY30: 63.1 | DZ30: 9.02 | EA30: 1034 | EB30: 23.71 | EC30: 5.6 | ED30: 120 | EE30: 2178 | EF30: TRUE | EG30: 95.2 | EH30: 53.1 | EI30: 36 | EJ30: 98.1 | EK30: 26.9 | EL30: 90.8 | EM30: 561 | EN30: 1190.5 | EO30: 381.3 | EP30: 16.5
A31: Bryan Mbeumo | B31: MUN | C31: MID | D31: MID | E31: 8 | F31: TRUE | G31: TRUE | H31: 27 | I31: a | L31: p446008 | M31: 427 | N31: 2 | O31: 2 | P31: 2 | Q31: 2611 | R31: 33 | S31: 31 | T31: 29.011 | U31: 79.1 | V31: 148 | W31: 5.101 | X31: 11 | Y31: 3 | Z31: 3 | AA31: 8 | AB31: 37 | AC31: 16 | AD31: 17 | AE31: 1 | AF31: 528 | AG31: 525 | AH31: -3 | AI31: 149 | AJ31: 0.108 | AK31: 0.121 | AL31: 139 | AM31: 4.791 | AN31: 0 | AO31: 0 | AP31: 0 | AQ31: 0.032 | AR31: 0 | AS31: 0.816 | AT31: 0.939 | AU31: 17 | AV31: 3 | AW31: 3.7 | AX31: 15 | AY31: 11.98 | AZ31: 13.309 | BA31: 12.645 | BB31: 13.309 | BC31: 0.413 | BD31: 0.459 | BE31: 0.436 | BF31: 9.9 | BG31: 0.341 | BH31: 1.029 | BI31: 43.68 | BJ31: 12.332 | BK31: 0.425 | BL31: -1.645 | BM31: -2.08 | BN31: 1.1 | BO31: -1.329 | BP31: 73 | BQ31: 32 | BR31: 13 | BS31: 150 | BT31: 5.17 | BV31: 1 | BW31: 4.99 | BX31: 5.091 | BY31: 5.041 | BZ31: 0.174 | CA31: 17.685 | CB31: 0.61 | CC31: 45 | CD31: 6 | CE31: 47 | CF31: 35 | CG31: 6 | CH31: 49 | CI31: 22.316 | CJ31: 6.068 | CK31: 23 | CL31: 91 | CM31: 25 | CN31: 11 | CO31: 8 | CP31: 14 | CQ31: 1 | CR31: 86 | CS31: 15 | CT31: 0.7 | CV31: 1 | CW31: 35.87 | CX31: 1.236 | CY31: 0 | DB31: 0 | DE31: 7.19 | DF31: 4 | DG31: 0 | DH31: 23 | DI31: 28 | DJ31: 1 | DL31: 18 | DM31: 29 | DN31: 7 | DO31: 26.7 | DP31: 166.11 | DQ31: 83.42 | DR31: 166.84 | DS31: -0.73 | DT31: 2822 | DU31: 74.25 | DV31: flat | DW31: 12.94 | DX31: 11.86 | DY31: 12.14 | DZ31: -0.81 | EA31: 1530 | EB31: 8.41 | EC31: 1.33 | ED31: 108 | EE31: 3137 | EF31: TRUE | EG31: 99.9 | EH31: 35.6 | EI31: 11 | EJ31: 35.8 | EK31: 17.4 | EL31: 55.6 | EM31: 206.5 | EN31: 518 | EO31: 147.6 | EP31: 17.6
A32: Jan Paul van Hecke | B32: TOT | C32: DEF | D32: DEF | E32: 5 | F32: TRUE | G32: TRUE | H32: 26.2 | I32: a | L32: p469142 | M32: 112 | Q32: 3210 | R32: 36 | S32: 36 | T32: 35.667 | U32: 89.2 | V32: 148 | W32: 4.15 | X32: 3 | Y32: 3 | Z32: 3 | AA32: 10 | AB32: 44 | AC32: 8 | AD32: 7 | AE32: -1 | AF32: 575 | AG32: 529 | AH32: -46 | AI32: 147 | AJ32: 0.054 | AK32: 0.057 | AL32: 317 | AM32: 8.888 | AN32: 13 | AO32: 26 | AP32: 0.361 | AQ32: 0.361 | AR32: 0.194 | AS32: 0.947 | AT32: 1 | AU32: 14 | AV32: 2 | AW32: 3 | AX32: 12 | AY32: 3.31 | AZ32: 3.359 | BA32: 3.334 | BB32: 3.359 | BC32: 0.093 | BD32: 0.094 | BE32: 0.093 | BF32: 3.8 | BG32: 0.107 | BH32: 0.973 | BI32: 6.6 | BJ32: 3.219 | BK32: 0.09 | BL32: -0.334 | BM32: 0.49 | BN32: -0.8 | BO32: -0.049 | BP32: 23 | BQ32: 10 | BR32: 3 | BS32: 50 | BT32: 1.402 | BV32: 1 | BW32: 1.57 | BX32: 1.026 | BY32: 1.298 | BZ32: 0.036 | CA32: 4.632 | CB32: 0.13 | CC32: 12 | CD32: 2 | CE32: 13 | CF32: 10 | CI32: 14.122 | CJ32: 13.214 | CK32: 264 | CL32: 113 | CM32: 53 | CN32: 30 | CO32: 47 | CP32: 189 | CQ32: 28 | CR32: 209 | CS32: 114 | CT32: 0.1 | CU32: 4 | CW32: 46.27 | CX32: 1.297 | CY32: 0 | DB32: 0 | DE32: 7.1 | DF32: 9 | DG32: 0 | DH32: 27 | DI32: 43 | DK32: 1 | DL32: 3 | DM32: 6 | DN32: 4 | DO32: 8.6 | DP32: 142.34 | DQ32: 71.17 | DR32: 142.34 | DS32: 0 | DT32: 3181 | DU32: 83.7 | DV32: flat | DW32: 77.47 | DX32: 83.11 | DY32: 73 | DZ32: -4.47 | EA32: 1465 | EB32: 21.4 | EC32: 7 | ED32: 120 | EE32: 3191 | EF32: TRUE | EG32: 87.2 | EH32: 24.9 | EI32: 223 | EJ32: 139.6 | EK32: 64.2 | EL32: 246.9 | EM32: 962.7 | EN32: 2473.4 | EO32: 693 | EP32: 21.7
A33: Enzo Le Fée | B33: SUN | C33: MID | D33: MID | E33: 6 | F33: TRUE | G33: TRUE | H33: 26.5 | I33: a | L33: p484420 | M33: 542 | N33: 2 | O33: 1 | P33: 2 | Q33: 2930 | R33: 36 | S33: 33 | T33: 32.556 | U33: 81.4 | V33: 147 | W33: 4.515 | X33: 5 | Y33: 6 | Z33: 6 | AA33: 10 | AB33: 43 | AC33: 16 | AD33: 15 | AE33: -1 | AF33: 621 | AG33: 602 | AH33: -19 | AI33: 146 | AJ33: 0.109 | AK33: 0.122 | AL33: 319 | AM33: 9.799 | AN33: 8 | AO33: 16 | AP33: 0.242 | AQ33: 0.424 | AR33: 0.242 | AS33: 0.868 | AT33: 0.917 | AU33: 18 | AV33: 4 | AW33: 3.43 | AX33: 13 | AY33: 5.22 | AZ33: 5.269 | BA33: 5.244 | BB33: 2.224 | BC33: 0.16 | BD33: 0.162 | BE33: 0.161 | BF33: 4.9 | BG33: 0.151 | BH33: 0.976 | BI33: 5.22 | BJ33: 5.094 | BK33: 0.156 | BL33: -0.244 | BM33: -0.32 | BN33: 0.1 | BO33: -0.049 | BP33: 36 | BQ33: 12 | BR33: 1 | BS33: 62 | BT33: 1.904 | BU33: 3 | BW33: 5.95 | BX33: 7.546 | BY33: 6.748 | BZ33: 0.207 | CA33: 11.993 | CB33: 0.368 | CC33: 53 | CD33: 13 | CE33: 53 | CF33: 25 | CG33: 9 | CH33: 50 | CI33: 13.18 | CJ33: 7.139 | CK33: 77 | CL33: 153 | CM33: 89 | CN33: 57 | CO33: 29 | CP33: 36 | CQ33: 12 | CR33: 157 | CS33: 18 | CT33: 0.7 | CU33: 1 | CV33: 3 | CW33: 46.5 | CX33: 1.428 | CY33: 0 | DB33: 0 | DE33: 7.14 | DF33: 5 | DG33: 0 | DH33: 31 | DI33: 37 | DL33: 13 | DM33: 31 | DN33: 4 | DO33: 12.8 | DP33: 153.32 | DQ33: 76.66 | DR33: 153.32 | DS33: 0 | DT33: 3324 | DU33: 87.48 | DV33: flat | DW33: 66.58 | DX33: 67.61 | DY33: 65.43 | DZ33: -1.14 | EA33: 1165 | EB33: 21.82 | EC33: 10 | ED33: 120 | EE33: 2833 | EF33: TRUE | EG33: 66.4 | EH33: 12.5 | EI33: 63 | EJ33: 81.4 | EK33: 47.3 | EL33: 55.3 | EM33: 558.7 | EN33: 434.2 | EO33: 244.3 | EP33: 19.9
A34: Ryan Gravenberch | B34: LIV | C34: MID | D34: MID | E34: 6 | F34: TRUE | G34: TRUE | H34: 24.3 | I34: a | L34: p441266 | M34: 371 | Q34: 2991 | R34: 36 | S34: 34 | T34: 33.233 | U34: 83.1 | V34: 144 | W34: 4.333 | X34: 5 | Y34: 5 | Z34: 3 | AA34: 9 | AB34: 42 | AC34: 17 | AD34: 17 | AE34: 0 | AF34: 671 | AG34: 651 | AH34: -20 | AI34: 144 | AJ34: 0.118 | AK34: 0.134 | AL34: 298 | AM34: 8.967 | AN34: 7 | AO34: 14 | AP34: 0.206 | AQ34: 0.382 | AR34: 0.206 | AS34: 0.895 | AT34: 0.917 | AU34: 17 | AV34: 4 | AW34: 3.38 | AX34: 15 | AY34: 1.89 | AZ34: 1.532 | BA34: 1.711 | BB34: 1.532 | BC34: 0.057 | BD34: 0.046 | BE34: 0.051 | BF34: 3.1 | BG34: 0.093 | BH34: 0.985 | BI34: 5.1 | BJ34: 1.861 | BK34: 0.056 | BL34: 3.289 | BM34: 1.21 | BN34: 1.9 | BO34: 0.358 | BP34: 38 | BQ34: 13 | BS34: 31 | BT34: 0.933 | BW34: 2.26 | BX34: 2.369 | BY34: 2.314 | BZ34: 0.07 | CA34: 4.025 | CB34: 0.121 | CC34: 29 | CD34: 4 | CE34: 29 | CF34: 0 | CG34: 3 | CI34: 13.042 | CJ34: 10.719 | CK34: 112 | CL34: 127 | CM34: 59 | CN34: 36 | CO34: 48 | CP34: 53 | CQ34: 12 | CR34: 160 | CS34: 27 | CT34: 0.3 | CV34: 4 | CW34: 38.41 | CX34: 1.156 | CY34: 0 | DB34: 0 | DE34: 7.25 | DF34: 5 | DG34: 0 | DH34: 38 | DI34: 42 | DL34: 32 | DM34: 26 | DO34: 2 | DP34: 121.71 | DQ34: 61.04 | DR34: 122.08 | DS34: -0.37 | DT34: 2964 | DU34: 78 | DV34: flat | DW34: 69.01 | DX34: 73.68 | DY34: 65.97 | DZ34: -3.05 | EA34: 956 | EB34: 22.65 | EC34: 2.67 | ED34: 120 | EE34: 1921 | EF34: TRUE | EG34: 43.8 | EH34: 10 | EI34: 64 | EJ34: 78.7 | EK34: 96.5 | EL34: 103.1 | EM34: 1748.3 | EN34: 1292.3 | EO34: 743.1 | EP34: 20.8
A35: Matheus Cunha | B35: MUN | C35: MID | D35: MID | E35: 8 | F35: TRUE | G35: TRUE | H35: 27.2 | I35: a | L35: p430871 | M35: 428 | Q35: 2493 | R35: 33 | S35: 29 | T35: 27.7 | U35: 75.5 | V35: 143 | W35: 5.162 | X35: 10 | Y35: 4 | Z35: 2 | AA35: 8 | AB35: 35 | AC35: 14 | AD35: 15 | AE35: 1 | AF35: 591 | AG35: 584 | AH35: -7 | AI35: 144 | AJ35: 0.098 | AK35: 0.109 | AL35: 211 | AM35: 7.617 | AN35: 1 | AO35: 2 | AP35: 0.034 | AQ35: 0.138 | AR35: 0.034 | AS35: 0.763 | AT35: 0.848 | AU35: 14 | AV35: 0 | AW35: 3.1 | AX35: 9 | AY35: 6.9 | AZ35: 7.076 | BA35: 6.988 | BB35: 7.076 | BC35: 0.249 | BD35: 0.255 | BE35: 0.252 | BF35: 7.2 | BG35: 0.26 | BH35: 1.053 | BI35: 26.84 | BJ35: 7.268 | BK35: 0.262 | BL35: 3.012 | BM35: 0.3 | BN35: 2.8 | BO35: -0.176 | BP35: 90 | BQ35: 35 | BR35: 4 | BS35: 137 | BT35: 4.946 | BW35: 3.36 | BX35: 3.698 | BY35: 3.529 | BZ35: 0.127 | CA35: 10.517 | CB35: 0.38 | CC35: 33 | CD35: 4 | CE35: 34 | CF35: 11 | CG35: 5 | CH35: 5 | CI35: 17.601 | CJ35: 10.044 | CK35: 46 | CL35: 126 | CM35: 39 | CN35: 23 | CO35: 21 | CP35: 22 | CQ35: 3 | CR35: 164 | CS35: 28 | CT35: 0.7 | CW35: 35.75 | CX35: 1.291 | CY35: 0 | DB35: 0 | DE35: 7.29 | DF35: 4 | DG35: 0 | DH35: 27 | DI35: 54 | DJ35: 2 | DL35: 44 | DM35: 53 | DN35: 2 | DO35: 12.2 | DP35: 153.17 | DQ35: 76.44 | DR35: 152.88 | DS35: 0.29 | DT35: 2616 | DU35: 68.85 | DV35: flat | DW35: 16.49 | DX35: 14.95 | DY35: 16.57 | DZ35: 0.08 | EA35: 1450 | EB35: 9.77 | EC35: 1.71 | ED35: 118.67 | EE35: 2768 | EF35: TRUE | EG35: 99.9 | EH35: 43.2 | EI35: 12 | EJ35: 27.7 | EK35: 18.2 | EL35: 73.3 | EM35: 356.8 | EN35: 706.4 | EO35: 237 | EP35: 17.4
A36: Caoimhín Kelleher | B36: BRE | C36: GKP | D36: GKP | E36: 5 | F36: TRUE | G36: TRUE | H36: 27.7 | I36: a | L36: p200720 | M36: 82 | Q36: 3330 | R36: 37 | S36: 37 | T36: 37 | U36: 90 | V36: 143 | W36: 3.865 | X36: 0 | Y36: 0 | AA36: 10 | AB36: 49 | AC36: 11 | AD36: 14 | AE36: 3 | AF36: 570 | AG36: 562 | AH36: -8 | AI36: 146 | AJ36: 0.077 | AK36: 0.083 | AL36: 0 | AM36: 0 | AN36: 0 | AO36: 0 | AP36: 0 | AQ36: 0 | AR36: 0 | AS36: 0.974 | AT36: 1 | AU36: 21 | AV36: 3 | AW36: 3.36 | AX36: 13 | AY36: 0 | AZ36: 0 | BA36: 0 | BB36: 0 | BC36: 0 | BD36: 0 | BE36: 0 | BH36: 1 | BI36: 0 | BJ36: 0 | BK36: 0 | BL36: 0 | BO36: 0 | BW36: 0.22 | BX36: 0.106 | BY36: 0.163 | BZ36: 0.004 | CA36: 0.163 | CB36: 0.004 | CC36: 2 | CE36: 2 | CG36: 1 | CI36: 5.348 | CJ36: 5.242 | CK36: 48 | CL36: 301 | CM36: 1 | CO36: 1 | CP36: 47 | CR36: 16 | CS36: 7 | CU36: 2 | CV36: 1 | CW36: 53.48 | CX36: 1.445 | CY36: 109 | CZ36: 69.2 | DA36: -0.1 | DB36: 3 | DC36: 27 | DD36: 31 | DE36: 6.93 | DF36: 1 | DG36: 0 | DH36: 3 | DI36: 6 | DK36: 3 | DL36: 3 | DO36: 5.7 | DP36: 127.72 | DQ36: 63.86 | DR36: 127.72 | DS36: 0 | DT36: 3385 | DU36: 89.09 | DV36: flat | DW36: 80.19 | DX36: 84.13 | DY36: 77.19 | DZ36: -2.99 | EA36: 1467 | EB36: 24.4 | EC36: 2.67 | ED36: 120 | EE36: 2818 | EF36: TRUE | EG36: 99.2 | EH36: 41.7 | EI36: 224 | EL36: 1665 | EN36: 20404.3 | EO36: 20404.3 | EP36: 23.3
A37: Dominic Calvert-Lewin | B37: LEE | C37: FWD | D37: FWD | E37: 6 | F37: TRUE | G37: TRUE | H37: 29.4 | I37: a | L37: p177815 | M37: 346 | N37: 1 | Q37: 2721 | R37: 35 | S37: 30 | T37: 30.233 | U37: 77.7 | V37: 142 | W37: 4.697 | X37: 14 | Y37: 2 | Z37: 1 | AA37: 8 | AB37: 34 | AC37: 20 | AD37: 20 | AE37: 0 | AF37: 472 | AG37: 464 | AH37: -8 | AI37: 142 | AJ37: 0.141 | AK37: 0.164 | AL37: 105 | AM37: 3.473 | AN37: 0 | AO37: 0 | AP37: 0 | AQ37: 0 | AR37: 0 | AS37: 0.789 | AT37: 0.857 | AU37: 22 | AV37: 2 | AW37: 3.38 | AX37: 13 | AY37: 15.57 | AZ37: 18.671 | BA37: 17.121 | BB37: 14.866 | BC37: 0.515 | BD37: 0.618 | BE37: 0.566 | BF37: 15.4 | BG37: 0.509 | BH37: 0.868 | BI37: 40.86 | BJ37: 13.511 | BK37: 0.447 | BL37: -3.121 | BM37: -0.17 | BN37: -1.4 | BO37: -3.101 | BP37: 74 | BQ37: 34 | BR37: 20 | BS37: 135 | BT37: 4.465 | BU37: 4 | BV37: 3 | BW37: 1.06 | BX37: 1.544 | BY37: 1.302 | BZ37: 0.043 | CA37: 18.423 | CB37: 0.609 | CC37: 20 | CD37: 2 | CE37: 20 | CF37: 1 | CG37: 1 | CH37: 0 | CI37: 18.026 | CJ37: 2.768 | CK37: 49 | CL37: 46 | CM37: 10 | CN37: 4 | CO37: 4 | CP37: 36 | CQ37: 9 | CR37: 184 | CS37: 128 | CT37: 0.6 | CV37: 1 | CW37: 35.74 | CX37: 1.182 | CY37: 0 | DB37: 0 | DE37: 6.85 | DF37: 3 | DG37: 0 | DH37: 45 | DI37: 38 | DJ37: 2 | DL37: 8 | DM37: 29 | DN37: 26 | DO37: 25.4 | DP37: 159.66 | DQ37: 79.83 | DR37: 159.66 | DS37: 0 | DT37: 3084 | DU37: 81.15 | DV37: flat | DW37: 35.52 | DX37: 34.78 | DY37: 32.72 | DZ37: -2.8 | EA37: 1625 | EB37: 17.66 | EC37: 2 | ED37: 118.86 | EE37: 3968 | EF37: TRUE | EG37: 99.6 | EH37: 18.3 | EI37: 65 | EJ37: 36.8 | EK37: 20.2 | EL37: 136 | EM37: 158.9 | EN37: 2089.8 | EO37: 147.7 | EP37: 19.2
A38: Marcus Tavernier | B38: BOU | C38: MID | D38: MID | E38: 6 | F38: TRUE | G38: TRUE | H38: 27.4 | I38: a | L38: p201658 | M38: 68 | N38: 3 | O38: 1 | P38: 1 | Q38: 2732 | R38: 34 | S38: 31 | T38: 30.356 | U38: 80.4 | V38: 137 | W38: 4.513 | X38: 7 | Y38: 4 | Z38: 4 | AA38: 11 | AB38: 44 | AC38: 14 | AD38: 14 | AE38: 0 | AF38: 552 | AG38: 543 | AH38: -9 | AI38: 137 | AJ38: 0.102 | AK38: 0.114 | AL38: 251 | AM38: 8.269 | AN38: 3 | AO38: 6 | AP38: 0.097 | AQ38: 0.194 | AR38: 0.097 | AS38: 0.816 | AT38: 0.912 | AU38: 16 | AV38: 4 | AW38: 3.28 | AX38: 12 | AY38: 9.06 | AZ38: 9.398 | BA38: 9.229 | BB38: 7.875 | BC38: 0.298 | BD38: 0.31 | BE38: 0.304 | BF38: 6.4 | BG38: 0.211 | BH38: 0.892 | BI38: 21.58 | BJ38: 8.086 | BK38: 0.266 | BL38: -2.229 | BM38: -2.66 | BN38: 0.6 | BO38: -0.338 | BP38: 70 | BQ38: 24 | BR38: 8 | BS38: 114 | BT38: 3.755 | BU38: 2 | BW38: 4.6 | BX38: 6.159 | BY38: 5.379 | BZ38: 0.177 | CA38: 14.608 | CB38: 0.481 | CC38: 52 | CD38: 9 | CE38: 54 | CF38: 19 | CG38: 3 | CH38: 63 | CI38: 17.828 | CJ38: 8.153 | CK38: 62 | CL38: 150 | CM38: 39 | CN38: 22 | CO38: 17 | CP38: 39 | CQ38: 6 | CR38: 138 | CS38: 24 | CT38: 0.9 | CW38: 41.06 | CX38: 1.353 | CY38: 0 | DB38: 0 | DE38: 7.24 | DF38: 6 | DG38: 0 | DH38: 30 | DI38: 35 | DL38: 39 | DM38: 44 | DN38: 4 | DO38: 1.8 | DP38: 159.9 | DQ38: 80.65 | DR38: 161.3 | DS38: -1.4 | DT38: 3061 | DU38: 80.55 | DV38: flat | DW38: 72.4 | DX38: 77.39 | DY38: 68.78 | DZ38: -3.63 | EA38: 1021 | EB38: 21.4 | EC38: 12.5 | ED38: 120 | EE38: 2050 | EF38: TRUE | EG38: 46.7 | EH38: 10 | EI38: 67 | EJ38: 39 | EK38: 24 | EL38: 50.6 | EM38: 296 | EN38: 507.9 | EO38: 187 | EP38: 19.9
A39: William Saliba | B39: ARS | C39: DEF | D39: DEF | E39: 6 | F39: TRUE | G39: TRUE | H39: 25.4 | I39: i | J39: Back injury - Unknown return date | K39: 0 | L39: p462424 | M39: 6 | Q39: 2614 | R39: 31 | S39: 30 | T39: 29.044 | U39: 84.3 | V39: 137 | W39: 4.717 | X39: 1 | Y39: 0 | AA39: 15 | AB39: 20 | AC39: 12 | AD39: 11 | AE39: -1 | AF39: 581 | AG39: 552 | AH39: -29 | AI39: 136 | AJ39: 0.088 | AK39: 0.096 | AL39: 193 | AM39: 6.645 | AN39: 4 | AO39: 8 | AP39: 0.133 | AQ39: 0.133 | AR39: 0.067 | AS39: 0.789 | AT39: 0.903 | AU39: 14 | AV39: 2 | AW39: 3.29 | AX39: 11 | AY39: 0.88 | AZ39: 1.578 | BA39: 1.229 | BB39: 1.578 | BC39: 0.03 | BD39: 0.054 | BE39: 0.042 | BF39: 0.9 | BG39: 0.031 | BH39: 0.949 | BI39: 5.91 | BJ39: 0.835 | BK39: 0.029 | BL39: -0.229 | BM39: 0.02 | BN39: 0.1 | BO39: -0.698 | BP39: 5 | BQ39: 1 | BR39: 2 | BS39: 22 | BT39: 0.757 | BV39: 1 | BW39: 1.21 | BX39: 1.306 | BY39: 1.258 | BZ39: 0.043 | CA39: 2.487 | CB39: 0.086 | CC39: 10 | CD39: 1 | CE39: 10 | CF39: 4 | CG39: 2 | CI39: 11.017 | CJ39: 10.502 | CK39: 158 | CL39: 113 | CM39: 35 | CN39: 22 | CO39: 17 | CP39: 133 | CQ39: 7 | CR39: 131 | CS39: 73 | CT39: 0.1 | CV39: 2 | CW39: 20.41 | CX39: 0.703 | CY39: 0 | DB39: 0 | DE39: 7.16 | DF39: 2 | DG39: 0 | DH39: 22 | DI39: 16 | DL39: 7 | DM39: 9 | DN39: 1 | DO39: 0.5 | DP39: 136.05 | DQ39: 57.06 | DR39: 114.12 | DS39: 21.93 | DT39: 3278 | DU39: 86.25 | DV39: ramp-up (injury / late WC return) | DW39: 68.04 | DX39: 64.1 | DY39: 72.69 | DZ39: 4.65 | EA39: 835 | EB39: 25.43 | EC39: 3.43 | ED39: 120 | EE39: 1552 | EF39: TRUE | EG39: 88 | EH39: 63.8 | EI39: 66 | EJ39: 522.8 | EK39: 118.8 | EL39: 261.4 | EM39: 2127.1 | EN39: 2077.9 | EO39: 1051.1 | EP39: 19.1
A40: Anton Stach | B40: LEE | C40: MID | D40: MID | E40: 6 | F40: TRUE | G40: TRUE | H40: 27.8 | I40: a | L40: p466525 | M40: 335 | O40: 1 | P40: 1 | Q40: 2369 | R40: 29 | S40: 28 | T40: 26.322 | U40: 81.7 | V40: 137 | W40: 5.205 | X40: 5 | Y40: 6 | Z40: 3 | AA40: 7 | AB40: 36 | AC40: 14 | AD40: 14 | AE40: 0 | AF40: 550 | AG40: 534 | AH40: -16 | AI40: 137 | AJ40: 0.102 | AK40: 0.114 | AL40: 266 | AM40: 10.106 | AN40: 10 | AO40: 20 | AP40: 0.357 | AQ40: 0.5 | AR40: 0.357 | AS40: 0.737 | AT40: 0.931 | AU40: 11 | AV40: 4 | AW40: 3.75 | AX40: 15 | AY40: 2.88 | AZ40: 2.921 | BA40: 2.9 | BB40: 2.921 | BC40: 0.109 | BD40: 0.111 | BE40: 0.11 | BF40: 2.9 | BG40: 0.11 | BH40: 1.002 | BI40: 2.88 | BJ40: 2.885 | BK40: 0.11 | BL40: 2.1 | BM40: 0.02 | BN40: 2.1 | BO40: -0.041 | BP40: 55 | BQ40: 14 | BR40: 1 | BS40: 55 | BT40: 2.089 | BW40: 4.47 | BX40: 5.958 | BY40: 5.214 | BZ40: 0.198 | CA40: 8.114 | CB40: 0.308 | CC40: 61 | CD40: 9 | CE40: 63 | CF40: 45 | CG40: 2 | CH40: 102 | CI40: 10.148 | CJ40: 6.207 | CK40: 81 | CL40: 120 | CM40: 65 | CN40: 36 | CO40: 20 | CP40: 52 | CQ40: 9 | CR40: 155 | CS40: 48 | CT40: 0.9 | CV40: 1 | CW40: 34.05 | CX40: 1.294 | CY40: 0 | DB40: 0 | DE40: 7.31 | DF40: 3 | DG40: 0 | DH40: 36 | DI40: 24 | DK40: 1 | DL40: 20 | DM40: 26 | DO40: 1.1 | DP40: 133.2 | DQ40: 66.6 | DR40: 133.2 | DS40: 0 | DT40: 2964 | DU40: 78 | DV40: flat | DW40: 75.38 | DX40: 79.63 | DY40: 73.31 | DZ40: -2.07 | EA40: 739 | EB40: 20.67 | EC40: 11.33 | ED40: 120 | EE40: 1480 | EF40: TRUE | EG40: 34.4 | EH40: 11.6 | EI40: 68 | EJ40: 43.1 | EK40: 43.1 | EL40: 37.6 | EM40: 816.8 | EN40: 454.3 | EO40: 291.9 | EP40: 17.3
A41: Daniel Muñoz | B41: CRY | C41: DEF | D41: DEF | E41: 5.5 | F41: TRUE | G41: TRUE | H41: 30.2 | I41: a | L41: p247348 | M41: 201 | Q41: 2400 | R41: 29 | S41: 29 | T41: 26.667 | U41: 82.8 | V41: 136 | W41: 5.1 | X41: 4 | Y41: 4 | Z41: 3 | AA41: 10 | AB41: 33 | AC41: 9 | AD41: 9 | AE41: 0 | AF41: 469 | AG41: 448 | AH41: -21 | AI41: 136 | AJ41: 0.066 | AK41: 0.071 | AL41: 196 | AM41: 7.35 | AN41: 7 | AO41: 14 | AP41: 0.241 | AQ41: 0.241 | AR41: 0.103 | AS41: 0.763 | AT41: 0.897 | AU41: 13 | AV41: 3 | AW41: 3.92 | AX41: 14 | AY41: 2.45 | AZ41: 3.147 | BA41: 2.799 | BB41: 3.147 | BC41: 0.092 | BD41: 0.118 | BE41: 0.105 | BF41: 3.7 | BG41: 0.139 | BH41: 0.884 | BI41: 8.63 | BJ41: 2.166 | BK41: 0.081 | BL41: 1.201 | BM41: 1.25 | BN41: 0.3 | BO41: -0.697 | BP41: 27 | BQ41: 13 | BR41: 1 | BS41: 75 | BT41: 2.812 | BV41: 1 | BW41: 3.94 | BX41: 5.066 | BY41: 4.503 | BZ41: 0.169 | CA41: 7.302 | CB41: 0.274 | CC41: 27 | CD41: 8 | CE41: 27 | CF41: 14 | CI41: 10.426 | CJ41: 4.438 | CK41: 124 | CL41: 97 | CM41: 72 | CN41: 48 | CO41: 26 | CP41: 97 | CQ41: 1 | CR41: 138 | CS41: 44 | CT41: 0.2 | CV41: 2 | CW41: 34.28 | CX41: 1.286 | CY41: 0 | DB41: 0 | DE41: 7.15 | DF41: 7 | DG41: 0 | DH41: 35 | DI41: 18 | DL41: 2 | DM41: 7 | DN41: 8 | DO41: 11.4 | DP41: 137.2 | DQ41: 68.6 | DR41: 137.2 | DS41: 0 | DT41: 3055 | DU41: 80.4 | DV41: flat | DW41: 57.14 | DX41: 59.03 | DY41: 53.96 | DZ41: -3.18 | EA41: 1593 | EB41: 17.22 | EC41: 6.67 | ED41: 120 | EE41: 3471 | EF41: TRUE | EG41: 99.5 | EH41: 28.4 | EI41: 114 | EJ41: 88.9 | EK41: 32 | EL41: 88.9 | EM41: 857.6 | EN41: 533 | EO41: 328.7 | EP41: 17.6
A42: Trevoh Chalobah | B42: CHE | C42: DEF | D42: DEF | E42: 5.5 | F42: TRUE | G42: TRUE | H42: 27.1 | I42: u | J42: Has joined Como permanently | K42: 0 | L42: p180736 | M42: 143 | Q42: 2780 | R42: 34 | S42: 31 | T42: 30.889 | U42: 81.8 | V42: 136 | W42: 4.403 | X42: 3 | Y42: 1 | AA42: 9 | AB42: 40 | AC42: 7 | AD42: 6 | AE42: -1 | AF42: 516 | AG42: 476 | AH42: -40 | AI42: 135 | AJ42: 0.051 | AK42: 0.054 | AL42: 265 | AM42: 8.579 | AN42: 14 | AO42: 28 | AP42: 0.452 | AQ42: 0.452 | AR42: 0.194 | AS42: 0.816 | AT42: 0.882 | AU42: 14 | AV42: 2 | AW42: 3.58 | AX42: 13 | AY42: 1.44 | AZ42: 1.841 | BA42: 1.641 | BB42: 1.841 | BC42: 0.047 | BD42: 0.06 | BE42: 0.053 | BF42: 2.5 | BG42: 0.081 | BH42: 1.19 | BI42: 4.44 | BJ42: 1.713 | BK42: 0.055 | BL42: 1.359 | BM42: 1.06 | BN42: 0.5 | BO42: -0.401 | BP42: 16 | BQ42: 5 | BR42: 2 | BS42: 17 | BT42: 0.55 | BV42: 2 | BW42: 1.03 | BX42: 0.631 | BY42: 0.83 | BZ42: 0.027 | CA42: 2.471 | CB42: 0.08 | CC42: 5 | CD42: 1 | CE42: 5 | CF42: 1 | CG42: 2 | CH42: 0 | CI42: 14.729 | CJ42: 14.597 | CK42: 230 | CL42: 119 | CM42: 35 | CN42: 23 | CO42: 35 | CP42: 178 | CQ42: 17 | CR42: 134 | CS42: 75 | CT42: 0.2 | CU42: 1 | CV42: 1 | CW42: 40.83 | CX42: 1.322 | CY42: 0 | DB42: 0 | DE42: 7.01 | DF42: 3 | DG42: 1 | DH42: 20 | DI42: 18 | DL42: 7 | DM42: 5 | DN42: 2 | DO42: 1.2 | DW42: 75.95 | DX42: 74.36 | DY42: 75.76 | DZ42: -0.19 | EA42: 239 | EB42: 18.82 | EC42: 21 | ED42: 120 | EE42: 819 | EF42: TRUE | EG42: 65.8 | EH42: 74.5 | EI42: 113 | EJ42: 173.8 | EK42: 163.5 | EL42: 556 | EM42: 1694.4 | EN42: 3348.2 | EO42: 1125 | EP42: 20.4
A43: Robin Roefs | B43: SUN | C43: GKP | D43: GKP | E43: 5 | F43: TRUE | G43: TRUE | H43: 23.6 | I43: a | L43: p498016 | M43: 529 | Q43: 3150 | R43: 35 | S43: 35 | T43: 35 | U43: 90 | V43: 136 | W43: 3.886 | X43: 0 | Y43: 0 | AA43: 10 | AB43: 46 | AC43: 12 | AD43: 12 | AE43: 0 | AF43: 573 | AG43: 567 | AH43: -6 | AI43: 136 | AJ43: 0.088 | AK43: 0.097 | AL43: 0 | AM43: 0 | AN43: 0 | AO43: 0 | AP43: 0 | AQ43: 0 | AR43: 0 | AS43: 0.921 | AT43: 1 | AU43: 17 | AV43: 3 | AW43: 3.18 | AX43: 11 | AY43: 0 | AZ43: 0 | BA43: 0 | BB43: 0 | BC43: 0 | BD43: 0 | BE43: 0 | BH43: 1 | BI43: 0 | BJ43: 0 | BK43: 0 | BL43: 0 | BO43: 0 | BW43: 0.1 | BX43: 0.705 | BY43: 0.403 | BZ43: 0.012 | CA43: 0.403 | CB43: 0.012 | CC43: 4 | CD43: 1 | CE43: 5 | CI43: 3.145 | CJ43: 2.439 | CK43: 37 | CL43: 333 | CM43: 0 | CP43: 37 | CR43: 35 | CS43: 24 | CU43: 4 | CV43: 3 | CW43: 50.05 | CX43: 1.43 | CY43: 109 | CZ43: 70.3 | DA43: -1.8 | DB43: 1 | DC43: 50 | DD43: 25 | DE43: 6.95 | DF43: 4 | DG43: 0 | DI43: 14 | DL43: 1 | DO43: 4.8 | DP43: 124.14 | DQ43: 62.07 | DR43: 124.14 | DS43: 0 | DT43: 3420 | DU43: 89.99 | DV43: flat | DW43: 89 | DX43: 90.79 | DY43: 88.8 | DZ43: -0.2 | EA43: 1330 | EB43: 23.22 | EC43: 5 | ED43: 120 | EE43: 2544 | EF43: TRUE | EG43: 97.5 | EH43: 46.5 | EI43: 225 | EL43: 630 | EN43: 7822.7 | EO43: 7822.7 | EP43: 23.2
A44: Dango Ouattara | B44: BRE | C44: MID | D44: MID | E44: 6.5 | F44: TRUE | G44: TRUE | H44: 24.5 | I44: a | L44: p533463 | M44: 95 | O44: 4 | Q44: 2271 | R44: 32 | S44: 25 | T44: 25.233 | U44: 71 | V44: 136 | W44: 5.39 | X44: 7 | Y44: 8 | Z44: 3 | AA44: 6 | AB44: 35 | AC44: 16 | AD44: 16 | AE44: 0 | AF44: 429 | AG44: 413 | AH44: -16 | AI44: 136 | AJ44: 0.118 | AK44: 0.133 | AL44: 185 | AM44: 7.332 | AN44: 2 | AO44: 4 | AP44: 0.08 | AQ44: 0.16 | AR44: 0.08 | AS44: 0.658 | AT44: 0.75 | AU44: 17 | AV44: 5 | AW44: 4.12 | AX44: 15 | AY44: 7.94 | AZ44: 8.694 | BA44: 8.317 | BB44: 8.694 | BC44: 0.315 | BD44: 0.345 | BE44: 0.33 | BF44: 6.8 | BG44: 0.269 | BH44: 0.838 | BI44: 22.53 | BJ44: 6.658 | BK44: 0.264 | BL44: -1.317 | BM44: -1.14 | BN44: 0.2 | BO44: -0.754 | BP44: 56 | BQ44: 20 | BR44: 13 | BS44: 119 | BT44: 4.716 | BV44: 2 | BW44: 4.12 | BX44: 5.863 | BY44: 4.992 | BZ44: 0.198 | CA44: 13.309 | CB44: 0.527 | CC44: 27 | CD44: 12 | CE44: 27 | CF44: 19 | CG44: 2 | CH44: 28 | CI44: 13.248 | CJ44: 2.526 | CK44: 76 | CL44: 85 | CM44: 24 | CN44: 13 | CO44: 24 | CP44: 52 | CQ44: 0 | CR44: 138 | CS44: 52 | CT44: 0.4 | CV44: 0 | CW44: 34.75 | CX44: 1.377 | CY44: 0 | DB44: 0 | DE44: 6.97 | DF44: 5 | DG44: 0 | DH44: 27 | DI44: 39 | DJ44: 5 | DL44: 23 | DM44: 31 | DN44: 9 | DO44: 1.4 | DP44: 155.24 | DQ44: 77.62 | DR44: 155.24 | DS44: 0 | DT44: 2878 | DU44: 75.75 | DV44: flat | DW44: 61.34 | DX44: 61.67 | DY44: 61.23 | DZ44: -0.11 | EA44: 1113 | EB44: 23.17 | EC44: 3.2 | ED44: 120 | EE44: 1860 | EF44: TRUE | EG44: 85.4 | EH44: 55.3 | EI44: 37 | EJ44: 40.6 | EK44: 19.1 | EL44: 84.1 | EM44: 273 | EN44: 455 | EO44: 170.6 | EP44: 16.7
A45: Alex Scott | B45: BOU | C45: MID | D45: MID | E45: 6 | F45: TRUE | G45: TRUE | H45: 23 | I45: a | L45: p503139 | M45: 69 | O45: 2 | P45: 4 | Q45: 2848 | R45: 37 | S45: 34 | T45: 31.644 | U45: 77 | V45: 136 | W45: 4.298 | X45: 3 | Y45: 2 | Z45: 1 | AA45: 11 | AB45: 41 | AC45: 9 | AD45: 9 | AE45: 0 | AF45: 603 | AG45: 572 | AH45: -31 | AI45: 136 | AJ45: 0.066 | AK45: 0.071 | AL45: 386 | AM45: 12.198 | AN45: 15 | AO45: 30 | AP45: 0.441 | AQ45: 0.765 | AR45: 0.441 | AS45: 0.895 | AT45: 0.892 | AU45: 14 | AV45: 2 | AW45: 2.75 | AX45: 13 | AY45: 3.8 | AZ45: 3.5 | BA45: 3.65 | BB45: 3.5 | BC45: 0.12 | BD45: 0.111 | BE45: 0.115 | BF45: 2.7 | BG45: 0.085 | BH45: 0.966 | BI45: 5.35 | BJ45: 3.672 | BK45: 0.116 | BL45: -0.65 | BM45: -1.1 | BN45: 0.3 | BO45: 0.3 | BP45: 44 | BQ45: 13 | BR45: 2 | BS45: 49 | BT45: 1.548 | BW45: 2.94 | BX45: 2.892 | BY45: 2.916 | BZ45: 0.092 | CA45: 6.566 | CB45: 0.207 | CC45: 26 | CD45: 4 | CE45: 27 | CF45: 14 | CG45: 5 | CH45: 56 | CI45: 15.246 | CJ45: 10.992 | CK45: 133 | CL45: 193 | CM45: 60 | CN45: 38 | CO45: 36 | CP45: 81 | CQ45: 15 | CR45: 185 | CS45: 37 | CT45: 0.4 | CV45: 1 | CW45: 47.02 | CX45: 1.486 | CY45: 0 | DB45: 0 | DE45: 7.17 | DF45: 5 | DG45: 0 | DH45: 45 | DI45: 60 | DK45: 1 | DL45: 29 | DM45: 26 | DN45: 1 | DO45: 1.6 | DP45: 148.22 | DQ45: 74.21 | DR45: 148.42 | DS45: -0.2 | DT45: 3175 | DU45: 83.55 | DV45: flat | DW45: 74.81 | DX45: 78.01 | DY45: 73.52 | DZ45: -1.29 | EA45: 718 | EB45: 21.47 | EC45: 9 | ED45: 120 | EE45: 1316 | EF45: TRUE | EG45: 30.8 | EH45: 12.4 | EI45: 69 | EJ45: 64.7 | EK45: 58.1 | EL45: 105.5 | EM45: 780.3 | EN45: 976.7 | EO45: 433.7 | EP45: 20.9
A46: Mateus Fernandes | B46: TOT | C46: MID | D46: MID | E46: 6 | F46: TRUE | G46: TRUE | H46: 22.1 | I46: a | L46: p551226 | M46: 525 | Q46: 3017 | R46: 36 | S46: 35 | T46: 33.522 | U46: 83.8 | V46: 135 | W46: 4.027 | X46: 3 | Y46: 4 | Z46: 4 | AA46: 8 | AB46: 50 | AC46: 7 | AD46: 6 | AE46: -1 | AF46: 659 | AG46: 639 | AH46: -20 | AI46: 134 | AJ46: 0.052 | AK46: 0.055 | AL46: 369 | AM46: 11.008 | AN46: 15 | AO46: 30 | AP46: 0.429 | AQ46: 0.571 | AR46: 0.429 | AS46: 0.921 | AT46: 0.944 | AU46: 17 | AV46: 0 | AW46: 2.43 | AX46: 9 | AY46: 1.99 | AZ46: 1.822 | BA46: 1.906 | BB46: 1.822 | BC46: 0.059 | BD46: 0.054 | BE46: 0.057 | BF46: 1.7 | BG46: 0.051 | BH46: 0.843 | BI46: 6.11 | BJ46: 1.678 | BK46: 0.05 | BL46: 1.094 | BM46: -0.29 | BN46: 1.3 | BO46: 0.168 | BP46: 28 | BQ46: 8 | BR46: 1 | BS46: 22 | BT46: 0.656 | BV46: 1 | BW46: 2.96 | BX46: 3.336 | BY46: 3.148 | BZ46: 0.094 | CA46: 5.054 | CB46: 0.151 | CC46: 37 | CD46: 3 | CE46: 37 | CF46: 12 | CG46: 7 | CH46: 13 | CI46: 10.319 | CJ46: 6.989 | CK46: 84 | CL46: 182 | CM46: 103 | CN46: 67 | CO46: 35 | CP46: 36 | CQ46: 12 | CR46: 199 | CS46: 19 | CT46: 0.5 | CV46: 4 | CW46: 48.3 | CX46: 1.441 | CY46: 0 | DB46: 0 | DE46: 7.24 | DF46: 7 | DG46: 0 | DH46: 49 | DI46: 49 | DL46: 28 | DM46: 32 | DO46: 2.8 | DP46: 145.49 | DQ46: 71.49 | DR46: 142.98 | DS46: 2.51 | DT46: 3089 | DU46: 81.3 | DV46: flat | DW46: 70.32 | DX46: 72.85 | DY46: 69.35 | DZ46: -0.97 | EA46: 879 | EB46: 22.28 | EC46: 4 | ED46: 120 | EE46: 1869 | EF46: TRUE | EG46: 42.7 | EH46: 10.1 | EI46: 70 | EJ46: 107.8 | EK46: 137.1 | EL46: 81.5 | EM46: 1583 | EN46: 958.4 | EO46: 597 | EP46: 22.3
A47: Rayan Cherki | B47: MCI | C47: MID | D47: MID | E47: 7.5 | F47: TRUE | G47: TRUE | H47: 23 | I47: a | L47: p466052 | M47: 399 | O47: 1 | P47: 1 | Q47: 1772 | R47: 33 | S47: 19 | T47: 19.689 | U47: 53.7 | V47: 135 | W47: 6.857 | X47: 4 | Y47: 13 | Z47: 12 | AA47: 8 | AB47: 18 | AC47: 16 | AD47: 16 | AE47: 0 | AF47: 580 | AG47: 579 | AH47: -1 | AI47: 135 | AJ47: 0.119 | AK47: 0.134 | AL47: 135 | AM47: 6.857 | AN47: 2 | AO47: 4 | AP47: 0.105 | AQ47: 0.105 | AR47: 0.105 | AS47: 0.5 | AT47: 0.485 | AU47: 14 | AV47: 5 | AW47: 3.67 | AX47: 13 | AY47: 4.28 | AZ47: 4.641 | BA47: 4.461 | BB47: 4.641 | BC47: 0.217 | BD47: 0.236 | BE47: 0.227 | BF47: 4.6 | BG47: 0.234 | BH47: 1.026 | BI47: 4.28 | BJ47: 4.392 | BK47: 0.223 | BL47: -0.461 | BM47: 0.32 | BN47: -0.6 | BO47: -0.361 | BP47: 55 | BQ47: 13 | BR47: 2 | BS47: 148 | BT47: 7.517 | BW47: 8.87 | BX47: 10.785 | BY47: 9.827 | BZ47: 0.499 | CA47: 14.288 | CB47: 0.726 | CC47: 60 | CD47: 19 | CE47: 60 | CF47: 24 | CG47: 13 | CH47: 55 | CI47: 20.81 | CJ47: 11.158 | CK47: 16 | CL47: 93 | CM47: 26 | CN47: 18 | CO47: 7 | CP47: 7 | CQ47: 1 | CR47: 112 | CS47: 1 | CT47: 0.8 | CV47: 1 | CW47: 25.23 | CX47: 1.281 | CY47: 0 | DB47: 0 | DE47: 7.35 | DF47: 1 | DG47: 0 | DH47: 17 | DI47: 34 | DL47: 51 | DM47: 34 | DN47: 1 | DO47: 8.8 | DP47: 114.29 | DQ47: 57.49 | DR47: 114.98 | DS47: -0.69 | DT47: 1796 | DU47: 47.25 | DV47: flat | DW47: 23.21 | DX47: 21.35 | DY47: 23.88 | DZ47: 0.67 | EA47: 1386 | EB47: 15.09 | EC47: 1.23 | ED47: 118.86 | EE47: 2451 | EF47: TRUE | EG47: 99.5 | EH47: 49.5 | EI47: 16 | EJ47: 32.2 | EK47: 12 | EL47: 29.5 | EM47: 397.2 | EN47: 180.3 | EO47: 124 | EP47: 13.1
A48: Jordan Pickford | B48: EVE | C48: GKP | D48: GKP | E48: 5.5 | F48: TRUE | G48: TRUE | H48: 32.5 | I48: a | L48: p111234 | M48: 226 | Q48: 3420 | R48: 38 | S48: 38 | T48: 38 | U48: 90 | V48: 135 | W48: 3.553 | X48: 0 | Y48: 0 | AA48: 11 | AB48: 50 | AC48: 11 | AD48: 15 | AE48: 4 | AF48: 545 | AG48: 530 | AH48: -15 | AI48: 139 | AJ48: 0.081 | AK48: 0.089 | AL48: 0 | AM48: 0 | AN48: 0 | AO48: 0 | AP48: 0 | AQ48: 0 | AR48: 0 | AS48: 1 | AT48: 1 | AU48: 23 | AV48: 4 | AW48: 3.4 | AX48: 15 | AY48: 0 | AZ48: 0 | BA48: 0 | BB48: 0 | BC48: 0 | BD48: 0 | BE48: 0 | BH48: 1 | BI48: 0 | BJ48: 0 | BK48: 0 | BL48: 0 | BO48: 0 | BS48: 1 | BT48: 0.026 | BW48: 0.2 | BX48: 0.233 | BY48: 0.217 | BZ48: 0.006 | CA48: 0.217 | CB48: 0.006 | CC48: 2 | CD48: 1 | CE48: 2 | CI48: 3.099 | CJ48: 3.017 | CK48: 52 | CL48: 313 | CM48: 2 | CN48: 1 | CO48: 0 | CP48: 52 | CR48: 13 | CS48: 5 | CU48: 3 | CW48: 56.24 | CX48: 1.48 | CY48: 100 | CZ48: 66.7 | DA48: 2.8 | DB48: 1 | DC48: 16 | DD48: 18 | DE48: 6.94 | DF48: 4 | DG48: 0 | DH48: 1 | DI48: 6 | DK48: 1 | DO48: 8.7 | DP48: 123.64 | DQ48: 61.82 | DR48: 123.64 | DS48: 0 | DT48: 3385 | DU48: 89.09 | DV48: flat | DW48: 53.35 | DX48: 56.16 | DY48: 51.03 | DZ48: -2.32 | EA48: 1571 | EB48: 21.25 | EC48: 0.73 | ED48: 118.67 | EE48: 3128 | EF48: TRUE | EG48: 99.9 | EH48: 35.8 | EI48: 115 | EK48: 3420 | EL48: 1710 | EN48: 15783.2 | EO48: 15783.2 | EP48: 25.3
A49: Gianluigi Donnarumma | B49: MCI | C49: GKP | D49: GKP | E49: 5.5 | F49: TRUE | G49: TRUE | H49: 27.5 | I49: a | L49: p204936 | M49: 384 | Q49: 3060 | R49: 34 | S49: 34 | T49: 34 | U49: 90 | V49: 135 | W49: 3.971 | X49: 0 | Y49: 0 | AA49: 15 | AB49: 29 | AC49: 5 | AD49: 6 | AE49: 1 | AF49: 567 | AG49: 560 | AH49: -7 | AI49: 136 | AJ49: 0.037 | AK49: 0.038 | AL49: 0 | AM49: 0 | AN49: 0 | AO49: 0 | AP49: 0 | AQ49: 0 | AR49: 0 | AS49: 0.895 | AT49: 1 | AU49: 16 | AV49: 0 | AW49: 2.6 | AX49: 8 | AY49: 0 | AZ49: 0 | BA49: 0 | BB49: 0 | BC49: 0 | BD49: 0 | BE49: 0 | BH49: 1 | BI49: 0 | BJ49: 0 | BK49: 0 | BL49: 0 | BO49: 0 | BS49: 1 | BT49: 0.029 | BW49: 0.13 | BX49: 0 | BY49: 0.065 | BZ49: 0.002 | CA49: 0.065 | CB49: 0.002 | CC49: 0 | CE49: 1 | CI49: 7.178 | CJ49: 7.178 | CK49: 42 | CL49: 236 | CM49: 0 | CO49: 1 | CP49: 43 | CR49: 22 | CS49: 16 | CU49: 2 | CV49: 3 | CW49: 38.5 | CX49: 1.132 | CY49: 78 | CZ49: 72.9 | DA49: 5.8 | DB49: 1 | DC49: 20 | DD49: 27 | DE49: 7.25 | DF49: 8 | DG49: 0 | DI49: 4 | DL49: 2 | DO49: 11.1 | DP49: 132.22 | DQ49: 66.11 | DR49: 132.22 | DS49: 0 | DT49: 3420 | DU49: 90 | DV49: flat | DW49: 43.7 | DX49: 47.09 | DY49: 39.45 | DZ49: -4.25 | EA49: 1632 | EB49: 19.27 | EC49: 1.6 | ED49: 119 | EE49: 3818 | EF49: TRUE | EG49: 99.8 | EH49: 21.5 | EI49: 116 | EK49: 3060 | EL49: 3060 | EN49: 47076.9 | EO49: 47076.9 | EP49: 22.7
A50: Tyrick Mitchell | B50: CRY | C50: DEF | D50: DEF | E50: 4.5 | F50: TRUE | G50: TRUE | H50: 27 | I50: a | L50: p244723 | M50: 204 | Q50: 3253 | R50: 38 | S50: 36 | T50: 36.144 | U50: 85.6 | V50: 135 | W50: 3.735 | X50: 1 | Y50: 3 | Z50: 2 | AA50: 12 | AB50: 47 | AC50: 8 | AD50: 8 | AE50: 0 | AF50: 498 | AG50: 468 | AH50: -30 | AI50: 135 | AJ50: 0.059 | AK50: 0.063 | AL50: 245 | AM50: 6.778 | AN50: 6 | AO50: 12 | AP50: 0.167 | AQ50: 0.167 | AR50: 0.056 | AS50: 0.947 | AT50: 0.921 | AU50: 21 | AV50: 2 | AW50: 3.06 | AX50: 11 | AY50: 1.59 | AZ50: 1.985 | BA50: 1.787 | BB50: 1.985 | BC50: 0.044 | BD50: 0.055 | BE50: 0.049 | BF50: 1.9 | BG50: 0.053 | BH50: 0.97 | BI50: 4.79 | BJ50: 1.542 | BK50: 0.043 | BL50: -0.787 | BM50: 0.31 | BN50: -0.9 | BO50: -0.395 | BP50: 19 | BQ50: 7 | BR50: 3 | BS50: 55 | BT50: 1.522 | BW50: 2.53 | BX50: 3.036 | BY50: 2.783 | BZ50: 0.077 | CA50: 4.57 | CB50: 0.126 | CC50: 29 | CD50: 4 | CE50: 29 | CF50: 22 | CI50: 13.155 | CJ50: 9.87 | CK50: 145 | CL50: 187 | CM50: 100 | CN50: 63 | CO50: 34 | CP50: 100 | CQ50: 12 | CR50: 170 | CS50: 26 | CT50: 0.2 | CV50: 2 | CW50: 49.78 | CX50: 1.377 | CY50: 0 | DB50: 0 | DE50: 7.06 | DF50: 6 | DG50: 0 | DH50: 23 | DI50: 28 | DL50: 15 | DM50: 26 | DN50: 5 | DO50: 6.9 | DP50: 95.16 | DQ50: 47.58 | DR50: 95.16 | DS50: 0 | DT50: 2554 | DU50: 67.2 | DV50: flat | DW50: 93.09 | DX50: 98.56 | DY50: 91.05 | DZ50: -2.04 | EA50: 658 | EB50: 17.54 | EC50: 13 | ED50: 120 | EE50: 1064 | EF50: TRUE | EG50: 23.4 | EH50: 6.8 | EI50: 390 | EJ50: 171.2 | EK50: 59.1 | EL50: 112.2 | EM50: 1820 | EN50: 1168.9 | EO50: 711.7 | EP50: 24.1
A51: Ethan Ampadu | B51: LEE | C51: MID | D51: MID | E51: 5.5 | F51: TRUE | G51: TRUE | H51: 25.9 | I51: a | L51: p199598 | M51: 338 | Q51: 3119 | R51: 35 | S51: 35 | T51: 34.656 | U51: 89.1 | V51: 134 | W51: 3.867 | X51: 1 | Y51: 4 | Z51: 1 | AA51: 8 | AB51: 49 | AC51: 11 | AD51: 11 | AE51: 0 | AF51: 586 | AG51: 562 | AH51: -24 | AI51: 134 | AJ51: 0.082 | AK51: 0.089 | AL51: 416 | AM51: 12.004 | AN51: 19 | AO51: 38 | AP51: 0.543 | AQ51: 0.686 | AR51: 0.543 | AS51: 0.921 | AT51: 1 | AU51: 12 | AV51: 2 | AW51: 2.66 | AX51: 12 | AY51: 2.47 | AZ51: 1.946 | BA51: 2.208 | BB51: 1.946 | BC51: 0.071 | BD51: 0.056 | BE51: 0.064 | BF51: 2.1 | BG51: 0.061 | BH51: 0.965 | BI51: 2.47 | BJ51: 2.383 | BK51: 0.069 | BL51: -1.208 | BM51: -0.37 | BN51: -1.1 | BO51: 0.524 | BP51: 26 | BQ51: 6 | BR51: 3 | BS51: 26 | BT51: 0.75 | BW51: 2.2 | BX51: 1.176 | BY51: 1.688 | BZ51: 0.049 | CA51: 3.896 | CB51: 0.112 | CC51: 19 | CD51: 1 | CE51: 19 | CF51: 10 | CG51: 2 | CI51: 11.866 | CJ51: 10.69 | CK51: 151 | CL51: 184 | CM51: 81 | CN51: 46 | CO51: 50 | CP51: 83 | CQ51: 18 | CR51: 184 | CS51: 57 | CT51: 0.5 | CV51: 5 | CW51: 48.66 | CX51: 1.404 | CY51: 0 | DB51: 0 | DE51: 7.21 | DF51: 10 | DG51: 0 | DH51: 50 | DI51: 36 | DJ51: 1 | DK51: 1 | DL51: 12 | DM51: 12 | DO51: 1.6 | DP51: 128.38 | DQ51: 64.19 | DR51: 128.38 | DS51: 0 | DT51: 3207 | DU51: 84.4 | DV51: flat | DW51: 85.57 | DX51: 86.39 | DY51: 85.9 | DZ51: 0.33 | EA51: 179 | EB51: 19.15 | EC51: 22 | ED51: 120 | EE51: 325 | EF51: TRUE | EG51: 7.6 | EH51: 12.4 | EI51: 117 | EJ51: 120 | EK51: 120 | EL51: 164.2 | EM51: 1412.6 | EN51: 1847.6 | EO51: 800.5 | EP51: 23.3
A52: Martín Zubimendi | B52: ARS | C52: MID | D52: MID | E52: 5.5 | F52: TRUE | G52: TRUE | H52: 27.5 | I52: a | L52: p481655 | M52: 19 | Q52: 2991 | R52: 38 | S52: 34 | T52: 33.233 | U52: 78.7 | V52: 133 | W52: 4.002 | X52: 5 | Y52: 1 | Z52: 1 | AA52: 16 | AB52: 25 | AC52: 9 | AD52: 9 | AE52: 0 | AF52: 604 | AG52: 578 | AH52: -26 | AI52: 133 | AJ52: 0.068 | AK52: 0.073 | AL52: 307 | AM52: 9.238 | AN52: 7 | AO52: 14 | AP52: 0.206 | AQ52: 0.382 | AR52: 0.206 | AS52: 0.895 | AT52: 0.842 | AU52: 17 | AV52: 3 | AW52: 3.06 | AX52: 16 | AY52: 2.84 | AZ52: 2.944 | BA52: 2.892 | BB52: 2.944 | BC52: 0.085 | BD52: 0.089 | BE52: 0.087 | BF52: 3.6 | BG52: 0.108 | BH52: 1.07 | BI52: 2.84 | BJ52: 3.039 | BK52: 0.091 | BL52: 2.108 | BM52: 0.76 | BN52: 1.4 | BO52: -0.104 | BP52: 27 | BQ52: 9 | BR52: 2 | BS52: 51 | BT52: 1.535 | BV52: 2 | BW52: 2.27 | BX52: 1.088 | BY52: 1.679 | BZ52: 0.051 | CA52: 4.571 | CB52: 0.138 | CC52: 19 | CD52: 1 | CE52: 19 | CF52: 3 | CG52: 2 | CI52: 13.477 | CJ52: 11.176 | CK52: 123 | CL52: 116 | CM52: 68 | CN52: 38 | CO52: 39 | CP52: 78 | CQ52: 5 | CR52: 153 | CS52: 65 | CT52: 0.2 | CU52: 2 | CV52: 3 | CW52: 26.09 | CX52: 0.785 | CY52: 0 | DB52: 0 | DE52: 7.2 | DF52: 4 | DG52: 0 | DH52: 33 | DI52: 15 | DL52: 7 | DM52: 10 | DN52: 1 | DO52: 1.4 | DP52: 47.39 | DQ52: 24.95 | DR52: 49.9 | DS52: -2.51 | DT52: 891 | DU52: 23.45 | DV52: fade (losing his place) | DW52: 80.61 | DX52: 84.42 | DY52: 80.83 | DZ52: 0.22 | EA52: 198 | EB52: 20.48 | EC52: 6.4 | ED52: 119.27 | EE52: 365 | EF52: TRUE | EG52: 8.5 | EH52: 12.3 | EI52: 118 | EJ52: 110.8 | EK52: 58.6 | EL52: 157.4 | EM52: 1034.2 | EN52: 1781.5 | EO52: 654.3 | EP52: 22.5
A53: Cody Gakpo | B53: LIV | C53: MID | D53: MID | E53: 7 | F53: TRUE | G53: TRUE | H53: 27.3 | I53: a | L53: p243298 | M53: 367 | N53: 3 | O53: 2 | Q53: 2736 | R53: 36 | S53: 32 | T53: 30.4 | U53: 76 | V53: 131 | W53: 4.309 | X53: 7 | Y53: 5 | Z53: 5 | AA53: 10 | AB53: 39 | AC53: 5 | AD53: 5 | AE53: 0 | AF53: 449 | AG53: 441 | AH53: -8 | AI53: 131 | AJ53: 0.038 | AK53: 0.04 | AL53: 152 | AM53: 5 | AN53: 1 | AO53: 2 | AP53: 0.031 | AQ53: 0.062 | AR53: 0.031 | AS53: 0.842 | AT53: 0.861 | AU53: 17 | AV53: 2 | AW53: 2.85 | AX53: 14 | AY53: 8.35 | AZ53: 9.826 | BA53: 9.088 | BB53: 9.826 | BC53: 0.275 | BD53: 0.323 | BE53: 0.299 | BF53: 5.6 | BG53: 0.184 | BH53: 0.875 | BI53: 30.97 | BJ53: 7.307 | BK53: 0.24 | BL53: -2.088 | BM53: -2.75 | BN53: 1.4 | BO53: -1.476 | BP53: 87 | BQ53: 21 | BR53: 8 | BS53: 187 | BT53: 6.151 | BW53: 4.67 | BX53: 6.592 | BY53: 5.631 | BZ53: 0.185 | CA53: 14.719 | CB53: 0.484 | CC53: 53 | CD53: 10 | CE53: 54 | CF53: 11 | CG53: 3 | CH53: 33 | CI53: 18.732 | CJ53: 5.831 | CK53: 37 | CL53: 87 | CM53: 28 | CN53: 14 | CO53: 13 | CP53: 21 | CQ53: 4 | CR53: 162 | CS53: 56 | CT53: 0.7 | CW53: 34.94 | CX53: 1.149 | CY53: 0 | DB53: 0 | DE53: 7.17 | DF53: 3 | DG53: 0 | DH53: 42 | DI53: 44 | DJ53: 1 | DL53: 34 | DM53: 28 | DN53: 30 | DO53: 3.3 | DP53: 150.69 | DQ53: 76.76 | DR53: 153.52 | DS53: -2.83 | DT53: 2457 | DU53: 64.65 | DV53: flat | DW53: 43.36 | DX53: 40.6 | DY53: 43.54 | DZ53: 0.18 | EA53: 1324 | EB53: 22.57 | EC53: 4 | ED53: 118.86 | EE53: 2259 | EF53: TRUE | EG53: 95.8 | EH53: 51.6 | EI53: 26 | EJ53: 31.4 | EK53: 14.6 | EL53: 50.7 | EM53: 301.1 | EN53: 485.9 | EO53: 185.9 | EP53: 20.9
A54: Dean Henderson | B54: CRY | C54: GKP | D54: GKP | E54: 5 | F54: TRUE | G54: TRUE | H54: 29.4 | I54: a | L54: p172649 | M54: 198 | Q54: 3330 | R54: 37 | S54: 37 | T54: 37 | U54: 90 | V54: 131 | W54: 3.541 | X54: 0 | Y54: 0 | AA54: 11 | AB54: 51 | AC54: 7 | AD54: 7 | AE54: 0 | AF54: 538 | AG54: 527 | AH54: -11 | AI54: 131 | AJ54: 0.053 | AK54: 0.056 | AL54: 0 | AM54: 0 | AN54: 0 | AO54: 0 | AP54: 0 | AQ54: 0 | AR54: 0 | AS54: 0.974 | AT54: 1 | AU54: 20 | AV54: 1 | AW54: 3.26 | AX54: 16 | AY54: 0 | AZ54: 0 | BA54: 0 | BB54: 0 | BC54: 0 | BD54: 0 | BE54: 0 | BH54: 0.999 | BI54: 0.01 | BJ54: 0 | BK54: 0 | BL54: 0 | BO54: 0 | BW54: 0.11 | BX54: 0.015 | BY54: 0.063 | BZ54: 0.002 | CA54: 0.063 | CB54: 0.002 | CC54: 1 | CE54: 1 | CH54: 0 | CI54: 3.761 | CJ54: 3.761 | CK54: 55 | CL54: 298 | CM54: 1 | CN54: 0 | CO54: 2 | CP54: 54 | CQ54: 0 | CR54: 21 | CS54: 17 | CV54: 2 | CW54: 51.4 | CX54: 1.389 | CY54: 106 | CZ54: 67.5 | DA54: 1.6 | DB54: 1 | DC54: 23 | DD54: 34 | DE54: 7.01 | DF54: 5 | DG54: 0 | DH54: 2 | DI54: 5 | DK54: 2 | DL54: 1 | DO54: 3.2 | DP54: 117.76 | DQ54: 58.88 | DR54: 117.76 | DS54: 0 | DT54: 3385 | DU54: 89.09 | DV54: flat | DW54: 91.07 | DX54: 94.78 | DY54: 90.27 | DZ54: -0.8 | EA54: 1409 | EB54: 23.34 | EC54: 2 | ED54: 120 | EE54: 2502 | EF54: TRUE | EG54: 97.7 | EH54: 47.5 | EI54: 226 | EL54: 3330 | EN54: 53078 | EO54: 53078 | EP54: 25.4
A55: Michael Keane | B55: EVE | C55: DEF | D55: DEF | E55: 5 | F55: TRUE | G55: TRUE | H55: 33.6 | I55: a | L55: p106611 | M55: 231 | Q55: 2588 | R55: 33 | S55: 29 | T55: 28.756 | U55: 78.4 | V55: 131 | W55: 4.556 | X55: 3 | Y55: 1 | Z55: 1 | AA55: 7 | AB55: 42 | AC55: 8 | AD55: 9 | AE55: 1 | AF55: 404 | AG55: 358 | AH55: -46 | AI55: 132 | AJ55: 0.061 | AK55: 0.065 | AL55: 302 | AM55: 10.502 | AN55: 15 | AO55: 30 | AP55: 0.517 | AQ55: 0.517 | AR55: 0.31 | AS55: 0.763 | AT55: 0.879 | AU55: 16 | AV55: 3 | AW55: 3.64 | AX55: 15 | AY55: 2.3 | AZ55: 3.569 | BA55: 2.935 | BB55: 3.569 | BC55: 0.08 | BD55: 0.124 | BE55: 0.102 | BF55: 2.2 | BG55: 0.077 | BH55: 1.05 | BI55: 4.76 | BJ55: 2.415 | BK55: 0.084 | BL55: 0.065 | BM55: -0.1 | BN55: 0.8 | BO55: -1.269 | BP55: 26 | BQ55: 7 | BR55: 3 | BS55: 65 | BT55: 2.26 | BV55: 1 | BW55: 0.49 | BX55: 0.13 | BY55: 0.31 | BZ55: 0.011 | CA55: 3.245 | CB55: 0.113 | CC55: 2 | CE55: 2 | CG55: 1 | CI55: 5.353 | CJ55: 4.284 | CK55: 265 | CL55: 87 | CM55: 37 | CN55: 23 | CO55: 37 | CP55: 203 | CQ55: 27 | CR55: 160 | CS55: 112 | CT55: 0 | CW55: 44.52 | CX55: 1.548 | CY55: 0 | DB55: 0 | DE55: 6.98 | DF55: 1 | DG55: 1 | DH55: 16 | DI55: 6 | DL55: 6 | DM55: 5 | DN55: 0 | DO55: 1.7 | DP55: 33.75 | DQ55: 16.88 | DR55: 33.76 | DS55: -0.01 | DT55: 623 | DU55: 16.39 | DV55: flat | DW55: 95.8 | DX55: 101.65 | DY55: 93.33 | DZ55: -2.47 | EA55: 677 | EB55: 15.71 | EC55: 31 | ED55: 120 | EE55: 1187 | EF55: TRUE | EG55: 52.4 | EH55: 53.5 | EI55: 227 | EJ55: 99.5 | EK55: 39.8 | EL55: 1294 | EM55: 881.9 | EN55: 8346.7 | EO55: 797.6 | EP55: 19.8
A56: Phil Foden | B56: MCI | C56: MID | D56: MID | E56: 7 | F56: TRUE | G56: TRUE | H56: 26.2 | I56: a | L56: p209244 | M56: 398 | O56: 2 | P56: 3 | Q56: 2078 | R56: 33 | S56: 23 | T56: 23.089 | U56: 63 | V56: 131 | W56: 5.674 | X56: 7 | Y56: 5 | Z56: 5 | AA56: 11 | AB56: 19 | AC56: 13 | AD56: 13 | AE56: 0 | AF56: 563 | AG56: 557 | AH56: -6 | AI56: 131 | AJ56: 0.099 | AK56: 0.11 | AL56: 160 | AM56: 6.93 | AN56: 3 | AO56: 6 | AP56: 0.13 | AQ56: 0.174 | AR56: 0.13 | AS56: 0.605 | AT56: 0.667 | AU56: 19 | AV56: 6 | AW56: 4.49 | AX56: 17 | AY56: 6.03 | AZ56: 6.689 | BA56: 6.359 | BB56: 6.689 | BC56: 0.261 | BD56: 0.29 | BE56: 0.275 | BF56: 6 | BG56: 0.26 | BH56: 1.253 | BI56: 27.12 | BJ56: 7.555 | BK56: 0.327 | BL56: 0.641 | BM56: -0.03 | BN56: 1 | BO56: -0.659 | BP56: 55 | BQ56: 19 | BR56: 6 | BS56: 94 | BT56: 4.071 | BV56: 2 | BW56: 4.76 | BX56: 6.107 | BY56: 5.434 | BZ56: 0.235 | CA56: 11.793 | CB56: 0.511 | CC56: 53 | CD56: 11 | CE56: 54 | CF56: 40 | CG56: 7 | CH56: 92 | CI56: 19.914 | CJ56: 11.249 | CK56: 24 | CL56: 102 | CM56: 34 | CN56: 16 | CO56: 9 | CP56: 12 | CQ56: 3 | CR56: 96 | CS56: 6 | CT56: 0.4 | CV56: 2 | CW56: 27.38 | CX56: 1.186 | CY56: 0 | DB56: 0 | DE56: 7.32 | DF56: 4 | DG56: 0 | DH56: 18 | DI56: 31 | DL56: 25 | DM56: 33 | DN56: 3 | DO56: 6.2 | DP56: 121.91 | DQ56: 61.4 | DR56: 122.8 | DS56: -0.89 | DT56: 2063 | DU56: 54.3 | DV56: flat | DW56: 33.55 | DX56: 30.09 | DY56: 34.76 | DZ56: 1.21 | EA56: 1455 | EB56: 18.28 | EC56: 0.89 | ED56: 117.33 | EE56: 3082 | EF56: TRUE | EG56: 97.8 | EH56: 35.3 | EI56: 27 | EJ56: 37.8 | EK56: 22.1 | EL56: 38.5 | EM56: 326.8 | EN56: 382.4 | EO56: 176.2 | EP56: 15.9
A57: Bart Verbruggen | B57: BHA | C57: GKP | D57: GKP | E57: 4.5 | F57: TRUE | G57: TRUE | H57: 24 | I57: a | L57: p489639 | M57: 109 | Q57: 3420 | R57: 38 | S57: 38 | T57: 38 | U57: 90 | V57: 130 | W57: 3.421 | X57: 0 | Y57: 0 | AA57: 10 | AB57: 46 | AC57: 6 | AD57: 11 | AE57: 5 | AF57: 616 | AG57: 610 | AH57: -6 | AI57: 135 | AJ57: 0.046 | AK57: 0.048 | AL57: 0 | AM57: 0 | AN57: 0 | AO57: 0 | AP57: 0 | AQ57: 0 | AR57: 0 | AS57: 1 | AT57: 1 | AU57: 21 | AV57: 1 | AW57: 2.64 | AX57: 11 | AY57: 0 | AZ57: 0 | BA57: 0 | BB57: 0 | BC57: 0 | BD57: 0 | BE57: 0 | BH57: 1 | BI57: 0 | BJ57: 0 | BK57: 0 | BL57: 0 | BO57: 0 | BS57: 0 | BT57: 0 | BW57: 0.06 | BX57: 0.076 | BY57: 0.068 | BZ57: 0.002 | CA57: 0.068 | CB57: 0.002 | CC57: 1 | CE57: 1 | CI57: 7.377 | CJ57: 7.377 | CK57: 32 | CL57: 332 | CM57: 1 | CN57: 1 | CO57: 0 | CP57: 32 | CR57: 16 | CS57: 11 | CU57: 4 | CV57: 2 | CW57: 49.06 | CX57: 1.291 | CY57: 106 | CZ57: 69.7 | DA57: 2 | DB57: 1 | DC57: 24 | DD57: 15 | DE57: 6.93 | DF57: 3 | DG57: 0 | DH57: 2 | DI57: 3 | DK57: 1 | DL57: 1 | DN57: 0 | DO57: 18.2 | DP57: 121.48 | DQ57: 60.74 | DR57: 121.48 | DS57: 0 | DT57: 3385 | DU57: 89.09 | DV57: flat | DW57: 102.97 | DX57: 108.17 | DY57: 100.4 | DZ57: -2.57 | EA57: 1281 | EB57: 21.18 | EC57: 0.89 | ED57: 120 | EE57: 2762 | EF57: TRUE | EG57: 61.4 | EH57: 7.7 | EI57: 391 | EL57: 3420 | EN57: 50123 | EO57: 50123 | EP57: 26.3
A58: Nathan Collins | B58: BRE | C58: DEF | D58: DEF | E58: 5.5 | F58: TRUE | G58: TRUE | H58: 25.3 | I58: a | L58: p432830 | M58: 84 | Q58: 2971 | R58: 35 | S58: 32 | T58: 33.011 | U58: 84.9 | V58: 129 | W58: 3.908 | X58: 1 | Y58: 2 | Z58: 2 | AA58: 9 | AB58: 44 | AC58: 7 | AD58: 6 | AE58: -1 | AF58: 450 | AG58: 404 | AH58: -46 | AI58: 128 | AJ58: 0.054 | AK58: 0.057 | AL58: 319 | AM58: 9.663 | AN58: 16 | AO58: 32 | AP58: 0.5 | AQ58: 0.5 | AR58: 0.281 | AS58: 0.842 | AT58: 0.914 | AU58: 15 | AV58: 2 | AW58: 3.34 | AX58: 13 | AY58: 2.24 | AZ58: 2.917 | BA58: 2.579 | BB58: 2.917 | BC58: 0.068 | BD58: 0.088 | BE58: 0.078 | BF58: 1.7 | BG58: 0.051 | BH58: 0.931 | BI58: 6.5 | BJ58: 2.086 | BK58: 0.063 | BL58: -1.579 | BM58: -0.54 | BN58: -0.7 | BO58: -0.677 | BP58: 20 | BQ58: 6 | BR58: 4 | BS58: 80 | BT58: 2.423 | BV58: 1 | BW58: 1.71 | BX58: 2.43 | BY58: 2.07 | BZ58: 0.063 | CA58: 4.648 | CB58: 0.141 | CC58: 9 | CD58: 5 | CE58: 11 | CF58: 1 | CG58: 0 | CI58: 10.036 | CJ58: 8.511 | CK58: 287 | CL58: 139 | CM58: 32 | CN58: 14 | CO58: 37 | CP58: 209 | CQ58: 41 | CR58: 144 | CS58: 89 | CT58: 0 | CU58: 1 | CV58: 3 | CW58: 47.52 | CX58: 1.44 | CY58: 0 | DB58: 0 | DE58: 6.88 | DF58: 7 | DG58: 0 | DH58: 20 | DI58: 17 | DJ58: 1 | DK58: 1 | DL58: 7 | DM58: 10 | DN58: 2 | DO58: 2.1 | DP58: 136.68 | DQ58: 69.28 | DR58: 138.56 | DS58: -1.88 | DT58: 3044 | DU58: 80.1 | DV58: flat | DW58: 82.39 | DX58: 83.54 | DY58: 82.02 | DZ58: -0.37 | EA58: 1056 | EB58: 18.27 | EC58: 8 | ED58: 120 | EE58: 1602 | EF58: TRUE | EG58: 88.5 | EH58: 62.9 | EI58: 119 | EJ58: 148.6 | EK58: 37.1 | EL58: 270.1 | EM58: 1152.2 | EN58: 1435.4 | EO58: 639.1 | EP58: 23
A59: Neco Williams | B59: NFO | C59: DEF | D59: DEF | E59: 5 | F59: TRUE | G59: TRUE | H59: 25.4 | I59: a | L59: p215136 | M59: 469 | O59: 1 | P59: 2 | Q59: 3203 | R59: 37 | S59: 36 | T59: 35.589 | U59: 86.6 | V59: 128 | W59: 3.597 | X59: 2 | Y59: 3 | Z59: 3 | AA59: 9 | AB59: 48 | AC59: 15 | AD59: 15 | AE59: 0 | AF59: 531 | AG59: 501 | AH59: -30 | AI59: 128 | AJ59: 0.117 | AK59: 0.133 | AL59: 247 | AM59: 6.94 | AN59: 4 | AO59: 8 | AP59: 0.111 | AQ59: 0.111 | AR59: 0.083 | AS59: 0.947 | AT59: 0.919 | AU59: 24 | AV59: 4 | AW59: 3.98 | AX59: 15 | AY59: 2.01 | AZ59: 1.871 | BA59: 1.94 | BB59: 1.871 | BC59: 0.056 | BD59: 0.053 | BE59: 0.055 | BF59: 3 | BG59: 0.084 | BH59: 1.029 | BI59: 6.28 | BJ59: 2.069 | BK59: 0.058 | BL59: 0.06 | BM59: 0.99 | BN59: -1 | BO59: 0.139 | BP59: 46 | BQ59: 19 | BR59: 2 | BS59: 68 | BT59: 1.911 | BW59: 3.97 | BX59: 4.396 | BY59: 4.183 | BZ59: 0.118 | CA59: 6.123 | CB59: 0.172 | CC59: 36 | CD59: 5 | CE59: 36 | CF59: 29 | CH59: 23 | CI59: 12.105 | CJ59: 9.01 | CK59: 151 | CL59: 164 | CM59: 96 | CN59: 62 | CO59: 47 | CP59: 88 | CQ59: 17 | CR59: 216 | CS59: 39 | CT59: 0.3 | CU59: 1 | CV59: 2 | CW59: 51.36 | CX59: 1.443 | CY59: 0 | DB59: 0 | DE59: 7.08 | DF59: 6 | DG59: 1 | DH59: 30 | DI59: 52 | DK59: 1 | DL59: 31 | DM59: 28 | DN59: 4 | DO59: 11.8 | DP59: 148.32 | DQ59: 74.16 | DR59: 148.32 | DS59: 0 | DT59: 3331 | DU59: 87.66 | DV59: flat | DW59: 81.86 | DX59: 87.32 | DY59: 76.11 | DZ59: -5.74 | EA59: 1382 | EB59: 21.63 | EC59: 6.67 | ED59: 120 | EE59: 3274 | EF59: TRUE | EG59: 82 | EH59: 18.1 | EI59: 229 | EJ59: 69.6 | EK59: 47.1 | EL59: 89 | EM59: 1650.8 | EN59: 765.8 | EO59: 523.1 | EP59: 25
A60: Viktor Gyökeres | B60: ARS | C60: FWD | D60: FWD | E60: 7.5 | F60: TRUE | G60: TRUE | H60: 28.2 | I60: a | L60: p224117 | M60: 25 | N60: 2 | Q60: 2217 | R60: 36 | S60: 26 | T60: 24.633 | U60: 61.6 | V60: 128 | W60: 5.196 | X60: 14 | Y60: 1 | Z60: 1 | AA60: 12 | AB60: 14 | AC60: 16 | AD60: 16 | AE60: 0 | AF60: 474 | AG60: 469 | AH60: -5 | AI60: 128 | AJ60: 0.125 | AK60: 0.143 | AL60: 85 | AM60: 3.451 | AN60: 0 | AO60: 0 | AP60: 0 | AQ60: 0 | AR60: 0 | AS60: 0.684 | AT60: 0.611 | AU60: 26 | AV60: 4 | AW60: 3.96 | AX60: 16 | AY60: 12.26 | AZ60: 13.871 | BA60: 13.066 | BB60: 11.588 | BC60: 0.498 | BD60: 0.563 | BE60: 0.53 | BF60: 9.4 | BG60: 0.382 | BH60: 0.859 | BI60: 12.26 | BJ60: 10.529 | BK60: 0.427 | BL60: 0.934 | BM60: -2.86 | BN60: 4.6 | BO60: -1.611 | BP60: 55 | BQ60: 22 | BR60: 13 | BS60: 142 | BT60: 5.765 | BU60: 3 | BV60: 2 | BW60: 1.94 | BX60: 2.654 | BY60: 2.297 | BZ60: 0.093 | CA60: 15.363 | CB60: 0.624 | CC60: 20 | CD60: 4 | CE60: 20 | CF60: 3 | CG60: 1 | CI60: 14.775 | CJ60: 3.26 | CK60: 23 | CL60: 55 | CM60: 7 | CN60: 5 | CO60: 1 | CP60: 19 | CQ60: 3 | CR60: 74 | CS60: 30 | CT60: 0.8 | CV60: 1 | CW60: 17.81 | CX60: 0.723 | CY60: 0 | DB60: 0 | DE60: 6.82 | DF60: 5 | DG60: 0 | DH60: 35 | DI60: 31 | DJ60: 0 | DL60: 7 | DM60: 25 | DN60: 4 | DO60: 13 | DP60: 89.86 | DQ60: 44.98 | DR60: 89.96 | DS60: -0.1 | DT60: 1459 | DU60: 38.4 | DV60: flat | DW60: 16.52 | DX60: 15.88 | DY60: 14.97 | DZ60: -1.55 | EA60: 1572 | EB60: 10.05 | EC60: 1 | ED60: 112 | EE60: 3287 | EF60: TRUE | EG60: 100 | EH60: 32.5 | EI60: 17 | EJ60: 40.3 | EK60: 15.6 | EL60: 110.8 | EM60: 169.7 | EN60: 965.2 | EO60: 144.3 | EP60: 17.3
A61: Iliman Ndiaye | B61: EVE | C61: MID | D61: MID | E61: 6 | F61: TRUE | G61: TRUE | H61: 26.5 | I61: a | L61: p440993 | M61: 237 | N61: 1 | Q61: 2781 | R61: 32 | S61: 32 | T61: 30.9 | U61: 86.9 | V61: 128 | W61: 4.142 | X61: 6 | Y61: 3 | Z61: 3 | AA61: 8 | AB61: 44 | AC61: 7 | AD61: 8 | AE61: 1 | AF61: 540 | AG61: 530 | AH61: -10 | AI61: 129 | AJ61: 0.055 | AK61: 0.058 | AL61: 283 | AM61: 9.159 | AN61: 6 | AO61: 12 | AP61: 0.188 | AQ61: 0.406 | AR61: 0.188 | AS61: 0.842 | AT61: 1 | AU61: 16 | AV61: 1 | AW61: 2.81 | AX61: 10 | AY61: 6.68 | AZ61: 6.144 | BA61: 6.412 | BB61: 4.621 | BC61: 0.216 | BD61: 0.199 | BE61: 0.208 | BF61: 9.1 | BG61: 0.294 | BH61: 1.186 | BI61: 12.91 | BJ61: 7.923 | BK61: 0.256 | BL61: -0.412 | BM61: 2.42 | BN61: -3.1 | BO61: 0.536 | BP61: 43 | BQ61: 22 | BR61: 3 | BS61: 102 | BT61: 3.301 | BU61: 2 | BW61: 4.41 | BX61: 4.457 | BY61: 4.434 | BZ61: 0.143 | CA61: 10.845 | CB61: 0.351 | CC61: 30 | CD61: 7 | CE61: 30 | CF61: 7 | CG61: 2 | CI61: 15.464 | CJ61: 6.866 | CK61: 38 | CL61: 178 | CM61: 67 | CN61: 43 | CO61: 16 | CP61: 19 | CQ61: 2 | CR61: 191 | CS61: 11 | CT61: 0.8 | CV61: 1 | CW61: 42.68 | CX61: 1.381 | CY61: 0 | DB61: 0 | DE61: 7.22 | DF61: 2 | DG61: 0 | DH61: 30 | DI61: 37 | DL61: 73 | DM61: 64 | DN61: 12 | DO61: 15.4 | DP61: 163.51 | DQ61: 81.76 | DR61: 163.52 | DS61: -0.01 | DT61: 3186 | DU61: 83.85 | DV61: flat | DW61: 62.53 | DX61: 67.7 | DY61: 57.29 | DZ61: -5.24 | EA61: 1336 | EB61: 22.37 | EC61: 10 | ED61: 120 | EE61: 3021 | EF61: TRUE | EG61: 67.5 | EH61: 8.1 | EI61: 71 | EJ61: 64.7 | EK61: 27.3 | EL61: 92.7 | EM61: 433.7 | EN61: 627.3 | EO61: 256.4 | EP61: 21.7
A62: Chris Richards | B62: CRY | C62: DEF | D62: DEF | E62: 5 | F62: TRUE | G62: TRUE | H62: 26.4 | I62: a | L62: p427623 | M62: 202 | Q62: 2825 | R62: 33 | S62: 31 | T62: 31.389 | U62: 85.6 | V62: 128 | W62: 4.078 | X62: 1 | Y62: 0 | AA62: 11 | AB62: 42 | AC62: 5 | AD62: 5 | AE62: 0 | AF62: 453 | AG62: 412 | AH62: -41 | AI62: 128 | AJ62: 0.039 | AK62: 0.041 | AL62: 311 | AM62: 9.908 | AN62: 13 | AO62: 26 | AP62: 0.419 | AQ62: 0.419 | AR62: 0.258 | AS62: 0.816 | AT62: 0.939 | AU62: 14 | AV62: 1 | AW62: 2.96 | AX62: 10 | AY62: 2.42 | AZ62: 1.781 | BA62: 2.101 | BB62: 1.781 | BC62: 0.077 | BD62: 0.057 | BE62: 0.067 | BF62: 1.6 | BG62: 0.051 | BH62: 0.934 | BI62: 5.06 | BJ62: 2.261 | BK62: 0.072 | BL62: -1.101 | BM62: -0.82 | BN62: -0.6 | BO62: 0.639 | BP62: 15 | BQ62: 2 | BR62: 1 | BS62: 44 | BT62: 1.402 | BV62: 1 | BW62: 1.56 | BX62: 0.488 | BY62: 1.024 | BZ62: 0.033 | CA62: 3.124 | CB62: 0.1 | CC62: 9 | CD62: 1 | CE62: 9 | CF62: 5 | CI62: 7.81 | CJ62: 7.503 | CK62: 257 | CL62: 65 | CM62: 54 | CN62: 35 | CO62: 43 | CP62: 196 | CQ62: 19 | CR62: 170 | CS62: 107 | CU62: 2 | CV62: 2 | CW62: 41.19 | CX62: 1.312 | CY62: 0 | DB62: 0 | DE62: 6.87 | DF62: 4 | DG62: 0 | DH62: 18 | DI62: 5 | DL62: 4 | DM62: 11 | DO62: 0.8 | DP62: 136.92 | DQ62: 68.46 | DR62: 136.92 | DS62: 0 | DT62: 3283 | DU62: 86.4 | DV62: flat | DW62: 94.38 | DX62: 100.06 | DY62: 91.75 | DZ62: -2.64 | EA62: 814 | EB62: 16.42 | EC62: 17 | ED62: 120 | EE62: 1526 | EF62: TRUE | EG62: 54.2 | EH62: 42.3 | EI62: 228 | EJ62: 188.3 | EK62: 64.2 | EL62: 313.9 | EM62: 1344.8 | EN62: 2759.4 | EO62: 904.1 | EP62: 22.1
A63: Jaidon Anthony | B63: BRE | C63: MID | D63: MID | E63: 6 | F63: TRUE | G63: TRUE | H63: 26.7 | I63: a | L63: p444180 | M63: 105 | Q63: 2717 | R63: 37 | S63: 32 | T63: 30.189 | U63: 73.4 | V63: 127 | W63: 4.207 | X63: 8 | Y63: 4 | Z63: 2 | AA63: 4 | AB63: 59 | AC63: 6 | AD63: 6 | AE63: 0 | AF63: 513 | AG63: 503 | AH63: -10 | AI63: 127 | AJ63: 0.047 | AK63: 0.05 | AL63: 232 | AM63: 7.685 | AN63: 1 | AO63: 2 | AP63: 0.031 | AQ63: 0.25 | AR63: 0.031 | AS63: 0.842 | AT63: 0.811 | AU63: 24 | AV63: 3 | AW63: 2.93 | AX63: 13 | AY63: 5.11 | AZ63: 5.564 | BA63: 5.337 | BB63: 5.564 | BC63: 0.169 | BD63: 0.184 | BE63: 0.177 | BF63: 8.2 | BG63: 0.272 | BH63: 1.244 | BI63: 6.87 | BJ63: 6.357 | BK63: 0.211 | BL63: 2.663 | BM63: 3.09 | BN63: -0.2 | BO63: -0.454 | BP63: 55 | BQ63: 23 | BR63: 3 | BS63: 108 | BT63: 3.577 | BW63: 2.85 | BX63: 4.374 | BY63: 3.612 | BZ63: 0.12 | CA63: 8.949 | CB63: 0.296 | CC63: 37 | CD63: 6 | CE63: 37 | CF63: 14 | CG63: 2 | CH63: 27 | CI63: 12.433 | CJ63: 5.834 | CK63: 49 | CL63: 141 | CM63: 42 | CN63: 22 | CO63: 15 | CP63: 27 | CQ63: 7 | CR63: 134 | CS63: 12 | CT63: 0.8 | CV63: 3 | CW63: 59 | CX63: 1.954 | CY63: 0 | DB63: 0 | DE63: 6.86 | DF63: 4 | DG63: 0 | DH63: 28 | DI63: 47 | DJ63: 1 | DK63: 1 | DL63: 36 | DM63: 41 | DN63: 9 | DO63: 0.2 | DP63: 41.33 | DQ63: 20.7 | DR63: 41.4 | DS63: -0.07 | DT63: 716 | DU63: 18.85 | DV63: flat | DW63: 86.73 | DX63: 88.45 | DY63: 86.24 | DZ63: -0.49 | EA63: 78 | EB63: 19.24 | EC63: 36 | ED63: 120 | EE63: 129 | EF63: TRUE | EG63: 3.1 | EH63: 13.4 | EI63: 108 | EJ63: 49.4 | EK63: 25.2 | EL63: 73.4 | EM63: 509.1 | EN63: 752.2 | EO63: 303.6 | EP63: 21.4
A64: Malick Thiaw | B64: NEW | C64: DEF | D64: DEF | E64: 5 | F64: TRUE | G64: TRUE | H64: 25 | I64: a | L64: p465642 | M64: 445 | Q64: 2963 | R64: 35 | S64: 33 | T64: 32.922 | U64: 84.7 | V64: 126 | W64: 3.827 | X64: 4 | Y64: 0 | AA64: 5 | AB64: 52 | AC64: 12 | AD64: 9 | AE64: -3 | AF64: 436 | AG64: 394 | AH64: -42 | AI64: 123 | AJ64: 0.095 | AK64: 0.105 | AL64: 292 | AM64: 8.869 | AN64: 12 | AO64: 24 | AP64: 0.364 | AQ64: 0.364 | AR64: 0.182 | AS64: 0.868 | AT64: 0.914 | AU64: 21 | AV64: 3 | AW64: 4.19 | AX64: 17 | AY64: 4.8 | AZ64: 5.898 | BA64: 5.349 | BB64: 5.898 | BC64: 0.146 | BD64: 0.179 | BE64: 0.162 | BF64: 5.3 | BG64: 0.161 | BH64: 1.039 | BI64: 4.8 | BJ64: 4.988 | BK64: 0.152 | BL64: -1.349 | BM64: 0.5 | BN64: -1.3 | BO64: -1.098 | BP64: 28 | BQ64: 14 | BR64: 6 | BS64: 50 | BT64: 1.519 | BV64: 2 | BW64: 0.96 | BX64: 0.827 | BY64: 0.893 | BZ64: 0.027 | CA64: 6.242 | CB64: 0.19 | CC64: 6 | CD64: 1 | CE64: 6 | CF64: 1 | CI64: 9.148 | CJ64: 8.645 | CK64: 248 | CL64: 118 | CM64: 44 | CN64: 32 | CO64: 31 | CP64: 184 | CQ64: 33 | CR64: 176 | CS64: 114 | CU64: 2 | CV64: 4 | CW64: 49.21 | CX64: 1.495 | CY64: 0 | DB64: 0 | DD64: 0 | DE64: 7.03 | DF64: 4 | DG64: 0 | DH64: 24 | DI64: 11 | DK64: 1 | DL64: 8 | DM64: 3 | DN64: 2 | DO64: 2 | DP64: 133.59 | DQ64: 66.8 | DR64: 133.6 | DS64: -0.01 | DT64: 3243 | DU64: 85.35 | DV64: flat | DW64: 92.34 | DX64: 98.56 | DY64: 89.28 | DZ64: -3.06 | EA64: 956 | EB64: 17.89 | EC64: 22.4 | ED64: 120 | EE64: 1817 | EF64: TRUE | EG64: 55.8 | EH64: 33.2 | EI64: 230 | EJ64: 105.8 | EK64: 59.3 | EL64: 493.8 | EM64: 553.9 | EN64: 3316.4 | EO64: 474.7 | EP64: 23.5
A65: Brenden Aaronson | B65: LEE | C65: MID | D65: MID | E65: 5.5 | F65: TRUE | G65: TRUE | H65: 25.8 | I65: a | L65: p427637 | M65: 337 | P65: 3 | Q65: 2449 | R65: 37 | S65: 30 | T65: 27.211 | U65: 66.2 | V65: 126 | W65: 4.63 | X65: 4 | Y65: 8 | Z65: 5 | AA65: 9 | AB65: 32 | AC65: 5 | AD65: 6 | AE65: 1 | AF65: 446 | AG65: 436 | AH65: -10 | AI65: 127 | AJ65: 0.04 | AK65: 0.041 | AL65: 216 | AM65: 7.938 | AN65: 3 | AO65: 6 | AP65: 0.1 | AQ65: 0.167 | AR65: 0.1 | AS65: 0.789 | AT65: 0.757 | AU65: 19 | AV65: 2 | AW65: 2.85 | AX65: 14 | AY65: 4.53 | AZ65: 5.881 | BA65: 5.206 | BB65: 5.881 | BC65: 0.166 | BD65: 0.216 | BE65: 0.191 | BF65: 4.5 | BG65: 0.165 | BH65: 0.957 | BI65: 8.51 | BJ65: 4.335 | BK65: 0.159 | BL65: -1.206 | BM65: -0.03 | BN65: -0.5 | BO65: -1.351 | BP65: 47 | BQ65: 17 | BR65: 4 | BS65: 98 | BT65: 3.601 | BW65: 3.6 | BX65: 5.663 | BY65: 4.631 | BZ65: 0.17 | CA65: 9.837 | CB65: 0.362 | CC65: 34 | CD65: 9 | CE65: 34 | CF65: 10 | CG65: 3 | CH65: 0 | CI65: 13.204 | CJ65: 3.488 | CK65: 36 | CL65: 130 | CM65: 50 | CN65: 25 | CO65: 15 | CP65: 17 | CQ65: 4 | CR65: 156 | CS65: 24 | CT65: 0.6 | CW65: 37.07 | CX65: 1.362 | CY65: 0 | DB65: 0 | DE65: 6.69 | DF65: 3 | DG65: 0 | DH65: 20 | DI65: 51 | DK65: 1 | DL65: 31 | DM65: 74 | DN65: 5 | DO65: 0.9 | DP65: 53.67 | DQ65: 26.99 | DR65: 53.98 | DS65: -0.31 | DT65: 1035 | DU65: 27.24 | DV65: flat | DW65: 84.48 | DX65: 83.78 | DY65: 82.1 | DZ65: -2.38 | EA65: 122 | EB65: 20.59 | EC65: 18 | ED65: 120 | EE65: 196 | EF65: TRUE | EG65: 4.5 | EH65: 10.9 | EI65: 120 | EJ65: 52.1 | EK65: 25 | EL65: 72 | EM65: 470.5 | EN65: 528.8 | EO65: 249 | EP65: 19.4
A66: Danny Welbeck | B66: CHE | C66: FWD | D66: FWD | E66: 6 | F66: TRUE | G66: TRUE | H66: 35.7 | I66: a | L66: p50175 | M66: 136 | Q66: 2249 | R66: 37 | S66: 26 | T66: 24.989 | U66: 60.8 | V66: 126 | W66: 5.042 | X66: 13 | Y66: 1 | Z66: 1 | AA66: 10 | AB66: 28 | AC66: 18 | AD66: 18 | AE66: 0 | AF66: 511 | AG66: 500 | AH66: -11 | AI66: 126 | AJ66: 0.143 | AK66: 0.167 | AL66: 112 | AM66: 4.482 | AN66: 0 | AO66: 0 | AP66: 0 | AQ66: 0 | AR66: 0 | AS66: 0.684 | AT66: 0.676 | AU66: 26 | AV66: 3 | AW66: 3.48 | AX66: 13 | AY66: 12.36 | AZ66: 12.719 | BA66: 12.539 | BB66: 10.435 | BC66: 0.495 | BD66: 0.509 | BE66: 0.502 | BF66: 11.9 | BG66: 0.476 | BH66: 0.986 | BI66: 35.62 | BJ66: 12.184 | BK66: 0.488 | BL66: 0.461 | BM66: -0.46 | BN66: 1.1 | BO66: -0.359 | BP66: 56 | BQ66: 28 | BR66: 11 | BS66: 114 | BT66: 4.562 | BU66: 1 | BV66: 2 | BW66: 1.4 | BX66: 2.263 | BY66: 1.831 | BZ66: 0.073 | CA66: 14.371 | CB66: 0.575 | CC66: 20 | CD66: 4 | CE66: 20 | CF66: 0 | CG66: 3 | CH66: 0 | CI66: 14.985 | CJ66: 4.797 | CK66: 39 | CL66: 49 | CM66: 24 | CN66: 14 | CO66: 9 | CP66: 30 | CQ66: 0 | CR66: 64 | CS66: 19 | CT66: 0.6 | CU66: 1 | CV66: 1 | CW66: 31.68 | CX66: 1.268 | CY66: 0 | DB66: 0 | DE66: 6.79 | DF66: 5 | DG66: 0 | DH66: 30 | DI66: 10 | DL66: 11 | DM66: 20 | DN66: 5 | DO66: 2.5 | DP66: 57.91 | DQ66: 28.98 | DR66: 57.96 | DS66: -0.05 | DT66: 586 | DU66: 15.42 | DV66: flat | DW66: 67.34 | DX66: 66.07 | DY66: 67.08 | DZ66: -0.26 | EA66: 987 | EB66: 25.96 | EC66: 2 | ED66: 120 | EE66: 1747 | EF66: TRUE | EG66: 82.5 | EH66: 56.6 | EI66: 72 | EJ66: 40.2 | EK66: 19.7 | EL66: 112.4 | EM66: 179.4 | EN66: 1228.1 | EO66: 156.5 | EP66: 17.8
A67: Florian Wirtz | B67: LIV | C67: MID | D67: MID | E67: 7.5 | F67: TRUE | G67: TRUE | H67: 23.3 | I67: a | L67: p494595 | M67: 366 | N67: 4 | O67: 3 | P67: 2 | Q67: 2374 | R67: 33 | S67: 27 | T67: 26.378 | U67: 71.9 | V67: 125 | W67: 4.739 | X67: 5 | Y67: 4 | Z67: 3 | AA67: 10 | AB67: 32 | AC67: 17 | AD67: 17 | AE67: 0 | AF67: 521 | AG67: 516 | AH67: -5 | AI67: 125 | AJ67: 0.136 | AK67: 0.157 | AL67: 176 | AM67: 6.672 | AN67: 1 | AO67: 2 | AP67: 0.037 | AQ67: 0.074 | AR67: 0.037 | AS67: 0.711 | AT67: 0.818 | AU67: 16 | AV67: 4 | AW67: 3.24 | AX67: 12 | AY67: 6.83 | AZ67: 7.577 | BA67: 7.203 | BB67: 7.577 | BC67: 0.259 | BD67: 0.287 | BE67: 0.273 | BF67: 6.5 | BG67: 0.246 | BH67: 0.978 | BI67: 6.83 | BJ67: 6.678 | BK67: 0.253 | BL67: -2.203 | BM67: -0.33 | BN67: -1.5 | BO67: -0.747 | BP67: 51 | BQ67: 18 | BR67: 8 | BS67: 161 | BT67: 6.104 | BW67: 5.14 | BX67: 5.384 | BY67: 5.262 | BZ67: 0.199 | CA67: 12.466 | CB67: 0.473 | CC67: 60 | CD67: 5 | CE67: 60 | CF67: 5 | CG67: 6 | CH67: 20 | CI67: 20.642 | CJ67: 10.743 | CK67: 26 | CL67: 116 | CM67: 34 | CN67: 26 | CO67: 11 | CP67: 13 | CQ67: 2 | CR67: 99 | CS67: 7 | CT67: 0.8 | CV67: 1 | CW67: 33.99 | CX67: 1.289 | CY67: 0 | DB67: 0 | DE67: 7.16 | DF67: 1 | DG67: 0 | DH67: 22 | DI67: 19 | DL67: 39 | DM67: 36 | DN67: 2 | DO67: 14.7 | DP67: 174.06 | DQ67: 87.03 | DR67: 174.06 | DS67: 0 | DT67: 2902 | DU67: 76.36 | DV67: flat | DW67: 19.58 | DX67: 18.35 | DY67: 18.47 | DZ67: -1.11 | EA67: 1516 | EB67: 10.84 | EC67: 1.45 | ED67: 112 | EE67: 3212 | EF67: TRUE | EG67: 99.8 | EH67: 34 | EI67: 18 | EJ67: 46.5 | EK67: 14.7 | EL67: 39.6 | EM67: 329.6 | EN67: 451.1 | EO67: 190.4 | EP67: 19
A68: Pedro Neto | B68: CHE | C68: MID | D68: MID | E68: 6.5 | F68: TRUE | G68: TRUE | H68: 26.5 | I68: a | L68: p247632 | M68: 156 | O68: 3 | P68: 4 | Q68: 2629 | R68: 34 | S68: 30 | T68: 29.211 | U68: 77.3 | V68: 125 | W68: 4.279 | X68: 5 | Y68: 7 | Z68: 6 | AA68: 11 | AB68: 33 | AC68: 9 | AD68: 10 | AE68: 1 | AF68: 543 | AG68: 539 | AH68: -4 | AI68: 126 | AJ68: 0.072 | AK68: 0.078 | AL68: 122 | AM68: 4.176 | AN68: 0 | AO68: 0 | AP68: 0 | AQ68: 0 | AR68: 0 | AS68: 0.789 | AT68: 0.882 | AU68: 18 | AV68: 1 | AW68: 2.93 | AX68: 12 | AY68: 4.59 | AZ68: 5.15 | BA68: 4.87 | BB68: 5.15 | BC68: 0.157 | BD68: 0.176 | BE68: 0.167 | BF68: 3.8 | BG68: 0.13 | BH68: 0.82 | BI68: 12.36 | BJ68: 3.765 | BK68: 0.129 | BL68: 0.13 | BM68: -0.79 | BN68: 1.2 | BO68: -0.56 | BP68: 46 | BQ68: 13 | BR68: 3 | BS68: 107 | BT68: 3.663 | BV68: 1 | BW68: 6.84 | BX68: 7.934 | BY68: 7.387 | BZ68: 0.253 | CA68: 12.257 | CB68: 0.42 | CC68: 53 | CD68: 12 | CE68: 53 | CF68: 38 | CG68: 2 | CH68: 71 | CI68: 19.275 | CJ68: 9.827 | CK68: 19 | CL68: 84 | CM68: 19 | CN68: 11 | CO68: 6 | CP68: 13 | CR68: 100 | CS68: 9 | CT68: 0.4 | CW68: 37.54 | CX68: 1.285 | CY68: 0 | DB68: 0 | DE68: 7.04 | DF68: 2 | DG68: 1 | DH68: 16 | DI68: 25 | DL68: 47 | DM68: 25 | DN68: 6 | DO68: 1.4 | DP68: 82.77 | DQ68: 41.5 | DR68: 83 | DS68: -0.23 | DT68: 1773 | DU68: 46.65 | DV68: flat | DW68: 60 | DX68: 59.03 | DY68: 59.88 | DZ68: -0.12 | EA68: 981 | EB68: 23.82 | EC68: 6.55 | ED68: 120 | EE68: 1652 | EF68: TRUE | EG68: 78.6 | EH68: 56.9 | EI68: 38 | EJ68: 57.2 | EK68: 24.6 | EL68: 49.6 | EM68: 539.9 | EN68: 355.9 | EO68: 214.5 | EP68: 21
A69: Hugo Ekitiké | B69: LIV | C69: FWD | D69: FWD | E69: 7.5 | F69: TRUE | G69: TRUE | H69: 24.2 | I69: i | J69: Achilles injury - Unknown return date | K69: 0 | L69: p510663 | M69: 380 | Q69: 1797 | R69: 28 | S69: 21 | T69: 19.967 | U69: 64.2 | V69: 125 | W69: 6.26 | X69: 11 | Y69: 4 | Z69: 4 | AA69: 7 | AB69: 25 | AC69: 22 | AD69: 22 | AE69: 0 | AF69: 433 | AG69: 429 | AH69: -4 | AI69: 125 | AJ69: 0.176 | AK69: 0.214 | AL69: 85 | AM69: 4.257 | AN69: 0 | AO69: 0 | AP69: 0 | AQ69: 0.048 | AR69: 0 | AS69: 0.553 | AT69: 0.679 | AU69: 19 | AV69: 5 | AW69: 4.48 | AX69: 15 | AY69: 10.1 | AZ69: 11.932 | BA69: 11.016 | BB69: 11.932 | BC69: 0.506 | BD69: 0.598 | BE69: 0.552 | BF69: 9.2 | BG69: 0.461 | BH69: 0.95 | BI69: 10.1 | BJ69: 9.598 | BK69: 0.481 | BL69: -0.016 | BM69: -0.9 | BN69: 1.8 | BO69: -1.832 | BP69: 65 | BQ69: 19 | BR69: 11 | BS69: 136 | BT69: 6.811 | BV69: 2 | BW69: 2.45 | BX69: 2.491 | BY69: 2.471 | BZ69: 0.124 | CA69: 13.487 | CB69: 0.675 | CC69: 21 | CD69: 3 | CE69: 21 | CF69: 1 | CG69: 1 | CI69: 16.323 | CJ69: 4.886 | CK69: 32 | CL69: 42 | CM69: 11 | CN69: 7 | CO69: 3 | CP69: 27 | CQ69: 2 | CR69: 92 | CS69: 31 | CT69: 0.7 | CW69: 26.11 | CX69: 1.308 | CY69: 0 | DB69: 0 | DE69: 7.08 | DF69: 0 | DG69: 0 | DH69: 35 | DI69: 12 | DL69: 38 | DM69: 26 | DN69: 10 | DO69: 0.2 | DP69: 58.16 | DQ69: 22.62 | DR69: 45.24 | DS69: 12.92 | DT69: 942 | DU69: 24.78 | DV69: flat | DW69: 61.27 | DX69: 55.74 | DY69: 63.85 | DZ69: 2.58 | EA69: 384 | EB69: 35.32 | EC69: 2.29 | ED69: 120 | EE69: 649 | EF69: TRUE | EG69: 83.1 | EH69: 84 | EI69: 19 | EJ69: 27.6 | EK69: 13.2 | EL69: 85.6 | EM69: 163.1 | EN69: 727.3 | EO69: 133.2 | EP69: 14.4
A70: Omar Alderete | B70: SUN | C70: DEF | D70: DEF | E70: 5 | F70: TRUE | G70: TRUE | H70: 29.7 | I70: d | J70: Knock - 75% chance of playing | K70: 75 | L70: p201895 | M70: 535 | Q70: 2797 | R70: 33 | S70: 32 | T70: 31.078 | U70: 84.8 | V70: 125 | W70: 4.022 | X70: 1 | Y70: 1 | Z70: 1 | AA70: 10 | AB70: 40 | AC70: 5 | AD70: 5 | AE70: 0 | AF70: 400 | AG70: 348 | AH70: -52 | AI70: 125 | AJ70: 0.04 | AK70: 0.042 | AL70: 312 | AM70: 10.039 | AN70: 12 | AO70: 24 | AP70: 0.375 | AQ70: 0.375 | AR70: 0.219 | AS70: 0.842 | AT70: 0.939 | AU70: 16 | AV70: 1 | AW70: 3.63 | AX70: 17 | AY70: 1.62 | AZ70: 1.546 | BA70: 1.583 | BB70: 1.546 | BC70: 0.052 | BD70: 0.05 | BE70: 0.051 | BF70: 1.5 | BG70: 0.048 | BH70: 0.988 | BI70: 1.62 | BJ70: 1.6 | BK70: 0.051 | BL70: -0.583 | BM70: -0.12 | BN70: -0.5 | BO70: 0.074 | BP70: 24 | BQ70: 9 | BR70: 2 | BS70: 47 | BT70: 1.512 | BV70: 1 | BW70: 0.91 | BX70: 0.607 | BY70: 0.759 | BZ70: 0.024 | CA70: 2.342 | CB70: 0.075 | CC70: 9 | CD70: 1 | CE70: 9 | CF70: 3 | CG70: 3 | CI70: 4.55 | CJ70: 3.773 | CK70: 280 | CL70: 103 | CM70: 32 | CN70: 18 | CO70: 36 | CP70: 217 | CQ70: 29 | CR70: 146 | CS70: 88 | CT70: 0.1 | CV70: 5 | CW70: 44.52 | CX70: 1.433 | CY70: 0 | DB70: 0 | DE70: 6.92 | DF70: 6 | DG70: 0 | DH70: 34 | DI70: 10 | DK70: 0 | DL70: 17 | DM70: 12 | DN70: 5 | DO70: 0.7 | DP70: 131.07 | DQ70: 65.19 | DR70: 130.38 | DS70: 0.69 | DT70: 3067 | DU70: 80.7 | DV70: flat | DW70: 101.06 | DX70: 105.04 | DY70: 100.79 | DZ70: -0.27 | EA70: 221 | EB70: 15.07 | EC70: 18.67 | ED70: 120 | EE70: 656 | EF70: TRUE | EG70: 28.5 | EH70: 52.8 | EI70: 231 | EJ70: 116.5 | EK70: 59.5 | EL70: 310.8 | EM70: 1767.1 | EN70: 3686.4 | EO70: 1194.5 | EP70: 22.4
A71: Kevin Schade | B71: BRE | C71: MID | D71: MID | E71: 6 | F71: TRUE | G71: TRUE | H71: 24.7 | I71: a | L71: p513418 | M71: 94 | N71: 2 | Q71: 2744 | R71: 35 | S71: 32 | T71: 30.489 | U71: 78.4 | V71: 125 | W71: 4.1 | X71: 8 | Y71: 5 | Z71: 3 | AA71: 11 | AB71: 34 | AC71: 5 | AD71: 5 | AE71: 0 | AF71: 385 | AG71: 371 | AH71: -14 | AI71: 125 | AJ71: 0.04 | AK71: 0.042 | AL71: 190 | AM71: 6.232 | AN71: 0 | AO71: 0 | AP71: 0 | AQ71: 0.062 | AR71: 0 | AS71: 0.842 | AT71: 0.857 | AU71: 16 | AV71: 1 | AW71: 3.7 | AX71: 20 | AY71: 12.08 | AZ71: 11.833 | BA71: 11.956 | BB71: 11.072 | BC71: 0.396 | BD71: 0.388 | BE71: 0.392 | BF71: 9.8 | BG71: 0.321 | BH71: 0.953 | BI71: 23.89 | BJ71: 11.516 | BK71: 0.378 | BL71: -3.956 | BM71: -2.28 | BN71: -1.8 | BO71: 0.247 | BP71: 57 | BQ71: 24 | BR71: 15 | BS71: 141 | BT71: 4.625 | BV71: 3 | BW71: 2.05 | BX71: 4.565 | BY71: 3.308 | BZ71: 0.108 | CA71: 15.264 | CB71: 0.501 | CC71: 29 | CD71: 7 | CE71: 28 | CF71: 5 | CH71: 1 | CI71: 17.375 | CJ71: 3.947 | CK71: 54 | CL71: 94 | CM71: 42 | CN71: 24 | CO71: 18 | CP71: 31 | CQ71: 3 | CR71: 190 | CS71: 87 | CT71: 0.3 | CW71: 40.05 | CX71: 1.314 | CY71: 0 | DB71: 0 | DE71: 6.83 | DF71: 6 | DG71: 1 | DH71: 50 | DI71: 43 | DJ71: 2 | DL71: 20 | DM71: 45 | DN71: 10 | DO71: 1.9 | DP71: 148.66 | DQ71: 74.33 | DR71: 148.66 | DS71: 0 | DT71: 2804 | DU71: 73.8 | DV71: flat | DW71: 76.44 | DX71: 81.08 | DY71: 73.62 | DZ71: -2.82 | EA71: 802 | EB71: 21.15 | EC71: 2 | ED71: 120 | EE71: 1586 | EF71: TRUE | EG71: 35.8 | EH71: 9.2 | EI71: 73 | EJ71: 48.1 | EK71: 19.5 | EL71: 98 | EM71: 229.5 | EN71: 829.6 | EO71: 179.8 | EP71: 22
A72: Djordje Petrovic | B72: BOU | C72: GKP | D72: GKP | E72: 4.5 | F72: TRUE | G72: TRUE | H72: 26.9 | I72: a | L72: p457569 | M72: 57 | Q72: 3420 | R72: 38 | S72: 38 | T72: 38 | U72: 90 | V72: 124 | W72: 3.263 | X72: 0 | Y72: 0 | AA72: 11 | AB72: 54 | AC72: 5 | AD72: 7 | AE72: 2 | AF72: 512 | AG72: 496 | AH72: -16 | AI72: 126 | AJ72: 0.04 | AK72: 0.042 | AL72: 0 | AM72: 0 | AN72: 0 | AO72: 0 | AP72: 0 | AQ72: 0 | AR72: 0 | AS72: 1 | AT72: 1 | AU72: 20 | AV72: 1 | AW72: 2.56 | AX72: 10 | AY72: 0 | AZ72: 0 | BA72: 0 | BB72: 0 | BC72: 0 | BD72: 0 | BE72: 0 | BH72: 1 | BI72: 0 | BJ72: 0 | BK72: 0 | BL72: 0 | BO72: 0 | BW72: 0 | BX72: 0 | BY72: 0 | BZ72: 0 | CA72: 0 | CB72: 0 | CC72: 0 | CI72: 3.018 | CJ72: 3.018 | CK72: 62 | CL72: 285 | CM72: 0 | CP72: 62 | CR72: 23 | CS72: 20 | CU72: 2 | CV72: 2 | CW72: 56.72 | CX72: 1.493 | CY72: 109 | CZ72: 66.9 | DA72: -3 | DB72: 0 | DC72: 41 | DD72: 35 | DE72: 6.94 | DF72: 3 | DG72: 0 | DI72: 2 | DM72: 0 | DO72: 3.7 | DP72: 120.28 | DQ72: 60.14 | DR72: 120.28 | DS72: 0 | DT72: 3385 | DU72: 89.09 | DV72: flat | DW72: 108.94 | DX72: 112.88 | DY72: 108.47 | DZ72: -0.47 | EA72: 900 | EB72: 15.93 | EC72: 11.43 | ED72: 120 | EE72: 1503 | EF72: TRUE | EG72: 33.9 | EH72: 9.1 | EI72: 392 | EP72: 27.6
A73: Granit Xhaka | B73: SUN | C73: MID | D73: MID | E73: 5.5 | F73: TRUE | G73: TRUE | H73: 33.9 | I73: a | L73: p84450 | M73: 544 | O73: 2 | P73: 1 | Q73: 2901 | R73: 34 | S73: 32 | T73: 32.233 | U73: 85.3 | V73: 124 | W73: 3.847 | X73: 1 | Y73: 6 | Z73: 6 | AA73: 9 | AB73: 39 | AC73: 8 | AD73: 8 | AE73: 0 | AF73: 603 | AG73: 583 | AH73: -20 | AI73: 124 | AJ73: 0.065 | AK73: 0.069 | AL73: 362 | AM73: 11.231 | AN73: 13 | AO73: 26 | AP73: 0.406 | AQ73: 0.594 | AR73: 0.406 | AS73: 0.842 | AT73: 0.941 | AU73: 13 | AV73: 1 | AW73: 2.45 | AX73: 10 | AY73: 1.01 | AZ73: 0.807 | BA73: 0.909 | BB73: 0.807 | BC73: 0.031 | BD73: 0.025 | BE73: 0.028 | BF73: 0.8 | BG73: 0.025 | BH73: 1.091 | BI73: 5.66 | BJ73: 1.102 | BK73: 0.034 | BL73: 0.091 | BM73: -0.21 | BN73: 0.2 | BO73: 0.203 | BP73: 21 | BQ73: 5 | BS73: 16 | BT73: 0.496 | BW73: 3.73 | BX73: 3.705 | BY73: 3.717 | BZ73: 0.115 | CA73: 4.626 | CB73: 0.144 | CC73: 34 | CD73: 9 | CE73: 34 | CF73: 23 | CG73: 3 | CH73: 61 | CI73: 10.455 | CJ73: 8.981 | CK73: 134 | CL73: 178 | CM73: 50 | CN73: 33 | CO73: 29 | CP73: 85 | CQ73: 20 | CR73: 155 | CS73: 56 | CT73: 0.3 | CV73: 3 | CW73: 45.68 | CX73: 1.417 | CY73: 0 | DB73: 0 | DE73: 7.24 | DF73: 8 | DG73: 0 | DH73: 23 | DI73: 41 | DL73: 11 | DM73: 17 | DO73: 5.1 | DP73: 132.54 | DQ73: 66.27 | DR73: 132.54 | DS73: 0 | DT73: 3295 | DU73: 86.7 | DV73: flat | DW73: 77.44 | DX73: 81.5 | DY73: 76.2 | DZ73: -1.24 | EA73: 490 | EB73: 22.43 | EC73: 3 | ED73: 120 | EE73: 947 | EF73: TRUE | EG73: 21.8 | EH73: 11 | EI73: 121 | EJ73: 138.1 | EK73: 181.3 | EL73: 85.3 | EM73: 3192.7 | EN73: 780.4 | EO73: 627.1 | EP73: 23.4
A74: Joachim Andersen | B74: FUL | C74: DEF | D74: DEF | E74: 5 | F74: TRUE | G74: TRUE | H74: 30.2 | I74: s | J74: Suspended until 30 Aug | K74: 0 | L74: p174874 | M74: 253 | Q74: 2882 | R74: 33 | S74: 33 | T74: 32.022 | U74: 87.3 | V74: 123 | W74: 3.841 | X74: 0 | Y74: 1 | Z74: 1 | AA74: 8 | AB74: 45 | AC74: 8 | AD74: 6 | AE74: -2 | AF74: 424 | AG74: 372 | AH74: -52 | AI74: 121 | AJ74: 0.065 | AK74: 0.07 | AL74: 329 | AM74: 10.274 | AN74: 20 | AO74: 40 | AP74: 0.606 | AQ74: 0.606 | AR74: 0.394 | AS74: 0.868 | AT74: 0.939 | AU74: 12 | AV74: 3 | AW74: 3.09 | AX74: 11 | AY74: 1.43 | AZ74: 1.659 | BA74: 1.545 | BB74: 1.659 | BC74: 0.045 | BD74: 0.052 | BE74: 0.048 | BF74: 0.8 | BG74: 0.025 | BH74: 0.958 | BI74: 6.09 | BJ74: 1.37 | BK74: 0.043 | BL74: -1.545 | BM74: -0.63 | BN74: -0.8 | BO74: -0.229 | BP74: 16 | BQ74: 4 | BR74: 2 | BS74: 35 | BT74: 1.093 | BW74: 1.83 | BX74: 0.581 | BY74: 1.205 | BZ74: 0.038 | CA74: 2.75 | CB74: 0.086 | CC74: 6 | CD74: 3 | CE74: 7 | CF74: 4 | CI74: 9.26 | CJ74: 8.928 | CK74: 284 | CL74: 114 | CM74: 45 | CN74: 27 | CO74: 36 | CP74: 229 | CQ74: 19 | CR74: 141 | CS74: 79 | CT74: 0 | CU74: 2 | CV74: 1 | CW74: 44.88 | CX74: 1.402 | CY74: 0 | DB74: 0 | DE74: 6.94 | DF74: 7 | DG74: 1 | DH74: 31 | DI74: 13 | DL74: 6 | DM74: 3 | DO74: 0.1 | DP74: 124.77 | DQ74: 60.7 | DR74: 121.4 | DS74: 3.37 | DT74: 3032 | DU74: 79.8 | DV74: flat | DW74: 100.2 | DX74: 101.85 | DY74: 100.94 | DZ74: 0.74 | EA74: 119 | EB74: 14.54 | EC74: 25.33 | ED74: 120 | EE74: 197 | EF74: TRUE | EG74: 14.6 | EH74: 72.3 | EI74: 232 | EJ74: 180.1 | EK74: 82.3 | EL74: 411.7 | EM74: 1865.8 | EN74: 2390.8 | EO74: 1048 | EP74: 23.4
A75: Bernd Leno | B75: FUL | C75: GKP | D75: GKP | E75: 4.5 | F75: TRUE | G75: TRUE | H75: 34.5 | I75: a | L75: p80201 | M75: 250 | Q75: 3420 | R75: 38 | S75: 38 | T75: 38 | U75: 90 | V75: 122 | W75: 3.211 | X75: 0 | Y75: 0 | AA75: 9 | AB75: 51 | AC75: 8 | AD75: 10 | AE75: 2 | AF75: 556 | AG75: 546 | AH75: -10 | AI75: 124 | AJ75: 0.066 | AK75: 0.07 | AL75: 0 | AM75: 0 | AN75: 0 | AO75: 0 | AP75: 0 | AQ75: 0 | AR75: 0 | AS75: 1 | AT75: 1 | AU75: 18 | AV75: 1 | AW75: 2.41 | AX75: 10 | AY75: 0 | AZ75: 0 | BA75: 0 | BB75: 0 | BC75: 0 | BD75: 0 | BE75: 0 | BH75: 1 | BI75: 0 | BJ75: 0 | BK75: 0 | BL75: 0 | BO75: 0 | BW75: 0.02 | BX75: 0 | BY75: 0.01 | BZ75: 0 | CA75: 0.01 | CB75: 0 | CC75: 0 | CI75: 4.903 | CJ75: 4.903 | CK75: 46 | CL75: 318 | CM75: 4 | CN75: 1 | CO75: 1 | CP75: 45 | CR75: 28 | CS75: 21 | CU75: 1 | CV75: 4 | CW75: 52.73 | CX75: 1.388 | CY75: 98 | CZ75: 65.8 | DA75: -5.8 | DB75: 0 | DC75: 30 | DD75: 30 | DE75: 6.85 | DF75: 3 | DG75: 0 | DI75: 6 | DL75: 0 | DO75: 3.3 | DP75: 120.4 | DQ75: 60.2 | DR75: 120.4 | DS75: 0 | DT75: 3420 | DU75: 89.99 | DV75: flat | DW75: 110.74 | DX75: 114.47 | DY75: 110.13 | DZ75: -0.61 | EA75: 885 | EB75: 13.91 | EC75: 20 | ED75: 120 | EE75: 1380 | EF75: TRUE | EG75: 30.4 | EH75: 6.9 | EI75: 393 | EN75: 342000 | EO75: 342000 | EP75: 28
A76: Emiliano Martínez | B76: AVL | C76: GKP | D76: GKP | E76: 5 | F76: TRUE | G76: TRUE | H76: 34 | I76: a | L76: p98980 | M76: 28 | Q76: 2835 | R76: 32 | S76: 32 | T76: 31.5 | U76: 88.6 | V76: 120 | W76: 3.81 | X76: 0 | Y76: 1 | Z76: 1 | AA76: 7 | AB76: 39 | AC76: 11 | AD76: 10 | AE76: -1 | AF76: 530 | AG76: 525 | AH76: -5 | AI76: 119 | AJ76: 0.092 | AK76: 0.101 | AL76: 0 | AM76: 0 | AN76: 0 | AO76: 0 | AP76: 0 | AQ76: 0 | AR76: 0 | AS76: 0.842 | AT76: 0.969 | AU76: 15 | AV76: 2 | AW76: 3.12 | AX76: 14 | AY76: 0 | AZ76: 0 | BA76: 0 | BB76: 0 | BC76: 0 | BD76: 0 | BE76: 0 | BH76: 1 | BI76: 0 | BJ76: 0 | BK76: 0 | BL76: 0 | BO76: 0 | BW76: 0.08 | BX76: 0.354 | BY76: 0.217 | BZ76: 0.007 | CA76: 0.217 | CB76: 0.007 | CC76: 2 | CD76: 2 | CE76: 2 | CI76: 4.598 | CJ76: 4.244 | CK76: 27 | CL76: 272 | CM76: 0 | CP76: 27 | CR76: 28 | CS76: 16 | CU76: 3 | CV76: 2 | CW76: 42.92 | CX76: 1.363 | CY76: 95 | CZ76: 70.9 | DA76: 3.5 | DB76: 1 | DC76: 48 | DD76: 10 | DE76: 7.07 | DF76: 2 | DG76: 0 | DI76: 17 | DO76: 5 | DP76: 129.04 | DQ76: 64.52 | DR76: 129.04 | DS76: 0 | DT76: 3385 | DU76: 89.09 | DV76: flat | DW76: 83.72 | DX76: 88.92 | DY76: 80.44 | DZ76: -3.27 | EA76: 1536 | EB76: 26.66 | EC76: 2 | ED76: 120 | EE76: 2935 | EF76: TRUE | EG76: 99 | EH76: 39.2 | EI76: 233 | EL76: 1417.5 | EN76: 13069.3 | EO76: 13069.3 | EP76: 23.6
A77: Jérémy Doku | B77: MCI | C77: MID | D77: MID | E77: 7.5 | F77: TRUE | G77: TRUE | H77: 24.2 | I77: a | L77: p248875 | M77: 400 | N77: 4 | Q77: 1773 | R77: 30 | S77: 19 | T77: 19.7 | U77: 59.1 | V77: 120 | W77: 6.091 | X77: 5 | Y77: 8 | Z77: 5 | AA77: 8 | AB77: 18 | AC77: 15 | AD77: 15 | AE77: 0 | AF77: 526 | AG77: 523 | AH77: -3 | AI77: 120 | AJ77: 0.125 | AK77: 0.143 | AL77: 126 | AM77: 6.396 | AN77: 0 | AO77: 0 | AP77: 0 | AQ77: 0.105 | AR77: 0 | AS77: 0.5 | AT77: 0.6 | AU77: 18 | AV77: 5 | AW77: 3.96 | AX77: 15 | AY77: 2.87 | AZ77: 4 | BA77: 3.435 | BB77: 4 | BC77: 0.146 | BD77: 0.203 | BE77: 0.174 | BF77: 5.2 | BG77: 0.264 | BH77: 1.28 | BI77: 6.76 | BJ77: 3.675 | BK77: 0.187 | BL77: 1.565 | BM77: 2.33 | BN77: -0.2 | BO77: -1.13 | BP77: 39 | BQ77: 15 | BR77: 4 | BS77: 194 | BT77: 9.848 | BW77: 5.86 | BX77: 7.553 | BY77: 6.707 | BZ77: 0.34 | CA77: 10.142 | CB77: 0.515 | CC77: 59 | CD77: 13 | CE77: 59 | CF77: 16 | CG77: 10 | CH77: 1 | CI77: 18.844 | CJ77: 9.702 | CK77: 15 | CL77: 88 | CM77: 23 | CN77: 15 | CO77: 13 | CP77: 2 | CR77: 171 | CS77: 4 | CT77: 1 | CW77: 23.2 | CX77: 1.178 | CY77: 0 | DB77: 0 | DE77: 7.33 | DF77: 0 | DG77: 0 | DH77: 23 | DI77: 61 | DJ77: 2 | DL77: 84 | DM77: 49 | DN77: 3 | DO77: 6.4 | DP77: 140.01 | DQ77: 70.03 | DR77: 140.06 | DS77: -0.05 | DT77: 2502 | DU77: 65.85 | DV77: flat | DW77: 27.88 | DX77: 25.77 | DY77: 28.04 | DZ77: 0.16 | EA77: 1456 | EB77: 15.72 | EC77: 2 | ED77: 120 | EE77: 2589 | EF77: TRUE | EG77: 99.2 | EH77: 46.5 | EI77: 20 | EJ77: 45.5 | EK77: 9.1 | EL77: 30.1 | EM77: 516.2 | EN77: 264.4 | EO77: 174.8 | EP77: 14.8
A78: Nikola Milenkovic | B78: NFO | C78: DEF | D78: DEF | E78: 5.5 | F78: TRUE | G78: TRUE | H78: 28.9 | I78: a | L78: p227444 | M78: 471 | Q78: 3375 | R78: 38 | S78: 37 | T78: 37.5 | U78: 88.8 | V78: 119 | W78: 3.173 | X78: 0 | Y78: 1 | AA78: 9 | AB78: 51 | AC78: 2 | AD78: 1 | AE78: -1 | AF78: 401 | AG78: 346 | AH78: -55 | AI78: 118 | AJ78: 0.017 | AK78: 0.017 | AL78: 311 | AM78: 8.293 | AN78: 13 | AO78: 26 | AP78: 0.351 | AQ78: 0.351 | AR78: 0.189 | AS78: 0.974 | AT78: 0.974 | AU78: 21 | AV78: 0 | AW78: 2.62 | AX78: 9 | AY78: 0.83 | AZ78: 0.509 | BA78: 0.67 | BB78: 0.509 | BC78: 0.022 | BD78: 0.014 | BE78: 0.018 | BF78: 0.1 | BG78: 0.003 | BH78: 0.994 | BI78: 4.88 | BJ78: 0.825 | BK78: 0.022 | BL78: -0.67 | BM78: -0.73 | BN78: -0.1 | BO78: 0.321 | BP78: 16 | BQ78: 1 | BR78: 2 | BS78: 35 | BT78: 0.933 | BW78: 0.68 | BX78: 0.268 | BY78: 0.474 | BZ78: 0.013 | CA78: 1.143 | CB78: 0.03 | CC78: 3 | CD78: 1 | CE78: 3 | CI78: 8.07 | CJ78: 7.998 | CK78: 281 | CL78: 107 | CM78: 30 | CN78: 17 | CO78: 29 | CP78: 218 | CQ78: 36 | CR78: 143 | CS78: 89 | CU78: 2 | CV78: 1 | CW78: 54.98 | CX78: 1.466 | CY78: 0 | DB78: 0 | DE78: 6.68 | DF78: 6 | DG78: 0 | DH78: 21 | DI78: 20 | DL78: 3 | DM78: 2 | DN78: 1 | DO78: 2.3 | DP78: 132.2 | DQ78: 66.1 | DR78: 132.2 | DS78: 0 | DT78: 3312 | DU78: 87.15 | DV78: flat | DW78: 80.91 | DX78: 82.41 | DY78: 80.09 | DZ78: -0.82 | EA78: 1174 | EB78: 18.39 | EC78: 12 | ED78: 120 | EE78: 1855 | EF78: TRUE | EG78: 90.2 | EH78: 57.8 | EI78: 122 | EJ78: 210.9 | EK78: 96.4 | EL78: 1125 | EM78: 5039.5 | EN78: 7123.4 | EO78: 2951.5 | EP78: 28.4
A79: Richarlison | B79: TOT | C79: FWD | D79: FWD | E79: 6 | F79: TRUE | G79: TRUE | H79: 29.3 | I79: a | L79: p212319 | M79: 527 | N79: 4 | Q79: 1954 | R79: 32 | S79: 20 | T79: 21.711 | U79: 61.1 | V79: 119 | W79: 5.481 | X79: 11 | Y79: 4 | Z79: 4 | AA79: 7 | AB79: 27 | AC79: 17 | AD79: 17 | AE79: 0 | AF79: 505 | AG79: 493 | AH79: -12 | AI79: 119 | AJ79: 0.143 | AK79: 0.167 | AL79: 147 | AM79: 6.771 | AN79: 0 | AO79: 0 | AP79: 0 | AQ79: 0.15 | AR79: 0 | AS79: 0.526 | AT79: 0.594 | AU79: 18 | AV79: 1 | AW79: 3.21 | AX79: 13 | AY79: 8.64 | AZ79: 9.866 | BA79: 9.253 | BB79: 9.866 | BC79: 0.398 | BD79: 0.454 | BE79: 0.426 | BF79: 12 | BG79: 0.553 | BH79: 1.055 | BI79: 25.27 | BJ79: 9.115 | BK79: 0.42 | BL79: 1.747 | BM79: 3.36 | BN79: -1 | BO79: -1.226 | BP79: 61 | BQ79: 26 | BR79: 10 | BS79: 125 | BT79: 5.757 | BV79: 3 | BW79: 1.46 | BX79: 3.408 | BY79: 2.434 | BZ79: 0.112 | CA79: 11.687 | CB79: 0.538 | CC79: 19 | CD79: 5 | CE79: 20 | CG79: 1 | CI79: 11.188 | CJ79: 2.256 | CK79: 60 | CL79: 60 | CM79: 27 | CN79: 16 | CO79: 5 | CP79: 51 | CQ79: 3 | CR79: 139 | CS79: 69 | CT79: 0.7 | CV79: 1 | CW79: 25.64 | CX79: 1.181 | CY79: 0 | DB79: 0 | DE79: 6.87 | DF79: 5 | DG79: 0 | DH79: 23 | DI79: 33 | DL79: 12 | DM79: 30 | DN79: 10 | DO79: 2 | DP79: 61.65 | DQ79: 36.63 | DR79: 73.26 | DS79: -11.61 | DT79: 697 | DU79: 18.34 | DV79: fade (losing his place) | DW79: 65.59 | DX79: 64.98 | DY79: 63.14 | DZ79: -2.44 | EA79: 1264 | EB79: 25.54 | EC79: 5 | ED79: 120 | EE79: 2336 | EF79: TRUE | EG79: 88.1 | EH79: 45.6 | EI79: 74 | EJ79: 32 | EK79: 15.6 | EL79: 97.7 | EM79: 211.2 | EN79: 802.8 | EO79: 167.2 | EP79: 16.4
A80: Ferdi Kadioglu | B80: BHA | C80: DEF | D80: DEF | E80: 4.5 | F80: TRUE | G80: TRUE | H80: 26.9 | I80: a | L80: p231416 | M80: 113 | O80: 2 | Q80: 3130 | R80: 37 | S80: 34 | T80: 34.778 | U80: 84.6 | V80: 118 | W80: 3.393 | X80: 1 | Y80: 2 | AA80: 10 | AB80: 41 | AC80: 7 | AD80: 8 | AE80: 1 | AF80: 514 | AG80: 493 | AH80: -21 | AI80: 119 | AJ80: 0.059 | AK80: 0.063 | AL80: 170 | AM80: 4.888 | AN80: 2 | AO80: 4 | AP80: 0.059 | AQ80: 0.059 | AR80: 0 | AS80: 0.895 | AT80: 0.946 | AU80: 25 | AV80: 1 | AW80: 3.24 | AX80: 15 | AY80: 2.06 | AZ80: 2.02 | BA80: 2.04 | BB80: 2.02 | BC80: 0.059 | BD80: 0.058 | BE80: 0.059 | BF80: 3.1 | BG80: 0.089 | BH80: 1.057 | BI80: 2.5 | BJ80: 2.178 | BK80: 0.063 | BL80: -1.04 | BM80: 1.04 | BN80: -2.1 | BO80: 0.04 | BP80: 28 | BQ80: 13 | BR80: 3 | BS80: 58 | BT80: 1.668 | BW80: 3.31 | BX80: 2.245 | BY80: 2.777 | BZ80: 0.08 | CA80: 4.817 | CB80: 0.139 | CC80: 22 | CD80: 2 | CE80: 21 | CF80: 23 | CH80: 25 | CI80: 14.009 | CJ80: 11.696 | CK80: 113 | CL80: 130 | CM80: 57 | CN80: 39 | CO80: 26 | CP80: 81 | CQ80: 7 | CR80: 136 | CS80: 32 | CT80: 0.3 | CW80: 44.61 | CX80: 1.283 | CY80: 0 | DB80: 0 | DE80: 6.93 | DF80: 6 | DG80: 0 | DH80: 22 | DI80: 36 | DL80: 12 | DM80: 18 | DN80: 7 | DO80: 3.1 | DP80: 118.37 | DQ80: 59.43 | DR80: 118.86 | DS80: -0.49 | DT80: 3198 | DU80: 84.15 | DV80: flat | DW80: 96.95 | DX80: 99.51 | DY80: 97.01 | DZ80: 0.06 | EA80: 392 | EB80: 17.62 | EC80: 14 | ED80: 120 | EE80: 630 | EF80: TRUE | EG80: 14 | EH80: 7.5 | EI80: 394 | EJ80: 111.8 | EK80: 54 | EL80: 149 | EM80: 1534.5 | EN80: 1127 | EO80: 649.8 | EP80: 26.5
A81: Ismaïla Sarr | B81: CRY | C81: MID | D81: MID | E81: 6.5 | F81: TRUE | G81: TRUE | H81: 28.5 | I81: a | L81: p232185 | M81: 208 | N81: 2 | Q81: 2173 | R81: 28 | S81: 24 | T81: 24.144 | U81: 77.6 | V81: 117 | W81: 4.846 | X81: 9 | Y81: 2 | Z81: 1 | AA81: 9 | AB81: 29 | AC81: 9 | AD81: 10 | AE81: 1 | AF81: 359 | AG81: 346 | AH81: -13 | AI81: 118 | AJ81: 0.077 | AK81: 0.083 | AL81: 137 | AM81: 5.674 | AN81: 0 | AO81: 0 | AP81: 0 | AQ81: 0.083 | AR81: 0 | AS81: 0.632 | AT81: 0.786 | AU81: 13 | AV81: 2 | AW81: 3.54 | AX81: 15 | AY81: 10.93 | AZ81: 11.543 | BA81: 11.237 | BB81: 9.26 | BC81: 0.453 | BD81: 0.478 | BE81: 0.465 | BF81: 9.6 | BG81: 0.398 | BH81: 0.992 | BI81: 21.75 | BJ81: 10.838 | BK81: 0.449 | BL81: -2.237 | BM81: -1.33 | BN81: -0.6 | BO81: -0.613 | BP81: 48 | BQ81: 21 | BR81: 11 | BS81: 99 | BT81: 4.1 | BU81: 3 | BV81: 1 | BW81: 1.17 | BX81: 2.2 | BY81: 1.685 | BZ81: 0.07 | CA81: 12.922 | CB81: 0.535 | CC81: 19 | CD81: 3 | CE81: 19 | CF81: 3 | CH81: 0 | CI81: 12.696 | CJ81: 3.183 | CK81: 40 | CL81: 79 | CM81: 18 | CN81: 9 | CO81: 8 | CP81: 28 | CQ81: 4 | CR81: 95 | CS81: 24 | CT81: 0.4 | CV81: 2 | CW81: 31.25 | CX81: 1.294 | CY81: 0 | DB81: 0 | DE81: 6.91 | DF81: 2 | DG81: 0 | DH81: 12 | DI81: 42 | DJ81: 2 | DL81: 11 | DM81: 43 | DN81: 14 | DO81: 7.6 | DP81: 159.76 | DQ81: 79.88 | DR81: 159.76 | DS81: 0 | DT81: 3135 | DU81: 82.5 | DV81: flat | DW81: 45.16 | DX81: 42.82 | DY81: 44.44 | DZ81: -0.71 | EA81: 1484 | EB81: 19.56 | EC81: 3 | ED81: 120 | EE81: 3237 | EF81: TRUE | EG81: 95.4 | EH81: 30.4 | EI81: 39 | EJ81: 45.3 | EK81: 21.9 | EL81: 114.4 | EM81: 193.4 | EN81: 1289.4 | EO81: 168.2 | EP81: 18.6
A82: Yankuba Minteh | B82: BHA | C82: MID | D82: MID | E82: 6 | F82: TRUE | G82: TRUE | H82: 22.1 | I82: i | J82: Leg injury - Expected back 28 Nov | K82: 0 | L82: p592031 | M82: 122 | O82: 3 | Q82: 2389 | R82: 34 | S82: 26 | T82: 26.544 | U82: 70.3 | V82: 117 | W82: 4.408 | X82: 3 | Y82: 8 | Z82: 4 | AA82: 11 | AB82: 33 | AC82: 9 | AD82: 10 | AE82: 1 | AF82: 466 | AG82: 459 | AH82: -7 | AI82: 118 | AJ82: 0.077 | AK82: 0.083 | AL82: 185 | AM82: 6.969 | AN82: 1 | AO82: 2 | AP82: 0.038 | AQ82: 0.115 | AR82: 0.038 | AS82: 0.684 | AT82: 0.735 | AU82: 17 | AV82: 1 | AW82: 2.88 | AX82: 11 | AY82: 3.81 | AZ82: 4.752 | BA82: 4.281 | BB82: 4.752 | BC82: 0.144 | BD82: 0.179 | BE82: 0.161 | BF82: 3 | BG82: 0.113 | BH82: 1.054 | BI82: 7.94 | BJ82: 4.016 | BK82: 0.151 | BL82: -1.281 | BM82: -0.81 | BN82: 0 | BO82: -0.942 | BP82: 41 | BQ82: 11 | BR82: 4 | BS82: 185 | BT82: 6.969 | BW82: 5.06 | BX82: 5.842 | BY82: 5.451 | BZ82: 0.205 | CA82: 9.732 | CB82: 0.367 | CC82: 44 | CD82: 11 | CE82: 44 | CF82: 37 | CG82: 1 | CH82: 32 | CI82: 16.411 | CJ82: 8.574 | CK82: 33 | CL82: 96 | CM82: 56 | CN82: 37 | CO82: 17 | CP82: 16 | CR82: 162 | CS82: 19 | CT82: 0.7 | CV82: 1 | CW82: 34.09 | CX82: 1.284 | CY82: 0 | DB82: 0 | DE82: 7.07 | DF82: 3 | DG82: 0 | DH82: 32 | DI82: 22 | DJ82: 1 | DL82: 65 | DM82: 34 | DN82: 10 | DO82: 0.7 | DP82: 106.7 | DQ82: 41.37 | DR82: 82.74 | DS82: 23.96 | DT82: 2713 | DU82: 71.4 | DV82: ramp-up (injury / late WC return) | DW82: 79.08 | DX82: 83.07 | DY82: 77.15 | DZ82: -1.93 | EA82: 483 | EB82: 20 | EC82: 2.67 | ED82: 120 | EE82: 895 | EF82: TRUE | EG82: 20.5 | EH82: 10.2 | EI82: 75 | EJ82: 58.3 | EK82: 12.9 | EL82: 54.3 | EM82: 558 | EN82: 438.3 | EO82: 245.5 | EP82: 20.4
A83: Pedro Porro | B83: TOT | C83: DEF | D83: DEF | E83: 5.5 | F83: TRUE | G83: TRUE | H83: 26.9 | I83: a | L83: p441164 | M83: 499 | O83: 1 | P83: 1 | Q83: 2793 | R83: 34 | S83: 32 | T83: 31.033 | U83: 82.1 | V83: 117 | W83: 3.77 | X83: 1 | Y83: 3 | Z83: 2 | AA83: 9 | AB83: 40 | AC83: 8 | AD83: 9 | AE83: 1 | AF83: 502 | AG83: 475 | AH83: -27 | AI83: 118 | AJ83: 0.068 | AK83: 0.073 | AL83: 218 | AM83: 7.025 | AN83: 8 | AO83: 16 | AP83: 0.25 | AQ83: 0.25 | AR83: 0.062 | AS83: 0.842 | AT83: 0.912 | AU83: 19 | AV83: 4 | AW83: 3.36 | AX83: 11 | AY83: 1.05 | AZ83: 1.403 | BA83: 1.226 | BB83: 1.403 | BC83: 0.034 | BD83: 0.045 | BE83: 0.04 | BF83: 1.4 | BG83: 0.045 | BH83: 0.999 | BI83: 7.41 | BJ83: 1.049 | BK83: 0.034 | BL83: -0.226 | BM83: 0.35 | BN83: -0.4 | BO83: -0.353 | BP83: 32 | BQ83: 8 | BS83: 39 | BT83: 1.257 | BV83: 1 | BW83: 4.37 | BX83: 4.248 | BY83: 4.309 | BZ83: 0.139 | CA83: 5.535 | CB83: 0.178 | CC83: 53 | CD83: 8 | CE83: 53 | CF83: 61 | CG83: 2 | CH83: 73 | CI83: 10.605 | CJ83: 8.792 | CK83: 142 | CL83: 132 | CM83: 76 | CN83: 50 | CO83: 31 | CP83: 102 | CQ83: 10 | CR83: 140 | CS83: 19 | CT83: 0.3 | CV83: 5 | CW83: 37.75 | CX83: 1.216 | CY83: 0 | DB83: 0 | DE83: 7.14 | DF83: 10 | DG83: 0 | DH83: 32 | DI83: 26 | DL83: 19 | DM83: 9 | DN83: 1 | DO83: 23.3 | DP83: 143.81 | DQ83: 71.95 | DR83: 143.9 | DS83: -0.09 | DT83: 3084 | DU83: 81.15 | DV83: flat | DW83: 53.36 | DX83: 56.94 | DY83: 47.73 | DZ83: -5.63 | EA83: 1613 | EB83: 17.66 | EC83: 3.56 | ED83: 116 | EE83: 3849 | EF83: TRUE | EG83: 99.8 | EH83: 20.9 | EI83: 123 | EJ83: 87.3 | EK83: 71.6 | EL83: 52.7 | EM83: 2277.3 | EN83: 648.2 | EO83: 504.6 | EP83: 23.9
A84: Matty Cash | B84: AVL | C84: DEF | D84: DEF | E84: 4.5 | F84: TRUE | G84: TRUE | H84: 29 | I84: a | L84: p199796 | M84: 32 | O84: 1 | Q84: 3016 | R84: 35 | S84: 34 | T84: 33.511 | U84: 86.2 | V84: 117 | W84: 3.491 | X84: 3 | Y84: 3 | Z84: 3 | AA84: 8 | AB84: 38 | AC84: 7 | AD84: 7 | AE84: 0 | AF84: 450 | AG84: 431 | AH84: -19 | AI84: 117 | AJ84: 0.06 | AK84: 0.064 | AL84: 186 | AM84: 5.55 | AN84: 1 | AO84: 2 | AP84: 0.029 | AQ84: 0.029 | AR84: 0 | AS84: 0.895 | AT84: 0.943 | AU84: 22 | AV84: 2 | AW84: 3.41 | AX84: 15 | AY84: 1.14 | AZ84: 1.218 | BA84: 1.179 | BB84: 1.218 | BC84: 0.034 | BD84: 0.036 | BE84: 0.035 | BF84: 1.6 | BG84: 0.048 | BH84: 1.04 | BI84: 6.23 | BJ84: 1.186 | BK84: 0.035 | BL84: 1.821 | BM84: 0.46 | BN84: 1.4 | BO84: -0.078 | BP84: 30 | BQ84: 10 | BS84: 41 | BT84: 1.223 | BW84: 2.94 | BX84: 3.215 | BY84: 3.077 | BZ84: 0.092 | CA84: 4.256 | CB84: 0.127 | CC84: 31 | CD84: 4 | CE84: 30 | CF84: 26 | CG84: 1 | CH84: 47 | CI84: 10.301 | CJ84: 8.073 | CK84: 120 | CL84: 88 | CM84: 66 | CN84: 32 | CO84: 22 | CP84: 84 | CQ84: 14 | CR84: 137 | CS84: 32 | CT84: 0.1 | CU84: 2 | CV84: 2 | CW84: 45.45 | CX84: 1.356 | CY84: 0 | DB84: 0 | DE84: 6.93 | DF84: 9 | DG84: 0 | DH84: 41 | DI84: 30 | DL84: 11 | DM84: 17 | DN84: 4 | DO84: 8.4 | DP84: 127.1 | DQ84: 63.55 | DR84: 127.1 | DS84: 0 | DT84: 3342 | DU84: 87.96 | DV84: flat | DW84: 93.39 | DX84: 95.21 | DY84: 93.4 | DZ84: 0.01 | EA84: 738 | EB84: 17.64 | EC84: 18.29 | ED84: 120 | EE84: 1172 | EF84: TRUE | EG84: 26.4 | EH84: 9 | EI84: 395 | EJ84: 100.5 | EK84: 73.6 | EL84: 100.5 | EM84: 2558.2 | EN84: 980 | EO84: 708.6 | EP84: 25.8
A85: Dan Ballard | B85: SUN | C85: DEF | D85: DEF | E85: 5 | F85: TRUE | G85: TRUE | H85: 26.9 | I85: a | L85: p223827 | M85: 532 | Q85: 2144 | R85: 29 | S85: 24 | T85: 23.822 | U85: 73.9 | V85: 116 | W85: 4.869 | X85: 2 | Y85: 2 | Z85: 0 | AA85: 6 | AB85: 35 | AC85: 9 | AD85: 8 | AE85: -1 | AF85: 340 | AG85: 300 | AH85: -40 | AI85: 115 | AJ85: 0.078 | AK85: 0.084 | AL85: 264 | AM85: 11.082 | AN85: 15 | AO85: 30 | AP85: 0.625 | AQ85: 0.625 | AR85: 0.333 | AS85: 0.632 | AT85: 0.759 | AU85: 13 | AV85: 3 | AW85: 4 | AX85: 17 | AY85: 2.46 | AZ85: 3.695 | BA85: 3.078 | BB85: 3.695 | BC85: 0.103 | BD85: 0.155 | BE85: 0.129 | BF85: 2.3 | BG85: 0.097 | BH85: 0.985 | BI85: 2.46 | BJ85: 2.422 | BK85: 0.102 | BL85: -1.078 | BM85: -0.16 | BN85: -0.3 | BO85: -1.235 | BP85: 26 | BQ85: 9 | BR85: 7 | BS85: 72 | BT85: 3.022 | BV85: 1 | BW85: 0.63 | BX85: 1.581 | BY85: 1.105 | BZ85: 0.046 | CA85: 4.183 | CB85: 0.176 | CC85: 14 | CD85: 3 | CE85: 15 | CF85: 0 | CI85: 4.753 | CJ85: 2.609 | CK85: 231 | CL85: 69 | CM85: 33 | CN85: 18 | CO85: 20 | CP85: 185 | CQ85: 24 | CR85: 168 | CS85: 106 | CT85: 0 | CV85: 3 | CW85: 33.2 | CX85: 1.394 | CY85: 0 | DB85: 0 | DE85: 6.85 | DF85: 4 | DG85: 1 | DH85: 29 | DI85: 30 | DJ85: 1 | DL85: 3 | DM85: 6 | DN85: 3 | DO85: 4.5 | DP85: 135.56 | DQ85: 67.88 | DR85: 135.76 | DS85: -0.2 | DT85: 2867 | DU85: 75.45 | DV85: flat | DW85: 93.01 | DX85: 97.43 | DY85: 91.38 | DZ85: -1.63 | EA85: 778 | EB85: 18.63 | EC85: 18 | ED85: 120 | EE85: 1532 | EF85: TRUE | EG85: 35 | EH85: 10.2 | EI85: 236 | EJ85: 82.5 | EK85: 29.8 | EL85: 142.9 | EM85: 696.6 | EN85: 1939.8 | EO85: 512.5 | EP85: 18.5
A86: Jake O'Brien | B86: EVE | C86: DEF | D86: DEF | E86: 5 | F86: TRUE | G86: TRUE | H86: 25.3 | I86: a | L86: p512462 | M86: 232 | Q86: 3118 | R86: 37 | S86: 35 | T86: 34.644 | U86: 84.3 | V86: 116 | W86: 3.348 | X86: 1 | Y86: 3 | Z86: 1 | AA86: 10 | AB86: 46 | AC86: 2 | AD86: 4 | AE86: 2 | AF86: 368 | AG86: 336 | AH86: -32 | AI86: 118 | AJ86: 0.017 | AK86: 0.018 | AL86: 231 | AM86: 6.668 | AN86: 6 | AO86: 12 | AP86: 0.171 | AQ86: 0.171 | AR86: 0.086 | AS86: 0.921 | AT86: 0.973 | AU86: 20 | AV86: 0 | AW86: 2.74 | AX86: 9 | AY86: 1.67 | AZ86: 1.307 | BA86: 1.488 | BB86: 1.307 | BC86: 0.048 | BD86: 0.038 | BE86: 0.043 | BF86: 2.3 | BG86: 0.066 | BH86: 1.149 | BI86: 2.44 | BJ86: 1.92 | BK86: 0.055 | BL86: -0.488 | BM86: 0.63 | BN86: -1.3 | BO86: 0.363 | BP86: 13 | BQ86: 6 | BR86: 1 | BS86: 37 | BT86: 1.068 | BV86: 1 | BW86: 1 | BX86: 0.724 | BY86: 0.862 | BZ86: 0.025 | CA86: 2.351 | CB86: 0.068 | CC86: 17 | CD86: 0 | CE86: 17 | CF86: 13 | CI86: 6.487 | CJ86: 5.053 | CK86: 174 | CL86: 114 | CM86: 57 | CN86: 32 | CO86: 15 | CP86: 144 | CQ86: 16 | CR86: 195 | CS86: 116 | CT86: 0.2 | CU86: 1 | CV86: 2 | CW86: 53.49 | CX86: 1.544 | CY86: 0 | DB86: 0 | DE86: 6.72 | DF86: 6 | DG86: 1 | DH86: 23 | DI86: 17 | DK86: 1 | DL86: 6 | DM86: 21 | DN86: 4 | DO86: 0.5 | DP86: 114.1 | DQ86: 57.07 | DR86: 114.14 | DS86: -0.04 | DT86: 3164 | DU86: 83.25 | DV86: flat | DW86: 99.3 | DX86: 104.94 | DY86: 97.94 | DZ86: -1.36 | EA86: 360 | EB86: 15.37 | EC86: 0.53 | ED86: 120 | EE86: 542 | EF86: TRUE | EG86: 16 | EH86: 30.5 | EI86: 234 | EJ86: 239.8 | EK86: 84.3 | EL86: 183.4 | EM86: 2094.8 | EN86: 3616.3 | EO86: 1326.4 | EP86: 26.9
A87: Micky van de Ven | B87: TOT | C87: DEF | D87: DEF | E87: 5 | F87: TRUE | G87: TRUE | H87: 25.3 | I87: a | L87: p491279 | M87: 503 | Q87: 3041 | R87: 35 | S87: 35 | T87: 33.789 | U87: 86.9 | V87: 116 | W87: 3.433 | X87: 4 | Y87: 1 | Z87: 1 | AA87: 9 | AB87: 50 | AC87: 10 | AD87: 9 | AE87: -1 | AF87: 431 | AG87: 401 | AH87: -30 | AI87: 115 | AJ87: 0.086 | AK87: 0.094 | AL87: 212 | AM87: 6.274 | AN87: 3 | AO87: 6 | AP87: 0.086 | AQ87: 0.086 | AR87: 0.057 | AS87: 0.921 | AT87: 0.943 | AU87: 23 | AV87: 3 | AW87: 4.8 | AX87: 23 | AY87: 2.82 | AZ87: 2.453 | BA87: 2.636 | BB87: 2.453 | BC87: 0.083 | BD87: 0.073 | BE87: 0.078 | BF87: 4.1 | BG87: 0.121 | BH87: 1.17 | BI87: 3.97 | BJ87: 3.298 | BK87: 0.098 | BL87: 1.364 | BM87: 1.28 | BN87: -0.1 | BO87: 0.367 | BP87: 16 | BQ87: 6 | BR87: 1 | BS87: 33 | BT87: 0.977 | BV87: 2 | BW87: 0.38 | BX87: 1.014 | BY87: 0.697 | BZ87: 0.021 | CA87: 3.333 | CB87: 0.099 | CC87: 5 | CD87: 1 | CE87: 6 | CI87: 5.582 | CJ87: 5.244 | CK87: 174 | CL87: 121 | CM87: 38 | CN87: 19 | CO87: 22 | CP87: 131 | CQ87: 22 | CR87: 119 | CS87: 47 | CU87: 1 | CV87: 2 | CW87: 42.99 | CX87: 1.272 | CY87: 0 | DB87: 0 | DE87: 6.69 | DF87: 9 | DG87: 1 | DH87: 28 | DI87: 22 | DJ87: 0 | DK87: 1 | DL87: 11 | DM87: 5 | DN87: 2 | DO87: 7.4 | DP87: 113.04 | DQ87: 56.52 | DR87: 113.04 | DS87: 0 | DT87: 3089 | DU87: 81.3 | DV87: flat | DW87: 80.86 | DX87: 89.45 | DY87: 73.78 | DZ87: -7.07 | EA87: 1451 | EB87: 23.64 | EC87: 4 | ED87: 120 | EE87: 3041 | EF87: TRUE | EG87: 67.5 | EH87: 7.6 | EI87: 235 | EJ87: 190.1 | EK87: 92.2 | EL87: 506.8 | EM87: 1153.5 | EN87: 4362.1 | EO87: 912.3 | EP87: 26.2
A88: Reece James | B88: CHE | C88: DEF | D88: DEF | E88: 5.5 | F88: TRUE | G88: TRUE | H88: 26.7 | I88: a | L88: p225796 | M88: 142 | O88: 1 | P88: 1 | Q88: 1957 | R88: 29 | S88: 20 | T88: 21.744 | U88: 67.5 | V88: 115 | W88: 5.289 | X88: 2 | Y88: 6 | Z88: 4 | AA88: 8 | AB88: 20 | AC88: 11 | AD88: 12 | AE88: 1 | AF88: 493 | AG88: 479 | AH88: -14 | AI88: 116 | AJ88: 0.096 | AK88: 0.106 | AL88: 128 | AM88: 5.887 | AN88: 2 | AO88: 4 | AP88: 0.1 | AQ88: 0.1 | AR88: 0 | AS88: 0.526 | AT88: 0.655 | AU88: 14 | AV88: 1 | AW88: 3.64 | AX88: 18 | AY88: 1.04 | AZ88: 1.228 | BA88: 1.134 | BB88: 1.228 | BC88: 0.048 | BD88: 0.056 | BE88: 0.052 | BF88: 2.1 | BG88: 0.097 | BH88: 1.124 | BI88: 2.85 | BJ88: 1.169 | BK88: 0.054 | BL88: 0.866 | BM88: 1.06 | BN88: -0.1 | BO88: -0.188 | BP88: 22 | BQ88: 7 | BS88: 16 | BT88: 0.736 | BW88: 3.2 | BX88: 3.993 | BY88: 3.597 | BZ88: 0.165 | CA88: 4.731 | CB88: 0.218 | CC88: 27 | CD88: 8 | CE88: 27 | CF88: 30 | CG88: 1 | CH88: 81 | CI88: 11.532 | CJ88: 9.755 | CK88: 80 | CL88: 101 | CM88: 48 | CN88: 33 | CO88: 33 | CP88: 41 | CQ88: 6 | CR88: 112 | CS88: 31 | CT88: 0.3 | CU88: 1 | CV88: 3 | CW88: 28.75 | CX88: 1.322 | CY88: 0 | DB88: 0 | DE88: 7.23 | DF88: 4 | DG88: 0 | DH88: 27 | DI88: 22 | DL88: 11 | DM88: 13 | DN88: 1 | DO88: 8.1 | DP88: 111.71 | DQ88: 56.28 | DR88: 112.56 | DS88: -0.85 | DT88: 2400 | DU88: 63.15 | DV88: flat | DW88: 65.76 | DX88: 67.85 | DY88: 63.2 | DZ88: -2.56 | EA88: 1543 | EB88: 18.93 | EC88: 10 | ED88: 120 | EE88: 3024 | EF88: TRUE | EG88: 98.3 | EH88: 36.9 | EI88: 125 | EJ88: 89 | EK88: 122.3 | EL88: 72.5 | EM88: 1725.7 | EN88: 544.1 | EO88: 413.7 | EP88: 17
A89: Evanilson | B89: BOU | C89: FWD | D89: FWD | E89: 6 | F89: TRUE | G89: TRUE | H89: 26.9 | I89: a | L89: p444102 | M89: 79 | Q89: 2741 | R89: 36 | S89: 32 | T89: 30.456 | U89: 76.1 | V89: 115 | W89: 3.776 | X89: 6 | Y89: 7 | Z89: 1 | AA89: 11 | AB89: 40 | AC89: 6 | AD89: 6 | AE89: 0 | AF89: 412 | AG89: 404 | AH89: -8 | AI89: 115 | AJ89: 0.052 | AK89: 0.055 | AL89: 135 | AM89: 4.433 | AN89: 0 | AO89: 0 | AP89: 0 | AQ89: 0 | AR89: 0 | AS89: 0.842 | AT89: 0.833 | AU89: 23 | AV89: 0 | AW89: 2.22 | AX89: 8 | AY89: 10.64 | AZ89: 11.83 | BA89: 11.235 | BB89: 11.83 | BC89: 0.349 | BD89: 0.388 | BE89: 0.369 | BF89: 6.9 | BG89: 0.227 | BH89: 0.842 | BI89: 23.11 | BJ89: 8.961 | BK89: 0.294 | BL89: -5.235 | BM89: -3.74 | BN89: -0.9 | BO89: -1.19 | BP89: 70 | BQ89: 22 | BR89: 10 | BS89: 140 | BT89: 4.597 | BV89: 2 | BW89: 1.48 | BX89: 3.069 | BY89: 2.275 | BZ89: 0.075 | CA89: 13.51 | CB89: 0.444 | CC89: 30 | CD89: 3 | CE89: 31 | CG89: 1 | CI89: 15.95 | CJ89: 3.486 | CK89: 42 | CL89: 80 | CM89: 13 | CN89: 5 | CO89: 8 | CP89: 29 | CQ89: 6 | CR89: 113 | CS89: 47 | CT89: 0.6 | CV89: 1 | CW89: 39.02 | CX89: 1.281 | CY89: 0 | DB89: 0 | DE89: 6.77 | DF89: 2 | DG89: 0 | DH89: 26 | DI89: 37 | DJ89: 2 | DL89: 16 | DM89: 39 | DN89: 30 | DO89: 2.1 | DP89: 141.07 | DQ89: 71.07 | DR89: 142.14 | DS89: -1.07 | DT89: 2662 | DU89: 70.05 | DV89: flat | DW89: 56.49 | DX89: 58.52 | DY89: 50.03 | DZ89: -6.46 | EA89: 1480 | EB89: 25.73 | EC89: 6.86 | ED89: 120 | EE89: 2958 | EF89: TRUE | EG89: 93.2 | EH89: 34.9 | EI89: 76 | EJ89: 39.2 | EK89: 19.6 | EL89: 88.4 | EM89: 244 | EN89: 1205.1 | EO89: 202.9 | EP89: 23.8
A90: Keane Lewis-Potter | B90: BRE | C90: MID | D90: DEF | E90: 5.5 | F90: TRUE | G90: TRUE | H90: 25.5 | I90: a | L90: p249231 | M90: 86 | P90: 1 | Q90: 1960 | R90: 36 | S90: 22 | T90: 21.778 | U90: 54.4 | V90: 115 | W90: 5.281 | X90: 3 | Y90: 4 | Z90: 3 | AA90: 9 | AB90: 32 | AC90: 5 | AD90: 6 | AE90: 1 | AF90: 356 | AG90: 346 | AH90: -10 | AI90: 116 | AJ90: 0.043 | AK90: 0.045 | AL90: 74 | AM90: 3.398 | AN90: 0 | AO90: 0 | AP90: 0 | AQ90: 0 | AR90: 0 | AS90: 0.579 | AT90: 0.583 | AU90: 23 | AV90: 2 | AW90: 4.06 | AX90: 21 | AY90: 3.01 | AZ90: 3.215 | BA90: 3.112 | BB90: 3.215 | BC90: 0.138 | BD90: 0.148 | BE90: 0.143 | BF90: 2.3 | BG90: 0.106 | BH90: 0.982 | BI90: 12.88 | BJ90: 2.955 | BK90: 0.136 | BL90: -0.112 | BM90: -0.71 | BN90: 0.7 | BO90: -0.205 | BP90: 31 | BQ90: 9 | BR90: 2 | BS90: 74 | BT90: 3.398 | BV90: 1 | BW90: 2.51 | BX90: 2.714 | BY90: 2.612 | BZ90: 0.12 | CA90: 5.725 | CB90: 0.263 | CC90: 19 | CD90: 6 | CE90: 19 | CF90: 22 | CH90: 2 | CI90: 7.843 | CJ90: 3.192 | CK90: 51 | CL90: 96 | CM90: 23 | CN90: 14 | CO90: 12 | CP90: 37 | CQ90: 2 | CR90: 86 | CS90: 11 | CT90: 0.3 | CU90: 1 | CW90: 33.74 | CX90: 1.549 | CY90: 0 | DB90: 0 | DE90: 6.67 | DF90: 1 | DG90: 0 | DH90: 15 | DI90: 36 | DL90: 16 | DM90: 15 | DN90: 3 | DO90: 0.5 | DP90: 66.66 | DQ90: 33.73 | DR90: 67.46 | DS90: -0.8 | DT90: 1659 | DU90: 43.65 | DV90: flat | DW90: 87.3 | DX90: 79.38 | DY90: 89.4 | DZ90: 2.1 | EA90: 46 | EB90: 19.15 | EC90: 12 | ED90: 114.5 | EE90: 78 | EF90: TRUE | EG90: 1.8 | EH90: 12.4 | EI90: 124 | EJ90: 63.2 | EK90: 26.5 | EL90: 103.2 | EM90: 629.7 | EN90: 750.3 | EO90: 342.4 | EP90: 17
A91: Cole Palmer | B91: CHE | C91: MID | D91: MID | E91: 9.5 | F91: TRUE | G91: TRUE | H91: 24.3 | I91: a | L91: p244851 | M91: 154 | N91: 1 | P91: 3 | Q91: 1954 | R91: 26 | S91: 24 | T91: 21.711 | U91: 75.2 | V91: 114 | W91: 5.251 | X91: 10 | Y91: 2 | Z91: 1 | AA91: 3 | AB91: 33 | AC91: 11 | AD91: 11 | AE91: 0 | AF91: 430 | AG91: 425 | AH91: -5 | AI91: 114 | AJ91: 0.096 | AK91: 0.107 | AL91: 135 | AM91: 6.218 | AN91: 2 | AO91: 4 | AP91: 0.083 | AQ91: 0.167 | AR91: 0.083 | AS91: 0.632 | AT91: 0.808 | AU91: 14 | AV91: 2 | AW91: 4.22 | AX91: 20 | AY91: 10.55 | AZ91: 10.258 | BA91: 10.404 | BB91: 5.691 | BC91: 0.486 | BD91: 0.472 | BE91: 0.479 | BF91: 10.1 | BG91: 0.465 | BH91: 1.039 | BI91: 45.05 | BJ91: 10.958 | BK91: 0.505 | BL91: -0.404 | BM91: -0.45 | BN91: -0.1 | BO91: 0.292 | BP91: 64 | BQ91: 25 | BR91: 6 | BS91: 93 | BT91: 4.284 | BU91: 5 | BW91: 2.49 | BX91: 2.123 | BY91: 2.307 | BZ91: 0.106 | CA91: 12.71 | CB91: 0.585 | CC91: 24 | CD91: 3 | CE91: 24 | CF91: 5 | CG91: 3 | CH91: 4 | CI91: 16.862 | CJ91: 10.538 | CK91: 27 | CL91: 83 | CM91: 25 | CN91: 12 | CO91: 15 | CP91: 12 | CR91: 84 | CT91: 1 | CV91: 1 | CW91: 31.13 | CX91: 1.434 | CY91: 0 | DB91: 0 | DE91: 7.04 | DF91: 5 | DG91: 0 | DH91: 13 | DI91: 37 | DL91: 22 | DM91: 35 | DN91: 2 | DO91: 11.2 | DP91: 191.31 | DQ91: 95.75 | DR91: 191.5 | DS91: -0.19 | DT91: 2884 | DU91: 75.9 | DV91: flat | DW91: 6.59 | DX91: 5.38 | DY91: 6.71 | DZ91: 0.11 | EA91: 1418 | EB91: 6.87 | EC91: 0.67 | ED91: 114.4 | EE91: 2890 | EF91: TRUE | EG91: 99.9 | EH91: 40.7 | EI91: 4 | EJ91: 30.5 | EK91: 21 | EL91: 81.4 | EM91: 187.8 | EN91: 847.1 | EO91: 153.7 | EP91: 17.1
A92: Jean-Philippe Mateta | B92: CRY | C92: FWD | D92: FWD | E92: 6.5 | F92: TRUE | G92: TRUE | H92: 29.1 | I92: a | L92: p231747 | M92: 223 | N92: 1 | Q92: 2210 | R92: 32 | S92: 25 | T92: 24.556 | U92: 69.1 | V92: 114 | W92: 4.643 | X92: 12 | Y92: 0 | AA92: 8 | AB92: 29 | AC92: 13 | AD92: 14 | AE92: 1 | AF92: 397 | AG92: 384 | AH92: -13 | AI92: 115 | AJ92: 0.114 | AK92: 0.129 | AL92: 125 | AM92: 5.09 | AN92: 0 | AO92: 0 | AP92: 0 | AQ92: 0 | AR92: 0 | AS92: 0.658 | AT92: 0.719 | AU92: 23 | AV92: 2 | AW92: 3.61 | AX92: 17 | AY92: 14.42 | AZ92: 15.977 | BA92: 15.199 | BB92: 12.933 | BC92: 0.587 | BD92: 0.651 | BE92: 0.619 | BF92: 13.2 | BG92: 0.538 | BH92: 0.977 | BI92: 42.47 | BJ92: 14.086 | BK92: 0.574 | BL92: -3.199 | BM92: -1.22 | BN92: -1.2 | BO92: -1.557 | BP92: 63 | BQ92: 32 | BR92: 20 | BS92: 88 | BT92: 3.584 | BU92: 4 | BV92: 5 | BW92: 1.32 | BX92: 1.25 | BY92: 1.285 | BZ92: 0.052 | CA92: 16.484 | CB92: 0.671 | CC92: 9 | CD92: 2 | CE92: 9 | CF92: 5 | CG92: 2 | CI92: 15.171 | CJ92: 2.394 | CK92: 58 | CL92: 57 | CM92: 10 | CN92: 5 | CO92: 6 | CP92: 46 | CQ92: 6 | CR92: 110 | CS92: 67 | CT92: 0.5 | CV92: 1 | CW92: 31.77 | CX92: 1.294 | CY92: 0 | DB92: 0 | DE92: 6.68 | DF92: 2 | DG92: 0 | DH92: 21 | DI92: 19 | DJ92: 1 | DL92: 14 | DM92: 41 | DN92: 18 | DO92: 6.5 | DP92: 132.34 | DQ92: 66.17 | DR92: 132.34 | DS92: 0 | DT92: 2422 | DU92: 63.75 | DV92: flat | DW92: 37.26 | DX92: 36.45 | DY92: 34.44 | DZ92: -2.82 | EA92: 1590 | EB92: 18.06 | EC92: 2.67 | ED92: 120 | EE92: 3317 | EF92: TRUE | EG92: 99.5 | EH92: 31.6 | EI92: 40 | EJ92: 35.1 | EK92: 25.1 | EL92: 245.6 | EM92: 145.4 | EN92: 1720.1 | EO92: 134.1 | EP92: 19.4
A93: Igor Jesus | B93: NFO | C93: FWD | D93: FWD | E93: 6 | F93: TRUE | G93: TRUE | H93: 25.5 | I93: a | L93: p482973 | M93: 491 | N93: 3 | Q93: 2293 | R93: 37 | S93: 28 | T93: 25.478 | U93: 62 | V93: 114 | W93: 4.474 | X93: 6 | Y93: 6 | Z93: 4 | AA93: 9 | AB93: 37 | AC93: 13 | AD93: 13 | AE93: 0 | AF93: 407 | AG93: 398 | AH93: -9 | AI93: 114 | AJ93: 0.114 | AK93: 0.129 | AL93: 123 | AM93: 4.828 | AN93: 0 | AO93: 0 | AP93: 0 | AQ93: 0 | AR93: 0 | AS93: 0.737 | AT93: 0.649 | AU93: 27 | AV93: 1 | AW93: 2.97 | AX93: 14 | AY93: 6.48 | AZ93: 7.199 | BA93: 6.84 | BB93: 6.438 | BC93: 0.254 | BD93: 0.283 | BE93: 0.268 | BF93: 5 | BG93: 0.196 | BH93: 0.898 | BI93: 6.48 | BJ93: 5.818 | BK93: 0.228 | BL93: -0.84 | BM93: -1.48 | BN93: 1 | BO93: -0.719 | BP93: 70 | BQ93: 21 | BR93: 3 | BS93: 124 | BT93: 4.867 | BU93: 1 | BV93: 2 | BW93: 1.26 | BX93: 2.28 | BY93: 1.77 | BZ93: 0.069 | CA93: 8.61 | CB93: 0.338 | CC93: 15 | CD93: 5 | CE93: 15 | CF93: 3 | CI93: 8.535 | CJ93: 1.848 | CK93: 38 | CL93: 61 | CM93: 24 | CN93: 16 | CO93: 3 | CP93: 30 | CQ93: 5 | CR93: 155 | CS93: 81 | CT93: 0.7 | CV93: 1 | CW93: 38.77 | CX93: 1.522 | CY93: 0 | DB93: 0 | DE93: 6.53 | DF93: 2 | DG93: 0 | DH93: 42 | DI93: 40 | DL93: 11 | DM93: 43 | DN93: 11 | DO93: 5.4 | DP93: 133.48 | DQ93: 66.74 | DR93: 133.48 | DS93: 0 | DT93: 2764 | DU93: 72.75 | DV93: flat | DW93: 52.68 | DX93: 53.04 | DY93: 47.46 | DZ93: -5.21 | EA93: 1488 | EB93: 25.23 | EC93: 3.2 | ED93: 120 | EE93: 3279 | EF93: TRUE | EG93: 93.8 | EH93: 28.3 | EI93: 77 | EJ93: 32.8 | EK93: 18.5 | EL93: 152.9 | EM93: 335.3 | EN93: 1295.4 | EO93: 266.3 | EP93: 20.1
A94: Junior Kroupi | B94: BOU | C94: MID | D94: FWD | E94: 7.5 | F94: TRUE | G94: TRUE | H94: 20.2 | I94: i | J94: Foot injury - Unknown return date | K94: 0 | L94: p560262 | M94: 78 | N94: 1 | Q94: 1663 | R94: 33 | S94: 21 | T94: 18.478 | U94: 50.4 | V94: 113 | W94: 6.115 | X94: 13 | Y94: 0 | AA94: 10 | AB94: 21 | AC94: 13 | AD94: 14 | AE94: 1 | AF94: 480 | AG94: 472 | AH94: -8 | AI94: 114 | AJ94: 0.115 | AK94: 0.13 | AL94: 112 | AM94: 6.061 | AN94: 0 | AO94: 0 | AP94: 0 | AQ94: 0.048 | AR94: 0 | AS94: 0.553 | AT94: 0.606 | AU94: 21 | AV94: 1 | AW94: 2.88 | AX94: 12 | AY94: 8.31 | AZ94: 8.849 | BA94: 8.58 | BB94: 7.327 | BC94: 0.45 | BD94: 0.479 | BE94: 0.464 | BF94: 9.8 | BG94: 0.53 | BH94: 1.091 | BI94: 8.31 | BJ94: 9.069 | BK94: 0.491 | BL94: 4.42 | BM94: 1.49 | BN94: 3.2 | BO94: -0.539 | BP94: 52 | BQ94: 22 | BR94: 3 | BS94: 84 | BT94: 4.546 | BU94: 2 | BV94: 1 | BW94: 1.51 | BX94: 1.816 | BY94: 1.663 | BZ94: 0.09 | CA94: 10.242 | CB94: 0.554 | CC94: 22 | CD94: 3 | CE94: 22 | CF94: 1 | CG94: 4 | CH94: 1 | CI94: 11.657 | CJ94: 5.083 | CK94: 42 | CL94: 61 | CM94: 9 | CN94: 6 | CO94: 9 | CP94: 33 | CR94: 44 | CS94: 8 | CT94: 1.1 | CV94: 1 | CW94: 25.91 | CX94: 1.402 | CY94: 0 | DB94: 0 | DE94: 6.93 | DF94: 5 | DG94: 0 | DH94: 27 | DI94: 12 | DL94: 15 | DM94: 20 | DN94: 6 | DO94: 2.6 | DP94: 115.47 | DQ94: 42.34 | DR94: 84.68 | DS94: 30.79 | DT94: 2594 | DU94: 68.25 | DV94: ramp-up (injury / late WC return) | DW94: 61.24 | DX94: 54.83 | DY94: 65.33 | DZ94: 4.09 | EA94: 240 | EB94: 31.57 | EC94: 5 | ED94: 120 | EE94: 403 | EF94: TRUE | EG94: 75.6 | EH94: 89.1 | EI94: 21 | EJ94: 32 | EK94: 19.8 | EL94: 75.6 | EM94: 193.8 | EN94: 1000.1 | EO94: 162.4 | EP94: 14.7
A95: Sepp van den Berg | B95: BRE | C95: DEF | D95: DEF | E95: 5 | F95: TRUE | G95: TRUE | H95: 24.7 | I95: a | L95: p444765 | M95: 85 | Q95: 2761 | R95: 32 | S95: 30 | T95: 30.678 | U95: 86.3 | V95: 113 | W95: 3.683 | X95: 0 | Y95: 3 | Z95: 2 | AA95: 8 | AB95: 41 | AC95: 3 | AD95: 1 | AE95: -2 | AF95: 435 | AG95: 391 | AH95: -44 | AI95: 111 | AJ95: 0.027 | AK95: 0.027 | AL95: 272 | AM95: 8.866 | AN95: 12 | AO95: 24 | AP95: 0.4 | AQ95: 0.4 | AR95: 0.233 | AS95: 0.789 | AT95: 0.938 | AU95: 12 | AV95: 0 | AW95: 2.48 | AX95: 8 | AY95: 3.36 | AZ95: 3.333 | BA95: 3.346 | BB95: 3.333 | BC95: 0.11 | BD95: 0.109 | BE95: 0.109 | BF95: 2 | BG95: 0.065 | BH95: 0.796 | BI95: 5.45 | BJ95: 2.673 | BK95: 0.087 | BL95: -3.346 | BM95: -1.36 | BN95: -2 | BO95: 0.027 | BP95: 23 | BQ95: 7 | BR95: 4 | BS95: 55 | BT95: 1.793 | BW95: 1.45 | BX95: 2.197 | BY95: 1.824 | BZ95: 0.059 | CA95: 5.17 | CB95: 0.169 | CC95: 7 | CD95: 5 | CE95: 7 | CG95: 1 | CH95: 0 | CI95: 8.736 | CJ95: 6.425 | CK95: 249 | CL95: 109 | CM95: 23 | CN95: 10 | CO95: 29 | CP95: 195 | CQ95: 23 | CR95: 175 | CS95: 140 | CT95: 0 | CU95: 2 | CV95: 2 | CW95: 41.59 | CX95: 1.356 | CY95: 0 | DB95: 0 | DE95: 6.86 | DF95: 2 | DG95: 0 | DH95: 15 | DI95: 11 | DK95: 0 | DL95: 1 | DM95: 4 | DO95: 0.7 | DP95: 107.02 | DQ95: 45.04 | DR95: 90.08 | DS95: 16.94 | DT95: 2947 | DU95: 77.55 | DV95: ramp-up (injury / late WC return) | DW95: 100.5 | DX95: 105.2 | DY95: 99.87 | DZ95: -0.63 | EA95: 349 | EB95: 14.02 | EC95: 5.87 | ED95: 120 | EE95: 542 | EF95: TRUE | EG95: 13.6 | EH95: 18.4 | EI95: 237 | EJ95: 120 | EK95: 50.2 | EL95: 394.4 | EM95: 825.1 | EN95: 1514.1 | EO95: 534 | EP95: 24.4
A96: Michael Kayode | B96: BRE | C96: DEF | D96: DEF | E96: 4.5 | F96: TRUE | G96: TRUE | H96: 22.1 | I96: a | L96: p607464 | M96: 88 | Q96: 3258 | R96: 37 | S96: 37 | T96: 36.2 | U96: 88.1 | V96: 113 | W96: 3.122 | X96: 1 | Y96: 2 | Z96: 1 | AA96: 10 | AB96: 49 | AC96: 9 | AD96: 9 | AE96: 0 | AF96: 494 | AG96: 464 | AH96: -30 | AI96: 113 | AJ96: 0.08 | AK96: 0.087 | AL96: 219 | AM96: 6.05 | AN96: 3 | AO96: 6 | AP96: 0.081 | AQ96: 0.081 | AR96: 0.027 | AS96: 0.974 | AT96: 1 | AU96: 22 | AV96: 1 | AW96: 2.82 | AX96: 10 | AY96: 1.28 | AZ96: 1.169 | BA96: 1.225 | BB96: 1.169 | BC96: 0.035 | BD96: 0.032 | BE96: 0.034 | BF96: 1.4 | BG96: 0.039 | BH96: 0.993 | BI96: 1.47 | BJ96: 1.271 | BK96: 0.035 | BL96: -0.225 | BM96: 0.12 | BN96: -0.4 | BO96: 0.111 | BP96: 9 | BQ96: 3 | BR96: 1 | BS96: 35 | BT96: 0.967 | BV96: 1 | BW96: 2.89 | BX96: 3.185 | BY96: 3.037 | BZ96: 0.084 | CA96: 4.262 | CB96: 0.118 | CC96: 33 | CD96: 4 | CE96: 34 | CF96: 14 | CG96: 1 | CI96: 13.046 | CJ96: 9.569 | CK96: 151 | CL96: 163 | CM96: 68 | CN96: 45 | CO96: 38 | CP96: 99 | CQ96: 15 | CR96: 213 | CS96: 41 | CT96: 0.1 | CU96: 1 | CV96: 3 | CW96: 52.65 | CX96: 1.454 | CY96: 0 | DB96: 0 | DE96: 7.01 | DF96: 8 | DG96: 0 | DH96: 26 | DI96: 50 | DK96: 2 | DL96: 55 | DM96: 31 | DN96: 1 | DO96: 3.7 | DP96: 120.92 | DQ96: 60.64 | DR96: 121.28 | DS96: -0.36 | DT96: 3192 | DU96: 84 | DV96: flat | DW96: 94.27 | DX96: 95.49 | DY96: 94.02 | DZ96: -0.25 | EA96: 384 | EB96: 17.87 | EC96: 19.2 | ED96: 120 | EE96: 659 | EF96: TRUE | EG96: 14.8 | EH96: 8.7 | EI96: 396 | EJ96: 362 | EK96: 93.1 | EL96: 95.8 | EM96: 2660.6 | EN96: 1072.6 | EO96: 764.4 | EP96: 28.8
A97: Luke Shaw | B97: MUN | C97: DEF | D97: DEF | E97: 4.5 | F97: TRUE | G97: TRUE | H97: 31.1 | I97: a | L97: p106760 | M97: 423 | O97: 3 | Q97: 3220 | R97: 38 | S97: 38 | T97: 35.778 | U97: 84.7 | V97: 113 | W97: 3.158 | X97: 1 | Y97: 1 | Z97: 1 | AA97: 10 | AB97: 45 | AC97: 3 | AD97: 2 | AE97: -1 | AF97: 449 | AG97: 423 | AH97: -26 | AI97: 112 | AJ97: 0.027 | AK97: 0.027 | AL97: 224 | AM97: 6.261 | AN97: 5 | AO97: 10 | AP97: 0.132 | AQ97: 0.132 | AR97: 0.053 | AS97: 1 | AT97: 0.974 | AU97: 24 | AV97: 1 | AW97: 2.56 | AX97: 11 | AY97: 0.72 | AZ97: 0.599 | BA97: 0.659 | BB97: 0.599 | BC97: 0.02 | BD97: 0.017 | BE97: 0.018 | BF97: 0.8 | BG97: 0.022 | BH97: 1.042 | BI97: 1.89 | BJ97: 0.75 | BK97: 0.021 | BL97: 0.341 | BM97: 0.08 | BN97: 0.2 | BO97: 0.121 | BP97: 10 | BQ97: 3 | BS97: 29 | BT97: 0.811 | BW97: 1.98 | BX97: 1.494 | BY97: 1.737 | BZ97: 0.049 | CA97: 2.396 | CB97: 0.067 | CC97: 15 | CD97: 1 | CE97: 16 | CF97: 9 | CG97: 2 | CH97: 11 | CI97: 11.457 | CJ97: 10.609 | CK97: 149 | CL97: 105 | CM97: 75 | CN97: 45 | CO97: 46 | CP97: 95 | CQ97: 9 | CR97: 168 | CS97: 64 | CT97: 0.1 | CV97: 2 | CW97: 44.9 | CX97: 1.255 | CY97: 0 | DB97: 0 | DE97: 6.95 | DF97: 9 | DG97: 0 | DH97: 49 | DI97: 20 | DL97: 10 | DM97: 6 | DO97: 24.2 | DP97: 120.72 | DQ97: 60.36 | DR97: 120.72 | DS97: 0 | DT97: 2992 | DU97: 78.75 | DV97: flat | DW97: 88.7 | DX97: 90.31 | DY97: 89.18 | DZ97: 0.48 | EA97: 802 | EB97: 21.51 | EC97: 6.67 | ED97: 120 | EE97: 1541 | EF97: TRUE | EG97: 34.6 | EH97: 8.7 | EI97: 397 | EJ97: 322 | EK97: 111 | EL97: 201.2 | EM97: 4883 | EN97: 1854 | EO97: 1343.8 | EP97: 28.5
A98: Rúben Dias | B98: MCI | C98: DEF | D98: DEF | E98: 5.5 | F98: TRUE | G98: TRUE | H98: 29.3 | I98: a | L98: p171314 | M98: 390 | Q98: 2139 | R98: 26 | S98: 24 | T98: 23.767 | U98: 82.3 | V98: 113 | W98: 4.755 | X98: 2 | Y98: 0 | AA98: 12 | AB98: 22 | AC98: 4 | AD98: 3 | AE98: -1 | AF98: 453 | AG98: 426 | AH98: -27 | AI98: 112 | AJ98: 0.035 | AK98: 0.037 | AL98: 167 | AM98: 7.027 | AN98: 5 | AO98: 10 | AP98: 0.208 | AQ98: 0.208 | AR98: 0.125 | AS98: 0.632 | AT98: 0.885 | AU98: 11 | AV98: 1 | AW98: 3.51 | AX98: 14 | AY98: 0.57 | AZ98: 0.437 | BA98: 0.504 | BB98: 0.437 | BC98: 0.024 | BD98: 0.018 | BE98: 0.021 | BF98: 0.9 | BG98: 0.038 | BH98: 0.887 | BI98: 4.85 | BJ98: 0.506 | BK98: 0.021 | BL98: 1.496 | BM98: 0.33 | BN98: 1.1 | BO98: 0.133 | BP98: 10 | BQ98: 4 | BR98: 1 | BS98: 8 | BT98: 0.337 | BW98: 0.65 | BX98: 0.423 | BY98: 0.536 | BZ98: 0.023 | CA98: 1.04 | CB98: 0.044 | CC98: 7 | CE98: 7 | CF98: 3 | CI98: 14.687 | CJ98: 14.249 | CK98: 154 | CL98: 74 | CM98: 13 | CN98: 6 | CO98: 23 | CP98: 117 | CQ98: 17 | CR98: 82 | CS98: 58 | CT98: 0.1 | CV98: 2 | CW98: 26.07 | CX98: 1.097 | CY98: 0 | DB98: 0 | DE98: 7.18 | DF98: 3 | DG98: 0 | DH98: 15 | DI98: 9 | DL98: 3 | DM98: 3 | DO98: 1.6 | DP98: 65.71 | DQ98: 33.31 | DR98: 66.62 | DS98: -0.91 | DT98: 1569 | DU98: 41.28 | DV98: flat | DW98: 68.51 | DX98: 70.26 | DY98: 66.29 | DZ98: -2.22 | EA98: 1464 | EB98: 20.58 | EC98: 11 | ED98: 120 | EE98: 2588 | EF98: TRUE | EG98: 95.3 | EH98: 44.3 | EI98: 127 | EJ98: 213.9 | EK98: 267.4 | EL98: 305.6 | EM98: 4248 | EN98: 3988.6 | EO98: 2057.1 | EP98: 18.9
A99: Robert Sánchez | B99: CHE | C99: GKP | D99: GKP | E99: 5 | F99: TRUE | G99: TRUE | H99: 28.8 | I99: a | L99: p215059 | M99: 140 | Q99: 3040 | R99: 35 | S99: 35 | T99: 33.778 | U99: 86.9 | V99: 113 | W99: 3.345 | X99: 0 | Y99: 1 | Z99: 1 | AA99: 9 | AB99: 49 | AC99: 7 | AD99: 8 | AE99: 1 | AF99: 509 | AG99: 502 | AH99: -7 | AI99: 114 | AJ99: 0.062 | AK99: 0.066 | AL99: 0 | AM99: 0 | AN99: 0 | AO99: 0 | AP99: 0 | AQ99: 0 | AR99: 0 | AS99: 0.921 | AT99: 0.971 | AU99: 20 | AV99: 2 | AW99: 2.78 | AX99: 11 | AY99: 0 | AZ99: 0 | BA99: 0 | BB99: 0 | BC99: 0 | BD99: 0 | BE99: 0 | BH99: 1 | BI99: 0 | BJ99: 0 | BK99: 0 | BL99: 0 | BO99: 0 | BW99: 0.04 | BX99: 0.885 | BY99: 0.462 | BZ99: 0.014 | CA99: 0.462 | CB99: 0.014 | CC99: 5 | CD99: 2 | CE99: 5 | CH99: 0 | CI99: 10.155 | CJ99: 9.27 | CK99: 27 | CL99: 302 | CM99: 2 | CN99: 0 | CO99: 1 | CP99: 26 | CR99: 26 | CS99: 14 | CU99: 1 | CV99: 3 | CW99: 48.64 | CX99: 1.44 | CY99: 98 | CZ99: 67.6 | DA99: 1.7 | DB99: 0 | DC99: 42 | DD99: 7 | DE99: 7.07 | DF99: 3 | DG99: 1 | DH99: 2 | DI99: 14 | DM99: 1 | DO99: 2.1 | DP99: 123.9 | DQ99: 61.95 | DR99: 123.9 | DS99: 0 | DT99: 3181 | DU99: 83.7 | DV99: flat | DW99: 93.31 | DX99: 98.09 | DY99: 90.65 | DZ99: -2.66 | EA99: 1399 | EB99: 23.51 | EC99: 4.57 | ED99: 120 | EE99: 2553 | EF99: TRUE | EG99: 95.9 | EH99: 45.4 | EI99: 238 | EL99: 608 | EN99: 6574 | EO99: 6574 | EP99: 26.9
A100: Mikkel Damsgaard | B100: BRE | C100: MID | D100: MID | E100: 5.5 | F100: TRUE | G100: TRUE | H100: 26.1 | I100: a | L100: p440089 | M100: 96 | O100: 2 | P100: 3 | Q100: 2046 | R100: 33 | S100: 24 | T100: 22.733 | U100: 62 | V100: 113 | W100: 4.971 | X100: 4 | Y100: 4 | Z100: 4 | AA100: 5 | AB100: 32 | AC100: 9 | AD100: 9 | AE100: 0 | AF100: 467 | AG100: 456 | AH100: -11 | AI100: 113 | AJ100: 0.08 | AK100: 0.087 | AL100: 241 | AM100: 10.601 | AN100: 6 | AO100: 12 | AP100: 0.25 | AQ100: 0.417 | AR100: 0.25 | AS100: 0.632 | AT100: 0.667 | AU100: 19 | AV100: 2 | AW100: 3.43 | AX100: 18 | AY100: 2.61 | AZ100: 2.974 | BA100: 2.792 | BB100: 2.974 | BC100: 0.115 | BD100: 0.131 | BE100: 0.123 | BF100: 3.1 | BG100: 0.136 | BH100: 1.001 | BI100: 8.59 | BJ100: 2.612 | BK100: 0.115 | BL100: 1.208 | BM100: 0.49 | BN100: 0.9 | BO100: -0.364 | BP100: 29 | BQ100: 11 | BR100: 3 | BS100: 80 | BT100: 3.519 | BV100: 1 | BW100: 5.43 | BX100: 6.469 | BY100: 5.949 | BZ100: 0.262 | CA100: 8.742 | CB100: 0.385 | CC100: 42 | CD100: 12 | CE100: 42 | CF100: 28 | CG100: 7 | CH100: 43 | CI100: 12.347 | CJ100: 6.473 | CK100: 45 | CL100: 139 | CM100: 57 | CN100: 35 | CO100: 25 | CP100: 16 | CQ100: 4 | CR100: 116 | CS100: 19 | CT100: 1.1 | CU100: 1 | CV100: 1 | CW100: 31.55 | CX100: 1.388 | CY100: 0 | DB100: 0 | DE100: 6.99 | DF100: 0 | DG100: 0 | DH100: 19 | DI100: 23 | DL100: 18 | DM100: 33 | DN100: 4 | DO100: 0.6 | DP100: 89.93 | DQ100: 44.97 | DR100: 89.94 | DS100: -0.01 | DT100: 1915 | DU100: 50.4 | DV100: flat | DW100: 85.42 | DX100: 86.23 | DY100: 84.55 | DZ100: -0.87 | EA100: 115 | EB100: 19.23 | EC100: 16 | ED100: 120 | EE100: 179 | EF100: TRUE | EG100: 4 | EH100: 9.1 | EI100: 126 | EJ100: 70.6 | EK100: 25.6 | EL100: 48.7 | EM100: 732.8 | EN100: 343.9 | EO100: 234.1 | EP100: 18.1
...

Sheet xPts model
A1: Player | B1: Team 26/27 | C1: Club 25/26 | D1: Moved club | E1: Pos | F1: Pos 25/26 | G1: Draftable | H1: Price | I1: Status | J1: News | K1: Mins 25/26 | L1: Pts 25/26 | M1: xMins Solio | N1: xMins Solio adjusted | O1: Research delta | P1: Research confidence | Q1: xMins pattern | R1: xMins 26/27 | S1: xMins source | T1: Research reason | U1: Mins per start | V1: Mins/start starts | W1: Matches | X1: P(CS) | Y1: xG/90 | Z1: xG basis | AA1: Non-pen share | AB1: Placement ratio | AC1: Placement sample xG | AD1: xA/90 | AE1: DefCon actions/90 | AF1: DefCon hit % | AG1: Bonus/90 | AH1: App pts 25/26 | AI1: Saves/match | AJ1: Goals against/match | AK1: Card rate/90 | AL1: Pens/season | AM1: Pen save pts | AN1: xG pts/90 | AO1: xA pts/90 | AP1: CS pts/90 | AQ1: Bonus pts/90 | AR1: Save pts/90 | AS1: GC pts/90 | AT1: Cards pts/90 | AU1: Rate pts/90 | AV1: App pts season | AW1: DC pts season | AX1: Pen pts season | AY1: xPts season | AZ1: xPts/90 | BA1: VORP | BB1: VORP per £m | BC1: _pool GKP | BD1: _pool DEF | BE1: _pool MID | BF1: _pool FWD | BG1: _app 60+ | BH1: _dc pts | BI1: _cs pts | BJ1: _goal pts
A2: Erling Haaland | B2: MCI | C2: MCI | D2: FALSE | E2: FWD | F2: FWD | G2: TRUE | H2: 15.5 | I2: a | K2: 2953 | L2: 239 | M2: 3204 | N2: 3000 | O2: -204 | P2: medium | Q2: flat | R2: 3000 | S2: research | T2: Not a doubt about his place — a doubt about the first month. He played no part in pre-season after a deep World Cup run, only returned to training in the week of the Community Shield, and was expected to start that match on the bench. 3,204 would also be a career high; his best in a City shirt is 2,953 last season. Trimming to roughly last season's level rather than above it. | U2: 84.6 | V2: 34 | W2: =IF(N(U2)<=0,0,MIN(Assumptions!$B$15,N(R2)/N(U2))) | X2: 0.371 | Y2: 0.6655 | Z2: adjusted xGOT | AA2: 0.894 | AB2: 0.958 | AC2: 105.5 | AD2: 0.1246 | AE2: 3.488 | AF2: 0.0001611404 | AG2: 1.3105 | AH2: 68 | AI2: 1.9737 | AJ2: 1.0365 | AK2: -0.090825412 | AL2: 6.0260078 | AM2: 0 | AN2: 2.662 | AO2: 0.493416 | AP2: =N(X2)*N(BI2) | AQ2: 1.3105 | AR2: 0 | AS2: 0 | AT2: -0.090825412 | AU2: =SUM(AN2:AT2) | AV2: =IF(OR(N(W2)<=0,N(BG2)=0),0,N(W2)*IF(N(R2)/N(W2)>=60,N(BG2),1)) | AW2: =N(W2)*N(AF2)*N(BH2) | AX2: =N(AL2)*(Assumptions!$B$13*N(BJ2)-(1-Assumptions!$B$13)*Assumptions!$B$14)+N(AM2) | AY2: =N(AU2)*N(R2)/90+N(AV2)+N(AW2)+N(AX2) | AZ2: =IF(N(R2)<=0,0,(N(AY2)-N(AX2))*90/N(R2)) | BA2: =IFERROR(AY2-VLOOKUP($E2,Assumptions!$A$40:$C$43,3,FALSE),"") | BB2: =IFERROR(BA2/H2,"") | BC2: =IF(AND($G2=TRUE,$E2="GKP"),AY2,"") | BD2: =IF(AND($G2=TRUE,$E2="DEF"),AY2,"") | BE2: =IF(AND($G2=TRUE,$E2="MID"),AY2,"") | BF2: =IF(AND($G2=TRUE,$E2="FWD"),AY2,"") | BG2: 2 | BH2: 2 | BI2: 0 | BJ2: 4
A3: Bruno Fernandes | B3: MUN | C3: MUN | D3: FALSE | E3: MID | F3: MID | G3: TRUE | H3: 12 | I3: a | K3: 3065 | L3: 235 | M3: 3342 | N3: 3342 | O3: 0 | Q3: flat | R3: 3342 | S3: Solio | U3: 85.9 | V3: 35 | W3: =IF(N(U3)<=0,0,MIN(Assumptions!$B$15,N(R3)/N(U3))) | X3: 0.334 | Y3: 0.1866 | Z3: adjusted xGOT | AA3: 0.617 | AB3: 0.954 | AC3: 39.8 | AD3: 0.441 | AE3: 8.456 | AF3: 0.11710146 | AG3: 1.2626 | AH3: 69 | AI3: 2.2165 | AJ3: 1.1467 | AK3: -0.17837551 | AL3: 5.8643532 | AM3: 0 | AN3: 0.933 | AO3: 1.74636 | AP3: =N(X3)*N(BI3) | AQ3: 1.2626 | AR3: 0 | AS3: 0 | AT3: -0.17837551 | AU3: =SUM(AN3:AT3) | AV3: =IF(OR(N(W3)<=0,N(BG3)=0),0,N(W3)*IF(N(R3)/N(W3)>=60,N(BG3),1)) | AW3: =N(W3)*N(AF3)*N(BH3) | AX3: =N(AL3)*(Assumptions!$B$13*N(BJ3)-(1-Assumptions!$B$13)*Assumptions!$B$14)+N(AM3) | AY3: =N(AU3)*N(R3)/90+N(AV3)+N(AW3)+N(AX3) | AZ3: =IF(N(R3)<=0,0,(N(AY3)-N(AX3))*90/N(R3)) | BA3: =IFERROR(AY3-VLOOKUP($E3,Assumptions!$A$40:$C$43,3,FALSE),"") | BB3: =IFERROR(BA3/H3,"") | BC3: =IF(AND($G3=TRUE,$E3="GKP"),AY3,"") | BD3: =IF(AND($G3=TRUE,$E3="DEF"),AY3,"") | BE3: =IF(AND($G3=TRUE,$E3="MID"),AY3,"") | BF3: =IF(AND($G3=TRUE,$E3="FWD"),AY3,"") | BG3: 2 | BH3: 2 | BI3: 1 | BJ3: 5
A4: Gabriel Magalhães | B4: ARS | C4: ARS | D4: FALSE | E4: DEF | F4: DEF | G4: TRUE | H4: 8 | I4: a | K4: 2750 | L4: 209 | M4: 3283 | N4: 3283 | O4: 0 | Q4: flat | R4: 3283 | S4: Solio | U4: 88.5 | V4: 30 | W4: =IF(N(U4)<=0,0,MIN(Assumptions!$B$15,N(R4)/N(U4))) | X4: 0.391 | Y4: 0.0785 | Z4: adjusted xGOT | AA4: 1 | AB4: 0.816 | AC4: 15.2 | AD4: 0.0732 | AE4: 8.779 | AF4: 0.36431888 | AG4: 0.7855 | AH4: 62 | AI4: 2.067 | AJ4: 0.9838 | AK4: -0.16538127 | AL4: 0 | AM4: 0 | AN4: 0.471 | AO4: 0.289872 | AP4: =N(X4)*N(BI4) | AQ4: 0.7855 | AR4: 0 | AS4: -0.27684799 | AT4: -0.16538127 | AU4: =SUM(AN4:AT4) | AV4: =IF(OR(N(W4)<=0,N(BG4)=0),0,N(W4)*IF(N(R4)/N(W4)>=60,N(BG4),1)) | AW4: =N(W4)*N(AF4)*N(BH4) | AX4: =N(AL4)*(Assumptions!$B$13*N(BJ4)-(1-Assumptions!$B$13)*Assumptions!$B$14)+N(AM4) | AY4: =N(AU4)*N(R4)/90+N(AV4)+N(AW4)+N(AX4) | AZ4: =IF(N(R4)<=0,0,(N(AY4)-N(AX4))*90/N(R4)) | BA4: =IFERROR(AY4-VLOOKUP($E4,Assumptions!$A$40:$C$43,3,FALSE),"") | BB4: =IFERROR(BA4/H4,"") | BC4: =IF(AND($G4=TRUE,$E4="GKP"),AY4,"") | BD4: =IF(AND($G4=TRUE,$E4="DEF"),AY4,"") | BE4: =IF(AND($G4=TRUE,$E4="MID"),AY4,"") | BF4: =IF(AND($G4=TRUE,$E4="FWD"),AY4,"") | BG4: 2 | BH4: 2 | BI4: 4 | BJ4: 6
A5: Antoine Semenyo | B5: MCI | C5: MCI | D5: FALSE | E5: MID | F5: MID | G5: TRUE | H5: 8.5 | I5: a | K5: 3200 | L5: 202 | M5: 3106 | N5: 2900 | O5: -206 | P5: low | Q5: flat | R5: 2900 | S5: research | T5: Lowest-confidence delta in this file, and included partly to keep the budget honest. 3,106 minutes is 34.5 full matches, which would make him the most-used City winger of the Guardiola-to-Maresca era. His 3,200 minutes last season were largely banked at Bournemouth before January, where he was genuinely nailed; at City he is in a rotation with Doku, Cherki, Savinho, Foden and Monga that Opta lists as one of the club's deepest areas. Small trim only — he was outstanding in pre-season and nothing suggests he loses his place. | U5: 85.1 | V5: 37 | W5: =IF(N(U5)<=0,0,MIN(Assumptions!$B$15,N(R5)/N(U5))) | X5: 0.371 | Y5: 0.3139 | Z5: adjusted xGOT | AA5: 0.881 | AB5: 1.141 | AC5: 25.7 | AD5: 0.102 | AE5: 6.994 | AF5: 0.03775901 | AG5: 0.5344 | AH5: 72 | AI5: 1.9737 | AJ5: 1.0365 | AK5: -0.23541492 | AL5: 0.3312989 | AM5: 0 | AN5: 1.5695 | AO5: 0.40392 | AP5: =N(X5)*N(BI5) | AQ5: 0.5344 | AR5: 0 | AS5: 0 | AT5: -0.23541492 | AU5: =SUM(AN5:AT5) | AV5: =IF(OR(N(W5)<=0,N(BG5)=0),0,N(W5)*IF(N(R5)/N(W5)>=60,N(BG5),1)) | AW5: =N(W5)*N(AF5)*N(BH5) | AX5: =N(AL5)*(Assumptions!$B$13*N(BJ5)-(1-Assumptions!$B$13)*Assumptions!$B$14)+N(AM5) | AY5: =N(AU5)*N(R5)/90+N(AV5)+N(AW5)+N(AX5) | AZ5: =IF(N(R5)<=0,0,(N(AY5)-N(AX5))*90/N(R5)) | BA5: =IFERROR(AY5-VLOOKUP($E5,Assumptions!$A$40:$C$43,3,FALSE),"") | BB5: =IFERROR(BA5/H5,"") | BC5: =IF(AND($G5=TRUE,$E5="GKP"),AY5,"") | BD5: =IF(AND($G5=TRUE,$E5="DEF"),AY5,"") | BE5: =IF(AND($G5=TRUE,$E5="MID"),AY5,"") | BF5: =IF(AND($G5=TRUE,$E5="FWD"),AY5,"") | BG5: 2 | BH5: 2 | BI5: 1 | BJ5: 5
A6: Morgan Gibbs-White | B6: NFO | C6: NFO | D6: FALSE | E6: MID | F6: MID | G6: TRUE | H6: 8 | I6: a | K6: 3101 | L6: 188 | M6: 3301 | N6: 3150 | O6: -151 | P6: medium | Q6: flat | R6: 3150 | S6: research | T6: Staying at Forest and central to Glasner's plans, so the headline number is broadly right. Trimmed because Solio projects 200 minutes above his own 2025-26 total of 3,101, and an attacking midfielder in a two-ten system is the profile most often substituted late. | U6: 85.3 | V6: 35 | W6: =IF(N(U6)<=0,0,MIN(Assumptions!$B$15,N(R6)/N(U6))) | X6: 0.224 | Y6: 0.2899 | Z6: adjusted xGOT | AA6: 0.935 | AB6: 0.989 | AC6: 30.5 | AD6: 0.1076 | AE6: 5.809 | AF6: 0.011068828 | AG6: 0.5224 | AH6: 72 | AI6: 3.1134 | AJ6: 1.5588 | AK6: -0.17519603 | AL6: 3.5888964 | AM6: 0 | AN6: 1.4495 | AO6: 0.426096 | AP6: =N(X6)*N(BI6) | AQ6: 0.5224 | AR6: 0 | AS6: 0 | AT6: -0.17519603 | AU6: =SUM(AN6:AT6) | AV6: =IF(OR(N(W6)<=0,N(BG6)=0),0,N(W6)*IF(N(R6)/N(W6)>=60,N(BG6),1)) | AW6: =N(W6)*N(AF6)*N(BH6) | AX6: =N(AL6)*(Assumptions!$B$13*N(BJ6)-(1-Assumptions!$B$13)*Assumptions!$B$14)+N(AM6) | AY6: =N(AU6)*N(R6)/90+N(AV6)+N(AW6)+N(AX6) | AZ6: =IF(N(R6)<=0,0,(N(AY6)-N(AX6))*90/N(R6)) | BA6: =IFERROR(AY6-VLOOKUP($E6,Assumptions!$A$40:$C$43,3,FALSE),"") | BB6: =IFERROR(BA6/H6,"") | BC6: =IF(AND($G6=TRUE,$E6="GKP"),AY6,"") | BD6: =IF(AND($G6=TRUE,$E6="DEF"),AY6,"") | BE6: =IF(AND($G6=TRUE,$E6="MID"),AY6,"") | BF6: =IF(AND($G6=TRUE,$E6="FWD"),AY6,"") | BG6: 2 | BH6: 2 | BI6: 1 | BJ6: 5
A7: Declan Rice | B7: ARS | C7: ARS | D7: FALSE | E7: MID | F7: MID | G7: TRUE | H7: 7.5 | I7: a | K7: 3093 | L7: 184 | M7: 3106 | N7: 2950 | O7: -156 | P7: low | Q7: flat | R7: 2950 | S7: research | T7: Rice is fit and available, so no large cut is warranted - but Solio's 3106 would be his heaviest league season yet on the back of hamstring nerve pain he has been managing since December, a knee problem, and a World Cup that ran to the third-place play-off. Fantasy Football Scout's 14 August guide flags that Rice has 'only just returned to training after the World Cup' and that early minutes may be managed. A 5% trim for load management, no more. | U7: 86 | V7: 35 | W7: =IF(N(U7)<=0,0,MIN(Assumptions!$B$15,N(R7)/N(U7))) | X7: 0.391 | Y7: 0.1037 | Z7: adjusted xGOT | AA7: 1 | AB7: 1.132 | AC7: 12.6 | AD7: 0.2252 | AE7: 10.494 | AF7: 0.30636727 | AG7: 0.6984 | AH7: 71 | AI7: 2.067 | AJ7: 0.9838 | AK7: -0.15062106 | AL7: 0 | AM7: 0 | AN7: 0.5185 | AO7: 0.891792 | AP7: =N(X7)*N(BI7) | AQ7: 0.6984 | AR7: 0 | AS7: 0 | AT7: -0.15062106 | AU7: =SUM(AN7:AT7) | AV7: =IF(OR(N(W7)<=0,N(BG7)=0),0,N(W7)*IF(N(R7)/N(W7)>=60,N(BG7),1)) | AW7: =N(W7)*N(AF7)*N(BH7) | AX7: =N(AL7)*(Assumptions!$B$13*N(BJ7)-(1-Assumptions!$B$13)*Assumptions!$B$14)+N(AM7) | AY7: =N(AU7)*N(R7)/90+N(AV7)+N(AW7)+N(AX7) | AZ7: =IF(N(R7)<=0,0,(N(AY7)-N(AX7))*90/N(R7)) | BA7: =IFERROR(AY7-VLOOKUP($E7,Assumptions!$A$40:$C$43,3,FALSE),"") | BB7: =IFERROR(BA7/H7,"") | BC7: =IF(AND($G7=TRUE,$E7="GKP"),AY7,"") | BD7: =IF(AND($G7=TRUE,$E7="DEF"),AY7,"") | BE7: =IF(AND($G7=TRUE,$E7="MID"),AY7,"") | BF7: =IF(AND($G7=TRUE,$E7="FWD"),AY7,"") | BG7: 2 | BH7: 2 | BI7: 1 | BJ7: 5
A8: Igor Thiago | B8: BRE | C8: BRE | D8: FALSE | E8: FWD | F8: FWD | G8: TRUE | H8: 8 | I8: a | K8: 3282 | L8: 181 | M8: 3209 | N8: 3050 | O8: -159 | P8: low | Q8: flat | R8: 3050 | S8: research | T8: Small trim only. Brentford signed Callum Wilson on a free on 9 July, and he replaced Thiago at half-time against Rennes and registered two assists. Solio's 3209 assumes essentially no in-game rotation at centre-forward; a dedicated deputy with 95 Premier League goals makes a modest number of early substitutions and rested matches likelier. Thiago remains the undisputed starter. | U8: 85.9 | V8: 37 | W8: =IF(N(U8)<=0,0,MIN(Assumptions!$B$15,N(R8)/N(U8))) | X8: 0.228 | Y8: 0.3992 | Z8: adjusted xGOT | AA8: 0.723 | AB8: 0.978 | AC8: 20.7 | AD8: 0.0724 | AE8: 5.675 | AF8: 0.0098456511 | AG8: 0.6033 | AH8: 75 | AI8: 3.2371 | AJ8: 1.5396 | AK8: -0.19096629 | AL8: 4.1891175 | AM8: 0 | AN8: 1.5968 | AO8: 0.286704 | AP8: =N(X8)*N(BI8) | AQ8: 0.6033 | AR8: 0 | AS8: 0 | AT8: -0.19096629 | AU8: =SUM(AN8:AT8) | AV8: =IF(OR(N(W8)<=0,N(BG8)=0),0,N(W8)*IF(N(R8)/N(W8)>=60,N(BG8),1)) | AW8: =N(W8)*N(AF8)*N(BH8) | AX8: =N(AL8)*(Assumptions!$B$13*N(BJ8)-(1-Assumptions!$B$13)*Assumptions!$B$14)+N(AM8) | AY8: =N(AU8)*N(R8)/90+N(AV8)+N(AW8)+N(AX8) | AZ8: =IF(N(R8)<=0,0,(N(AY8)-N(AX8))*90/N(R8)) | BA8: =IFERROR(AY8-VLOOKUP($E8,Assumptions!$A$40:$C$43,3,FALSE),"") | BB8: =IFERROR(BA8/H8,"") | BC8: =IF(AND($G8=TRUE,$E8="GKP"),AY8,"") | BD8: =IF(AND($G8=TRUE,$E8="DEF"),AY8,"") | BE8: =IF(AND($G8=TRUE,$E8="MID"),AY8,"") | BF8: =IF(AND($G8=TRUE,$E8="FWD"),AY8,"") | BG8: 2 | BH8: 2 | BI8: 0 | BJ8: 4
A9: Elliot Anderson | B9: MCI | C9: NFO | D9: TRUE | E9: MID | F9: MID | G9: TRUE | H9: 6.5 | I9: a | K9: 3332 | L9: 180 | M9: 2096 | N9: 2700 | O9: 604 | P9: high | Q9: flat | R9: 2700 | S9: research | T9: Resolves the flagged question. The 'more likely to start on the bench' read is real but it is about one match, not the season: he had only four days' training with the squad before the Community Shield, which is why one preview made Nico Gonzalez the safer bet for that game. Everything longer-range points the other way — British-record £116m fee for an English player, reported as central to Maresca's midfield plans from the restart, Maresca himself mapping him as both a six and an eight, Reijnders sold and Rodri unavailable. Bench for one match, starter for the season. | U9: 87 | V9: 37 | W9: =IF(N(U9)<=0,0,MIN(Assumptions!$B$15,N(R9)/N(U9))) | X9: 0.371 | Y9: 0.0558 | Z9: adjusted xGOT | AA9: 0.779 | AB9: 0.902 | AC9: 7.8 | AD9: 0.1301 | AE9: 12.963 | AF9: 0.59759145 | AG9: 0.4862 | AH9: 75 | AI9: 1.9737 | AJ9: 1.0365 | AK9: -0.2595103 | AL9: 0 | AM9: 0 | AN9: 0.279 | AO9: 0.515196 | AP9: =N(X9)*N(BI9) | AQ9: 0.4862 | AR9: 0 | AS9: 0 | AT9: -0.2595103 | AU9: =SUM(AN9:AT9) | AV9: =IF(OR(N(W9)<=0,N(BG9)=0),0,N(W9)*IF(N(R9)/N(W9)>=60,N(BG9),1)) | AW9: =N(W9)*N(AF9)*N(BH9) | AX9: =N(AL9)*(Assumptions!$B$13*N(BJ9)-(1-Assumptions!$B$13)*Assumptions!$B$14)+N(AM9) | AY9: =N(AU9)*N(R9)/90+N(AV9)+N(AW9)+N(AX9) | AZ9: =IF(N(R9)<=0,0,(N(AY9)-N(AX9))*90/N(R9)) | BA9: =IFERROR(AY9-VLOOKUP($E9,Assumptions!$A$40:$C$43,3,FALSE),"") | BB9: =IFERROR(BA9/H9,"") | BC9: =IF(AND($G9=TRUE,$E9="GKP"),AY9,"") | BD9: =IF(AND($G9=TRUE,$E9="DEF"),AY9,"") | BE9: =IF(AND($G9=TRUE,$E9="MID"),AY9,"") | BF9: =IF(AND($G9=TRUE,$E9="FWD"),AY9,"") | BG9: 2 | BH9: 2 | BI9: 1 | BJ9: 5
A10: Marc Guéhi | B10: MCI | C10: MCI | D10: FALSE | E10: DEF | F10: DEF | G10: TRUE | H10: 6 | I10: a | K10: 3150 | L10: 179 | M10: 2611 | N10: 2611 | O10: 0 | Q10: flat | R10: 2611 | S10: Solio | U10: 89 | V10: 35 | W10: =IF(N(U10)<=0,0,MIN(Assumptions!$B$15,N(R10)/N(U10))) | X10: 0.371 | Y10: 0.1254 | Z10: adjusted xGOT | AA10: 1 | AB10: 1.084 | AC10: 8 | AD10: 0.0728 | AE10: 7.895 | AF10: 0.25976977 | AG10: 0.3429 | AH10: 70 | AI10: 1.9737 | AJ10: 1.0365 | AK10: -0.19455957 | AL10: 0 | AM10: 0 | AN10: 0.7524 | AO10: 0.288288 | AP10: =N(X10)*N(BI10) | AQ10: 0.3429 | AR10: 0 | AS10: -0.29970195 | AT10: -0.19455957 | AU10: =SUM(AN10:AT10) | AV10: =IF(OR(N(W10)<=0,N(BG10)=0),0,N(W10)*IF(N(R10)/N(W10)>=60,N(BG10),1)) | AW10: =N(W10)*N(AF10)*N(BH10) | AX10: =N(AL10)*(Assumptions!$B$13*N(BJ10)-(1-Assumptions!$B$13)*Assumptions!$B$14)+N(AM10) | AY10: =N(AU10)*N(R10)/90+N(AV10)+N(AW10)+N(AX10) | AZ10: =IF(N(R10)<=0,0,(N(AY10)-N(AX10))*90/N(R10)) | BA10: =IFERROR(AY10-VLOOKUP($E10,Assumptions!$A$40:$C$43,3,FALSE),"") | BB10: =IFERROR(BA10/H10,"") | BC10: =IF(AND($G10=TRUE,$E10="GKP"),AY10,"") | BD10: =IF(AND($G10=TRUE,$E10="DEF"),AY10,"") | BE10: =IF(AND($G10=TRUE,$E10="MID"),AY10,"") | BF10: =IF(AND($G10=TRUE,$E10="FWD"),AY10,"") | BG10: 2 | BH10: 2 | BI10: 4 | BJ10: 6
A11: João Pedro | B11: CHE | C11: CHE | D11: FALSE | E11: FWD | F11: FWD | G11: TRUE | H11: 7.5 | I11: a | K11: 2658 | L11: 177 | M11: 2890 | N11: 2890 | O11: 0 | Q11: flat | R11: 2890 | S11: Solio | U11: 81.1 | V11: 31 | W11: =IF(N(U11)<=0,0,MIN(Assumptions!$B$15,N(R11)/N(U11))) | X11: 0.322 | Y11: 0.5062 | Z11: adjusted xGOT | AA11: 1 | AB11: 1.003 | AC11: 35.9 | AD11: 0.1006 | AE11: 4.698 | AF11: 0.001466395 | AG11: 1.0158 | AH11: 65 | AI11: 2.4232 | AJ11: 1.1851 | AK11: -0.17161794 | AL11: 0 | AM11: 0 | AN11: 2.0248 | AO11: 0.398376 | AP11: =N(X11)*N(BI11) | AQ11: 1.0158 | AR11: 0 | AS11: 0 | AT11: -0.17161794 | AU11: =SUM(AN11:AT11) | AV11: =IF(OR(N(W11)<=0,N(BG11)=0),0,N(W11)*IF(N(R11)/N(W11)>=60,N(BG11),1)) | AW11: =N(W11)*N(AF11)*N(BH11) | AX11: =N(AL11)*(Assumptions!$B$13*N(BJ11)-(1-Assumptions!$B$13)*Assumptions!$B$14)+N(AM11) | AY11: =N(AU11)*N(R11)/90+N(AV11)+N(AW11)+N(AX11) | AZ11: =IF(N(R11)<=0,0,(N(AY11)-N(AX11))*90/N(R11)) | BA11: =IFERROR(AY11-VLOOKUP($E11,Assumptions!$A$40:$C$43,3,FALSE),"") | BB11: =IFERROR(BA11/H11,"") | BC11: =IF(AND($G11=TRUE,$E11="GKP"),AY11,"") | BD11: =IF(AND($G11=TRUE,$E11="DEF"),AY11,"") | BE11: =IF(AND($G11=TRUE,$E11="MID"),AY11,"") | BF11: =IF(AND($G11=TRUE,$E11="FWD"),AY11,"") | BG11: 2 | BH11: 2 | BI11: 0 | BJ11: 4
A12: Virgil van Dijk | B12: LIV | C12: LIV | D12: FALSE | E12: DEF | F12: DEF | G12: TRUE | H12: 6.5 | I12: a | K12: 3420 | L12: 175 | M12: 3340 | N12: 3340 | O12: 0 | Q12: flat | R12: 3340 | S12: Solio | U12: 89.1 | V12: 38 | W12: =IF(N(U12)<=0,0,MIN(Assumptions!$B$15,N(R12)/N(U12))) | X12: 0.342 | Y12: 0.0983 | Z12: adjusted xGOT | AA12: 1 | AB12: 0.991 | AC12: 11.4 | AD12: 0.0233 | AE12: 8.989 | AF12: 0.39930145 | AG12: 0.2368 | AH12: 76 | AI12: 2.409 | AJ12: 1.1228 | AK12: -0.14446275 | AL12: 0 | AM12: 0 | AN12: 0.5898 | AO12: 0.092268 | AP12: =N(X12)*N(BI12) | AQ12: 0.2368 | AR12: 0 | AS12: -0.337866 | AT12: -0.14446275 | AU12: =SUM(AN12:AT12) | AV12: =IF(OR(N(W12)<=0,N(BG12)=0),0,N(W12)*IF(N(R12)/N(W12)>=60,N(BG12),1)) | AW12: =N(W12)*N(AF12)*N(BH12) | AX12: =N(AL12)*(Assumptions!$B$13*N(BJ12)-(1-Assumptions!$B$13)*Assumptions!$B$14)+N(AM12) | AY12: =N(AU12)*N(R12)/90+N(AV12)+N(AW12)+N(AX12) | AZ12: =IF(N(R12)<=0,0,(N(AY12)-N(AX12))*90/N(R12)) | BA12: =IFERROR(AY12-VLOOKUP($E12,Assumptions!$A$40:$C$43,3,FALSE),"") | BB12: =IFERROR(BA12/H12,"") | BC12: =IF(AND($G12=TRUE,$E12="GKP"),AY12,"") | BD12: =IF(AND($G12=TRUE,$E12="DEF"),AY12,"") | BE12: =IF(AND($G12=TRUE,$E12="MID"),AY12,"") | BF12: =IF(AND($G12=TRUE,$E12="FWD"),AY12,"") | BG12: 2 | BH12: 2 | BI12: 4 | BJ12: 6
A13: Marcos Senesi | B13: TOT | C13: BOU | D13: TRUE | E13: DEF | F13: DEF | G13: TRUE | H13: 6 | I13: a | K13: 3288 | L13: 175 | M13: 1573 | N13: 1950 | O13: 377 | P13: medium | Q13: flat | R13: 1950 | S13: research | T13: Solio's 1,573 reads Senesi as a squad centre-back. He is a rotation option behind the intended van Hecke-van de Ven pairing, but he started alongside van Hecke against Hoffenheim and is in line to start the opening fixtures while van de Ven builds fitness. With Romero sold, Vuskovic and Phillips sold and Dragusin loaned out, Senesi is the third of only four senior centre-backs. | U13: 88.1 | V13: 37 | W13: =IF(N(U13)<=0,0,MIN(Assumptions!$B$15,N(R13)/N(U13))) | X13: 0.286 | Y13: 0.0335 | Z13: adjusted xGOT | AA13: 1 | AB13: 0.799 | AC13: 6 | AD13: 0.1197 | AE13: 10.789 | AF13: 0.61004383 | AG13: 0.3285 | AH13: 74 | AI13: 2.5739 | AJ13: 1.3096 | AK13: -0.29516506 | AL13: 0 | AM13: 0 | AN13: 0.201 | AO13: 0.474012 | AP13: =N(X13)*N(BI13) | AQ13: 0.3285 | AR13: 0 | AS13: -0.42301528 | AT13: -0.29516506 | AU13: =SUM(AN13:AT13) | AV13: =IF(OR(N(W13)<=0,N(BG13)=0),0,N(W13)*IF(N(R13)/N(W13)>=60,N(BG13),1)) | AW13: =N(W13)*N(AF13)*N(BH13) | AX13: =N(AL13)*(Assumptions!$B$13*N(BJ13)-(1-Assumptions!$B$13)*Assumptions!$B$14)+N(AM13) | AY13: =N(AU13)*N(R13)/90+N(AV13)+N(AW13)+N(AX13) | AZ13: =IF(N(R13)<=0,0,(N(AY13)-N(AX13))*90/N(R13)) | BA13: =IFERROR(AY13-VLOOKUP($E13,Assumptions!$A$40:$C$43,3,FALSE),"") | BB13: =IFERROR(BA13/H13,"") | BC13: =IF(AND($G13=TRUE,$E13="GKP"),AY13,"") | BD13: =IF(AND($G13=TRUE,$E13="DEF"),AY13,"") | BE13: =IF(AND($G13=TRUE,$E13="MID"),AY13,"") | BF13: =IF(AND($G13=TRUE,$E13="FWD"),AY13,"") | BG13: 2 | BH13: 2 | BI13: 4 | BJ13: 6
A14: James Tarkowski | B14: EVE | C14: EVE | D14: FALSE | E14: DEF | F14: DEF | G14: TRUE | H14: 6 | I14: a | K14: 3330 | L14: 170 | M14: 3266 | N14: 3266 | O14: 0 | Q14: flat | R14: 3266 | S14: Solio | U14: 89 | V14: 37 | W14: =IF(N(U14)<=0,0,MIN(Assumptions!$B$15,N(R14)/N(U14))) | X14: 0.231 | Y14: 0.0555 | Z14: adjusted xGOT | AA14: 1 | AB14: 0.812 | AC14: 9.4 | AD14: 0.0562 | AE14: 9.722 | AF14: 0.49294386 | AG14: 0.3243 | AH14: 74 | AI14: 3.0311 | AJ14: 1.5252 | AK14: -0.23713401 | AL14: 0 | AM14: 0 | AN14: 0.333 | AO14: 0.222552 | AP14: =N(X14)*N(BI14) | AQ14: 0.3243 | AR14: 0 | AS14: -0.524435 | AT14: -0.23713401 | AU14: =SUM(AN14:AT14) | AV14: =IF(OR(N(W14)<=0,N(BG14)=0),0,N(W14)*IF(N(R14)/N(W14)>=60,N(BG14),1)) | AW14: =N(W14)*N(AF14)*N(BH14) | AX14: =N(AL14)*(Assumptions!$B$13*N(BJ14)-(1-Assumptions!$B$13)*Assumptions!$B$14)+N(AM14) | AY14: =N(AU14)*N(R14)/90+N(AV14)+N(AW14)+N(AX14) | AZ14: =IF(N(R14)<=0,0,(N(AY14)-N(AX14))*90/N(R14)) | BA14: =IFERROR(AY14-VLOOKUP($E14,Assumptions!$A$40:$C$43,3,FALSE),"") | BB14: =IFERROR(BA14/H14,"") | BC14: =IF(AND($G14=TRUE,$E14="GKP"),AY14,"") | BD14: =IF(AND($G14=TRUE,$E14="DEF"),AY14,"") | BE14: =IF(AND($G14=TRUE,$E14="MID"),AY14,"") | BF14: =IF(AND($G14=TRUE,$E14="FWD"),AY14,"") | BG14: 2 | BH14: 2 | BI14: 4 | BJ14: 6
A15: Morgan Rogers | B15: CHE | C15: AVL | D15: TRUE | E15: MID | F15: MID | G15: TRUE | H15: 7.5 | I15: a | K15: 3280 | L15: 169 | M15: 2890 | N15: 2890 | O15: 0 | Q15: flat | R15: 2890 | S15: Solio | U15: 86.8 | V15: 37 | W15: =IF(N(U15)<=0,0,MIN(Assumptions!$B$15,N(R15)/N(U15))) | X15: 0.322 | Y15: 0.2094 | Z15: adjusted xGOT | AA15: 1 | AB15: 1.116 | AC15: 14.7 | AD15: 0.1618 | AE15: 6.719 | AF15: 0.033228251 | AG15: 0.4665 | AH15: 74 | AI15: 2.4232 | AJ15: 1.1851 | AK15: -0.24534392 | AL15: 0 | AM15: 0 | AN15: 1.047 | AO15: 0.640728 | AP15: =N(X15)*N(BI15) | AQ15: 0.4665 | AR15: 0 | AS15: 0 | AT15: -0.24534392 | AU15: =SUM(AN15:AT15) | AV15: =IF(OR(N(W15)<=0,N(BG15)=0),0,N(W15)*IF(N(R15)/N(W15)>=60,N(BG15),1)) | AW15: =N(W15)*N(AF15)*N(BH15) | AX15: =N(AL15)*(Assumptions!$B$13*N(BJ15)-(1-Assumptions!$B$13)*Assumptions!$B$14)+N(AM15) | AY15: =N(AU15)*N(R15)/90+N(AV15)+N(AW15)+N(AX15) | AZ15: =IF(N(R15)<=0,0,(N(AY15)-N(AX15))*90/N(R15)) | BA15: =IFERROR(AY15-VLOOKUP($E15,Assumptions!$A$40:$C$43,3,FALSE),"") | BB15: =IFERROR(BA15/H15,"") | BC15: =IF(AND($G15=TRUE,$E15="GKP"),AY15,"") | BD15: =IF(AND($G15=TRUE,$E15="DEF"),AY15,"") | BE15: =IF(AND($G15=TRUE,$E15="MID"),AY15,"") | BF15: =IF(AND($G15=TRUE,$E15="FWD"),AY15,"") | BG15: 2 | BH15: 2 | BI15: 1 | BJ15: 5
A16: Harry Wilson | B16: LEE | C16: FUL | D16: TRUE | E16: MID | F16: MID | G16: TRUE | H16: 6.5 | I16: a | K16: 2674 | L16: 168 | M16: 2810 | N16: 2810 | O16: 0 | Q16: flat | R16: 2810 | S16: Solio | U16: 80.7 | V16: 32 | W16: =IF(N(U16)<=0,0,MIN(Assumptions!$B$15,N(R16)/N(U16))) | X16: 0.218 | Y16: 0.2446 | Z16: adjusted xGOT | AA16: 1 | AB16: 1.236 | AC16: 15.6 | AD16: 0.1729 | AE16: 6.513 | AF16: 0.016721415 | AG16: 0.7068 | AH16: 66 | AI16: 3.0611 | AJ16: 1.5875 | AK16: -0.24461939 | AL16: 0 | AM16: 0 | AN16: 1.223 | AO16: 0.684684 | AP16: =N(X16)*N(BI16) | AQ16: 0.7068 | AR16: 0 | AS16: 0 | AT16: -0.24461939 | AU16: =SUM(AN16:AT16) | AV16: =IF(OR(N(W16)<=0,N(BG16)=0),0,N(W16)*IF(N(R16)/N(W16)>=60,N(BG16),1)) | AW16: =N(W16)*N(AF16)*N(BH16) | AX16: =N(AL16)*(Assumptions!$B$13*N(BJ16)-(1-Assumptions!$B$13)*Assumptions!$B$14)+N(AM16) | AY16: =N(AU16)*N(R16)/90+N(AV16)+N(AW16)+N(AX16) | AZ16: =IF(N(R16)<=0,0,(N(AY16)-N(AX16))*90/N(R16)) | BA16: =IFERROR(AY16-VLOOKUP($E16,Assumptions!$A$40:$C$43,3,FALSE),"") | BB16: =IFERROR(BA16/H16,"") | BC16: =IF(AND($G16=TRUE,$E16="GKP"),AY16,"") | BD16: =IF(AND($G16=TRUE,$E16="DEF"),AY16,"") | BE16: =IF(AND($G16=TRUE,$E16="MID"),AY16,"") | BF16: =IF(AND($G16=TRUE,$E16="FWD"),AY16,"") | BG16: 2 | BH16: 2 | BI16: 1 | BJ16: 5
A17: Ollie Watkins | B17: AVL | C17: AVL | D17: FALSE | E17: FWD | F17: FWD | G17: TRUE | H17: 8 | I17: a | K17: 2833 | L17: 167 | M17: 2679 | N17: 2679 | O17: 0 | Q17: flat | R17: 2679 | S17: Solio | U17: 81.2 | V17: 33 | W17: =IF(N(U17)<=0,0,MIN(Assumptions!$B$15,N(R17)/N(U17))) | X17: 0.273 | Y17: 0.5015 | Z17: adjusted xGOT | AA17: 1 | AB17: 1.025 | AC17: 63.4 | AD17: 0.0635 | AE17: 3.352 | AF17: 7.692078e-05 | AG17: 0.826 | AH17: 69 | AI17: 2.7451 | AJ17: 1.3575 | AK17: -0.13060083 | AL17: 0.76358398 | AM17: 0 | AN17: 2.006 | AO17: 0.25146 | AP17: =N(X17)*N(BI17) | AQ17: 0.826 | AR17: 0 | AS17: 0 | AT17: -0.13060083 | AU17: =SUM(AN17:AT17) | AV17: =IF(OR(N(W17)<=0,N(BG17)=0),0,N(W17)*IF(N(R17)/N(W17)>=60,N(BG17),1)) | AW17: =N(W17)*N(AF17)*N(BH17) | AX17: =N(AL17)*(Assumptions!$B$13*N(BJ17)-(1-Assumptions!$B$13)*Assumptions!$B$14)+N(AM17) | AY17: =N(AU17)*N(R17)/90+N(AV17)+N(AW17)+N(AX17) | AZ17: =IF(N(R17)<=0,0,(N(AY17)-N(AX17))*90/N(R17)) | BA17: =IFERROR(AY17-VLOOKUP($E17,Assumptions!$A$40:$C$43,3,FALSE),"") | BB17: =IFERROR(BA17/H17,"") | BC17: =IF(AND($G17=TRUE,$E17="GKP"),AY17,"") | BD17: =IF(AND($G17=TRUE,$E17="DEF"),AY17,"") | BE17: =IF(AND($G17=TRUE,$E17="MID"),AY17,"") | BF17: =IF(AND($G17=TRUE,$E17="FWD"),AY17,"") | BG17: 2 | BH17: 2 | BI17: 0 | BJ17: 4
A18: Adrien Truffert | B18: BOU | C18: BOU | D18: FALSE | E18: DEF | F18: DEF | G18: TRUE | H18: 5.5 | I18: a | K18: 3378 | L18: 165 | M18: 3266 | N18: 3266 | O18: 0 | Q18: flat | R18: 3266 | S18: Solio | U18: 88.2 | V18: 38 | W18: =IF(N(U18)<=0,0,MIN(Assumptions!$B$15,N(R18)/N(U18))) | X18: 0.23 | Y18: 0.0369 | Z18: adjusted xGOT | AA18: 1 | AB18: 1.027 | AC18: 1.4 | AD18: 0.0996 | AE18: 7.961 | AF18: 0.2591059 | AG18: 0.5062 | AH18: 76 | AI18: 3.0957 | AJ18: 1.53 | AK18: -0.16939041 | AL18: 0 | AM18: 0 | AN18: 0.2214 | AO18: 0.394416 | AP18: =N(X18)*N(BI18) | AQ18: 0.5062 | AR18: 0 | AS18: -0.52672192 | AT18: -0.16939041 | AU18: =SUM(AN18:AT18) | AV18: =IF(OR(N(W18)<=0,N(BG18)=0),0,N(W18)*IF(N(R18)/N(W18)>=60,N(BG18),1)) | AW18: =N(W18)*N(AF18)*N(BH18) | AX18: =N(AL18)*(Assumptions!$B$13*N(BJ18)-(1-Assumptions!$B$13)*Assumptions!$B$14)+N(AM18) | AY18: =N(AU18)*N(R18)/90+N(AV18)+N(AW18)+N(AX18) | AZ18: =IF(N(R18)<=0,0,(N(AY18)-N(AX18))*90/N(R18)) | BA18: =IFERROR(AY18-VLOOKUP($E18,Assumptions!$A$40:$C$43,3,FALSE),"") | BB18: =IFERROR(BA18/H18,"") | BC18: =IF(AND($G18=TRUE,$E18="GKP"),AY18,"") | BD18: =IF(AND($G18=TRUE,$E18="DEF"),AY18,"") | BE18: =IF(AND($G18=TRUE,$E18="MID"),AY18,"") | BF18: =IF(AND($G18=TRUE,$E18="FWD"),AY18,"") | BG18: 2 | BH18: 2 | BI18: 4 | BJ18: 6
A19: David Raya | B19: ARS | C19: ARS | D19: FALSE | E19: GKP | F19: GKP | G19: TRUE | H19: 6 | I19: a | K19: 3330 | L19: 162 | M19: 3385 | N19: 3385 | O19: 0 | Q19: flat | R19: 3385 | S19: Solio | U19: 90 | V19: 37 | W19: =IF(N(U19)<=0,0,MIN(Assumptions!$B$15,N(R19)/N(U19))) | X19: 0.391 | Y19: 0 | Z19: adjusted xGOT | AA19: 1 | AB19: 0.986 | AC19: 0.1 | AD19: 0.003 | AE19: 0 | AF19: 0 | AG19: 0.2973 | AH19: 74 | AI19: 2.067 | AJ19: 0.9838 | AK19: -0.056840825 | AL19: 0 | AM19: 2.0788133 | AN19: 0 | AO19: 0.01188 | AP19: =N(X19)*N(BI19) | AQ19: 0.2973 | AR19: 0.36085975 | AS19: -0.27684799 | AT19: -0.056840825 | AU19: =SUM(AN19:AT19) | AV19: =IF(OR(N(W19)<=0,N(BG19)=0),0,N(W19)*IF(N(R19)/N(W19)>=60,N(BG19),1)) | AW19: =N(W19)*N(AF19)*N(BH19) | AX19: =N(AL19)*(Assumptions!$B$13*N(BJ19)-(1-Assumptions!$B$13)*Assumptions!$B$14)+N(AM19) | AY19: =N(AU19)*N(R19)/90+N(AV19)+N(AW19)+N(AX19) | AZ19: =IF(N(R19)<=0,0,(N(AY19)-N(AX19))*90/N(R19)) | BA19: =IFERROR(AY19-VLOOKUP($E19,Assumptions!$A$40:$C$43,3,FALSE),"") | BB19: =IFERROR(BA19/H19,"") | BC19: =IF(AND($G19=TRUE,$E19="GKP"),AY19,"") | BD19: =IF(AND($G19=TRUE,$E19="DEF"),AY19,"") | BE19: =IF(AND($G19=TRUE,$E19="MID"),AY19,"") | BF19: =IF(AND($G19=TRUE,$E19="FWD"),AY19,"") | BG19: 2 | BH19: 0 | BI19: 4 | BJ19: 10
A20: Dominik Szoboszlai | B20: LIV | C20: LIV | D20: FALSE | E20: MID | F20: MID | G20: TRUE | H20: 7 | I20: a | K20: 3232 | L20: 160 | M20: 3344 | N20: 3344 | O20: 0 | Q20: flat | R20: 3344 | S20: Solio | U20: 87.6 | V20: 35 | W20: =IF(N(U20)<=0,0,MIN(Assumptions!$B$15,N(R20)/N(U20))) | X20: 0.342 | Y20: 0.0886 | Z20: adjusted xGOT | AA20: 0.839 | AB20: 0.797 | AC20: 15.3 | AD20: 0.2181 | AE20: 9.26 | AF20: 0.19826118 | AG20: 0.5848 | AH20: 72 | AI20: 2.409 | AJ20: 1.1228 | AK20: -0.21183569 | AL20: 2.1659719 | AM20: 0 | AN20: 0.443 | AO20: 0.863676 | AP20: =N(X20)*N(BI20) | AQ20: 0.5848 | AR20: 0 | AS20: 0 | AT20: -0.21183569 | AU20: =SUM(AN20:AT20) | AV20: =IF(OR(N(W20)<=0,N(BG20)=0),0,N(W20)*IF(N(R20)/N(W20)>=60,N(BG20),1)) | AW20: =N(W20)*N(AF20)*N(BH20) | AX20: =N(AL20)*(Assumptions!$B$13*N(BJ20)-(1-Assumptions!$B$13)*Assumptions!$B$14)+N(AM20) | AY20: =N(AU20)*N(R20)/90+N(AV20)+N(AW20)+N(AX20) | AZ20: =IF(N(R20)<=0,0,(N(AY20)-N(AX20))*90/N(R20)) | BA20: =IFERROR(AY20-VLOOKUP($E20,Assumptions!$A$40:$C$43,3,FALSE),"") | BB20: =IFERROR(BA20/H20,"") | BC20: =IF(AND($G20=TRUE,$E20="GKP"),AY20,"") | BD20: =IF(AND($G20=TRUE,$E20="DEF"),AY20,"") | BE20: =IF(AND($G20=TRUE,$E20="MID"),AY20,"") | BF20: =IF(AND($G20=TRUE,$E20="FWD"),AY20,"") | BG20: 2 | BH20: 2 | BI20: 1 | BJ20: 5
A21: Nico O'Reilly | B21: MCI | C21: MCI | D21: FALSE | E21: DEF | F21: DEF | G21: TRUE | H21: 6.5 | I21: a | K21: 2643 | L21: 160 | M21: 2753 | N21: 2753 | O21: 0 | Q21: flat | R21: 2753 | S21: Solio | U21: 86.3 | V21: 29 | W21: =IF(N(U21)<=0,0,MIN(Assumptions!$B$15,N(R21)/N(U21))) | X21: 0.371 | Y21: 0.2165 | Z21: adjusted xGOT | AA21: 1 | AB21: 1.039 | AC21: 7.4 | AD21: 0.111 | AE21: 6.248 | AF21: 0.083315307 | AG21: 0.3746 | AH21: 62 | AI21: 1.9737 | AJ21: 1.0365 | AK21: -0.18354238 | AL21: 0 | AM21: 0 | AN21: 1.299 | AO21: 0.43956 | AP21: =N(X21)*N(BI21) | AQ21: 0.3746 | AR21: 0 | AS21: -0.29970195 | AT21: -0.18354238 | AU21: =SUM(AN21:AT21) | AV21: =IF(OR(N(W21)<=0,N(BG21)=0),0,N(W21)*IF(N(R21)/N(W21)>=60,N(BG21),1)) | AW21: =N(W21)*N(AF21)*N(BH21) | AX21: =N(AL21)*(Assumptions!$B$13*N(BJ21)-(1-Assumptions!$B$13)*Assumptions!$B$14)+N(AM21) | AY21: =N(AU21)*N(R21)/90+N(AV21)+N(AW21)+N(AX21) | AZ21: =IF(N(R21)<=0,0,(N(AY21)-N(AX21))*90/N(R21)) | BA21: =IFERROR(AY21-VLOOKUP($E21,Assumptions!$A$40:$C$43,3,FALSE),"") | BB21: =IFERROR(BA21/H21,"") | BC21: =IF(AND($G21=TRUE,$E21="GKP"),AY21,"") | BD21: =IF(AND($G21=TRUE,$E21="DEF"),AY21,"") | BE21: =IF(AND($G21=TRUE,$E21="MID"),AY21,"") | BF21: =IF(AND($G21=TRUE,$E21="FWD"),AY21,"") | BG21: 2 | BH21: 2 | BI21: 4 | BJ21: 6
A22: James Garner | B22: EVE | C22: EVE | D22: FALSE | E22: MID | F22: MID | G22: TRUE | H22: 6 | I22: i | J22: Groin injury - Expected back 22 Aug | K22: 3413 | L22: 159 | M22: 3310 | N22: 2850 | O22: -460 | P22: medium | Q22: flat | R22: 2850 | S22: research | T22: Solio's second-highest Everton projection for a player who has had groin surgery and has not played a minute of pre-season. Read Everton's injury tracker on 14 August: 'Still recovering from groin surgery and has missed every pre-season friendly so far. Now genuinely up against it to be involved for the start of the league season.' The official FPL game lists him status 'i' with a 0% chance of playing and an expected return of 22 August - the day of the Crystal Palace opener itself. He is still the closest thing Everton have to a nailed central midfielder, so the cut is a month of games plus a re-integration allowance, not a re-rating. | U22: 87.8 | V22: 38 | W22: =IF(N(U22)<=0,0,MIN(Assumptions!$B$15,N(R22)/N(U22))) | X22: 0.231 | Y22: 0.0507 | Z22: adjusted xGOT | AA22: 1 | AB22: 0.916 | AC22: 6.1 | AD22: 0.1615 | AE22: 11.468 | AF22: 0.4431252 | AG22: 0.3164 | AH22: 76 | AI22: 3.0311 | AJ22: 1.5252 | AK22: -0.28622808 | AL22: 0.079305551 | AM22: 0 | AN22: 0.2535 | AO22: 0.63954 | AP22: =N(X22)*N(BI22) | AQ22: 0.3164 | AR22: 0 | AS22: 0 | AT22: -0.28622808 | AU22: =SUM(AN22:AT22) | AV22: =IF(OR(N(W22)<=0,N(BG22)=0),0,N(W22)*IF(N(R22)/N(W22)>=60,N(BG22),1)) | AW22: =N(W22)*N(AF22)*N(BH22) | AX22: =N(AL22)*(Assumptions!$B$13*N(BJ22)-(1-Assumptions!$B$13)*Assumptions!$B$14)+N(AM22) | AY22: =N(AU22)*N(R22)/90+N(AV22)+N(AW22)+N(AX22) | AZ22: =IF(N(R22)<=0,0,(N(AY22)-N(AX22))*90/N(R22)) | BA22: =IFERROR(AY22-VLOOKUP($E22,Assumptions!$A$40:$C$43,3,FALSE),"") | BB22: =IFERROR(BA22/H22,"") | BC22: =IF(AND($G22=TRUE,$E22="GKP"),AY22,"") | BD22: =IF(AND($G22=TRUE,$E22="DEF"),AY22,"") | BE22: =IF(AND($G22=TRUE,$E22="MID"),AY22,"") | BF22: =IF(AND($G22=TRUE,$E22="FWD"),AY22,"") | BG22: 2 | BH22: 2 | BI22: 1 | BJ22: 5
A23: Enzo Fernández | B23: CHE | C23: CHE | D23: FALSE | E23: MID | F23: MID | G23: TRUE | H23: 7 | I23: a | K23: 3114 | L23: 157 | M23: 3146 | N23: 2800 | O23: -346 | P23: medium | Q23: flat | R23: 2800 | S23: research | T23: Trimmed from 92% of every available minute. He was a substitute, not a starter, in the final pre-season friendly - the XI Last Word on Football calls 'likely the strongest XI for the start of the league campaign' - with captain Reece James starting the pivot alongside Caicedo after Enzo's late return from the World Cup final. He also carries live exit interest (Real Madrid; Chelsea asking around EUR 140m, rated 'Low' likelihood). Still projected as a heavy-minutes starter, just not an ever-present. | U23: 86.2 | V23: 35 | W23: =IF(N(U23)<=0,0,MIN(Assumptions!$B$15,N(R23)/N(U23))) | X23: 0.322 | Y23: 0.3008 | Z23: adjusted xGOT | AA23: 0.872 | AB23: 1.06 | AC23: 24 | AD23: 0.233 | AE23: 7.338 | AF23: 0.054632507 | AG23: 0.5491 | AH23: 71 | AI23: 2.4232 | AJ23: 1.1851 | AK23: -0.27640822 | AL23: 0.84358229 | AM23: 0 | AN23: 1.504 | AO23: 0.92268 | AP23: =N(X23)*N(BI23) | AQ23: 0.5491 | AR23: 0 | AS23: 0 | AT23: -0.27640822 | AU23: =SUM(AN23:AT23) | AV23: =IF(OR(N(W23)<=0,N(BG23)=0),0,N(W23)*IF(N(R23)/N(W23)>=60,N(BG23),1)) | AW23: =N(W23)*N(AF23)*N(BH23) | AX23: =N(AL23)*(Assumptions!$B$13*N(BJ23)-(1-Assumptions!$B$13)*Assumptions!$B$14)+N(AM23) | AY23: =N(AU23)*N(R23)/90+N(AV23)+N(AW23)+N(AX23) | AZ23: =IF(N(R23)<=0,0,(N(AY23)-N(AX23))*90/N(R23)) | BA23: =IFERROR(AY23-VLOOKUP($E23,Assumptions!$A$40:$C$43,3,FALSE),"") | BB23: =IFERROR(BA23/H23,"") | BC23: =IF(AND($G23=TRUE,$E23="GKP"),AY23,"") | BD23: =IF(AND($G23=TRUE,$E23="DEF"),AY23,"") | BE23: =IF(AND($G23=TRUE,$E23="MID"),AY23,"") | BF23: =IF(AND($G23=TRUE,$E23="FWD"),AY23,"") | BG23: 2 | BH23: 2 | BI23: 1 | BJ23: 5
A24: Bukayo Saka | B24: ARS | C24: ARS | D24: FALSE | E24: MID | F24: MID | G24: TRUE | H24: 9.5 | I24: a | K24: 2218 | L24: 157 | M24: 2827 | N24: 2827 | O24: 0 | Q24: flat | R24: 2827 | S24: Solio | U24: 81.7 | V24: 25 | W24: =IF(N(U24)<=0,0,MIN(Assumptions!$B$15,N(R24)/N(U24))) | X24: 0.391 | Y24: 0.2699 | Z24: adjusted xGOT | AA24: 0.913 | AB24: 0.963 | AC24: 41.3 | AD24: 0.3188 | AE24: 7.738 | AF24: 0.054458782 | AG24: 0.6492 | AH24: 54 | AI24: 2.067 | AJ24: 0.9838 | AK24: -0.14854432 | AL24: 5.4873508 | AM24: 0 | AN24: 1.3495 | AO24: 1.262448 | AP24: =N(X24)*N(BI24) | AQ24: 0.6492 | AR24: 0 | AS24: 0 | AT24: -0.14854432 | AU24: =SUM(AN24:AT24) | AV24: =IF(OR(N(W24)<=0,N(BG24)=0),0,N(W24)*IF(N(R24)/N(W24)>=60,N(BG24),1)) | AW24: =N(W24)*N(AF24)*N(BH24) | AX24: =N(AL24)*(Assumptions!$B$13*N(BJ24)-(1-Assumptions!$B$13)*Assumptions!$B$14)+N(AM24) | AY24: =N(AU24)*N(R24)/90+N(AV24)+N(AW24)+N(AX24) | AZ24: =IF(N(R24)<=0,0,(N(AY24)-N(AX24))*90/N(R24)) | BA24: =IFERROR(AY24-VLOOKUP($E24,Assumptions!$A$40:$C$43,3,FALSE),"") | BB24: =IFERROR(BA24/H24,"") | BC24: =IF(AND($G24=TRUE,$E24="GKP"),AY24,"") | BD24: =IF(AND($G24=TRUE,$E24="DEF"),AY24,"") | BE24: =IF(AND($G24=TRUE,$E24="MID"),AY24,"") | BF24: =IF(AND($G24=TRUE,$E24="FWD"),AY24,"") | BG24: 2 | BH24: 2 | BI24: 1 | BJ24: 5
A25: Maxence Lacroix | B25: CHE | C25: CRY | D25: TRUE | E25: DEF | F25: DEF | G25: TRUE | H25: 6 | I25: a | K25: 3085 | L25: 154 | M25: 2189 | N25: 2189 | O25: 0 | Q25: flat | R25: 2189 | S25: Solio | U25: 88.3 | V25: 34 | W25: =IF(N(U25)<=0,0,MIN(Assumptions!$B$15,N(R25)/N(U25))) | X25: 0.322 | Y25: 0.0574 | Z25: adjusted xGOT | AA25: 1 | AB25: 0.803 | AC25: 6 | AD25: 0.0309 | AE25: 10.206 | AF25: 0.54372314 | AG25: 0.3501 | AH25: 69 | AI25: 2.4232 | AJ25: 1.1851 | AK25: -0.16100232 | AL25: 0 | AM25: 0 | AN25: 0.3444 | AO25: 0.122364 | AP25: =N(X25)*N(BI25) | AQ25: 0.3501 | AR25: 0 | AS25: -0.36591551 | AT25: -0.16100232 | AU25: =SUM(AN25:AT25) | AV25: =IF(OR(N(W25)<=0,N(BG25)=0),0,N(W25)*IF(N(R25)/N(W25)>=60,N(BG25),1)) | AW25: =N(W25)*N(AF25)*N(BH25) | AX25: =N(AL25)*(Assumptions!$B$13*N(BJ25)-(1-Assumptions!$B$13)*Assumptions!$B$14)+N(AM25) | AY25: =N(AU25)*N(R25)/90+N(AV25)+N(AW25)+N(AX25) | AZ25: =IF(N(R25)<=0,0,(N(AY25)-N(AX25))*90/N(R25)) | BA25: =IFERROR(AY25-VLOOKUP($E25,Assumptions!$A$40:$C$43,3,FALSE),"") | BB25: =IFERROR(BA25/H25,"") | BC25: =IF(AND($G25=TRUE,$E25="GKP"),AY25,"") | BD25: =IF(AND($G25=TRUE,$E25="DEF"),AY25,"") | BE25: =IF(AND($G25=TRUE,$E25="MID"),AY25,"") | BF25: =IF(AND($G25=TRUE,$E25="FWD"),AY25,"") | BG25: 2 | BH25: 2 | BI25: 4 | BJ25: 6
A26: Bruno Guimarães | B26: ARS | C26: NEW | D26: TRUE | E26: MID | F26: MID | G26: TRUE | H26: 7 | I26: a | K26: 2456 | L26: 154 | M26: 2816 | N26: 2816 | O26: 0 | Q26: flat | R26: 2816 | S26: Solio | U26: 86.1 | V26: 27 | W26: =IF(N(U26)<=0,0,MIN(Assumptions!$B$15,N(R26)/N(U26))) | X26: 0.391 | Y26: 0.1744 | Z26: adjusted xGOT | AA26: 0.769 | AB26: 1.107 | AC26: 17.7 | AD26: 0.1618 | AE26: 9.057 | AF26: 0.16570759 | AG26: 0.8062 | AH26: 56 | AI26: 2.067 | AJ26: 0.9838 | AK26: -0.22501786 | AL26: 0 | AM26: 0 | AN26: 0.872 | AO26: 0.640728 | AP26: =N(X26)*N(BI26) | AQ26: 0.8062 | AR26: 0 | AS26: 0 | AT26: -0.22501786 | AU26: =SUM(AN26:AT26) | AV26: =IF(OR(N(W26)<=0,N(BG26)=0),0,N(W26)*IF(N(R26)/N(W26)>=60,N(BG26),1)) | AW26: =N(W26)*N(AF26)*N(BH26) | AX26: =N(AL26)*(Assumptions!$B$13*N(BJ26)-(1-Assumptions!$B$13)*Assumptions!$B$14)+N(AM26) | AY26: =N(AU26)*N(R26)/90+N(AV26)+N(AW26)+N(AX26) | AZ26: =IF(N(R26)<=0,0,(N(AY26)-N(AX26))*90/N(R26)) | BA26: =IFERROR(AY26-VLOOKUP($E26,Assumptions!$A$40:$C$43,3,FALSE),"") | BB26: =IFERROR(BA26/H26,"") | BC26: =IF(AND($G26=TRUE,$E26="GKP"),AY26,"") | BD26: =IF(AND($G26=TRUE,$E26="DEF"),AY26,"") | BE26: =IF(AND($G26=TRUE,$E26="MID"),AY26,"") | BF26: =IF(AND($G26=TRUE,$E26="FWD"),AY26,"") | BG26: 2 | BH26: 2 | BI26: 1 | BJ26: 5
A27: Matheus Nunes | B27: MCI | C27: MCI | D27: FALSE | E27: DEF | F27: DEF | G27: TRUE | H27: 6 | I27: a | K27: 2861 | L27: 154 | M27: 2896 | N27: 2896 | O27: 0 | Q27: flat | R27: 2896 | S27: Solio | U27: 86.8 | V27: 32 | W27: =IF(N(U27)<=0,0,MIN(Assumptions!$B$15,N(R27)/N(U27))) | X27: 0.371 | Y27: 0.0105 | Z27: adjusted xGOT | AA27: 1 | AB27: 0.98 | AC27: 4.8 | AD27: 0.0838 | AE27: 6.446 | AF27: 0.099656715 | AG27: 0.5033 | AH27: 64 | AI27: 1.9737 | AJ27: 1.0365 | AK27: -0.18622477 | AL27: 0.0076126737 | AM27: 0 | AN27: 0.063 | AO27: 0.331848 | AP27: =N(X27)*N(BI27) | AQ27: 0.5033 | AR27: 0 | AS27: -0.29970195 | AT27: -0.18622477 | AU27: =SUM(AN27:AT27) | AV27: =IF(OR(N(W27)<=0,N(BG27)=0),0,N(W27)*IF(N(R27)/N(W27)>=60,N(BG27),1)) | AW27: =N(W27)*N(AF27)*N(BH27) | AX27: =N(AL27)*(Assumptions!$B$13*N(BJ27)-(1-Assumptions!$B$13)*Assumptions!$B$14)+N(AM27) | AY27: =N(AU27)*N(R27)/90+N(AV27)+N(AW27)+N(AX27) | AZ27: =IF(N(R27)<=0,0,(N(AY27)-N(AX27))*90/N(R27)) | BA27: =IFERROR(AY27-VLOOKUP($E27,Assumptions!$A$40:$C$43,3,FALSE),"") | BB27: =IFERROR(BA27/H27,"") | BC27: =IF(AND($G27=TRUE,$E27="GKP"),AY27,"") | BD27: =IF(AND($G27=TRUE,$E27="DEF"),AY27,"") | BE27: =IF(AND($G27=TRUE,$E27="MID"),AY27,"") | BF27: =IF(AND($G27=TRUE,$E27="FWD"),AY27,"") | BG27: 2 | BH27: 2 | BI27: 4 | BJ27: 6
